Workbook
Name Slicer_Cell_Group: #REF!
Name Slicer_Cell_Group1: #REF!
Name Slicer_City_Address21: #REF!
Name Slicer_Cell_Group2: #REF!
Name Slicer_City_Address3: #REF!
Name Slicer_Department: #REF!
Name Slicer_City_Address1: #REF!
Name Slicer_City_Address: #REF!
Name Slicer_City_Address2: #REF!

Sheet Summary
B2: CHURCH MEMBERS PROFILING (Summary)
B5: TOTAL HEADCOUNT
B7: LM | C7: =COUNTA(LM!$K$5:$K$298) -> 183
B8: AMM | C8: =COUNTA(AMM!$K$5:$K$299) -> 76
B9: YOUTH | C9: =COUNTA(Youth!K5:K401) -> 192
B10: CHILDREN | C10: =COUNTA(Childrens!J5:J1001) -> 19
C11: =SUM(C7:C10) -> 470
C14: PROFILING FORM
C15: YES | D15: NO
B16: LM | C16: =COUNTIF(LM!$D$5:$D$298,"YES") -> 106 | D16: =COUNTIF(LM!$D$5:$D$298,"NO") -> 77 | E16: =C16+D16 -> 183
B17: AMM | C17: =COUNTIF(AMM!$D$5:$D$299,"YES") -> 49 | D17: =COUNTIF(AMM!$D$5:$D$299,"NO") -> 27 | E17: =C17+D17 -> 76
B18: YOUTH | C18: =COUNTIF(Youth!$D$5:$D$401,"YES") -> 90 | D18: =COUNTIF(Youth!$D$5:$D$401,"NO") -> 102 | E18: =C18+D18 -> 192
B19: CHILDREN

Sheet LM
A1: LADIES MINISTRIES DEPARTMENT
A3: Count per filter | B3: =SUBTOTAL(3,LM!$K$5:$K$298) -> 183
D4: With Profiling Forn | E4: Status | F4: Cell Group | G4: Age Group | H4: CG Position | I4: Full Name (Last, First) | J4: Last Name | K4: First Name | L4: Middle Initial | M4: Gender | N4: Street | O4: City Address | P4: Provincial Address | Q4: Contact Number | R4: Email | S4: Birthdate | T4: Age | U4: Birthplace | V4: Father | W4: Mother | X4: Baptized in Water | Y4: Date | Z4: Baptized in Holy Ghost | AA4: Date2 | AB4: Former Religious Affiliation | AC4: Educational Attaintment | AD4: Current Occupation | AE4: Church ministries (Present) | AF4: Church ministries (Past) | AG4: Personal skills | AH4: Sports Interest | AI4: Other skills | AJ4: Spouse Name | AK4: Spouse Occupation | AL4: Is you spouse a believer? | AM4: Do both of you attend the same church? | AN4: Emergency Contact | AO4: Address | AP4: Relationship | AQ4: Contact Number2
D5: Yes | F5: Palm | H5: Secretary | I5: =IF(AND(K5="",J5=""),"",CONCATENATE(J5,", ",K5)) -> Abuan, Christine | J5: Abuan | K5: Christine | L5: Villamin | M5: Female | N5: 14 Purok 8 Upper Km 5 | O5: Asin Road | P5: Paniqui, Tarlac | Q5: 0927-393-4928 | R5: cmvillamin.11@gmail.com | S5: 33970 | T5: =IF(S5="","",DATEDIF(S5,TODAY(),"Y")) -> 33 | U5: Quezon City | V5: Villamin, Martin Labasan | W5: Villamin, Irene Macadangdang | X5: Yes | Y5: November 11, 2009 | Z5: Yes | AA5: December 26, 2009 | AC5: College Level | AD5: Accountant | AE5: Music Ministry - Choir, Bible Quizzing Commission | AF5: Teaching, Music Ministry - Choir, Youth and Church Leader | AH5: Table Tennis | AJ5: Abuan, Jomar Caballero | AK5: Virtual Assistant | AL5: Yes | AM5: Yes | AN5: Abuan, Jomar | AO5: 14 Purok 8 Upper Km 5, Asin Rd | AP5: Spouse | AQ5: 0946-168-8476
D6: No | F6: Almond | H6: Member | I6: =IF(AND(K6="",J6=""),"",CONCATENATE(J6,", ",K6)) -> Abuan, Maria Fe | J6: Abuan | K6: Maria Fe | L6: Caballero | M6: Female | N6: 14 Purok 8 Upper Km 5 | O6: Asin Road | Q6: 0910-944-4093 | S6: 22531 | T6: =IF(S6="","",DATEDIF(S6,TODAY(),"Y")) -> 65
D7: No | F7: Juniper | H7: Member | I7: =IF(AND(K7="",J7=""),"",CONCATENATE(J7,", ",K7)) -> Akiapat, Felipa | J7: Akiapat | K7: Felipa | M7: Female | N7: MD 212 Longlong | O7: Puguis, La Trinidad | Q7: 0949-370-2539 | S7: 20718 | T7: =IF(S7="","",DATEDIF(S7,TODAY(),"Y")) -> 70
D8: Yes | F8: Acacia | H8: Leader | I8: =IF(AND(K8="",J8=""),"",CONCATENATE(J8,", ",K8)) -> Alarcio, Grace | J8: Alarcio | K8: Grace | M8: Female | N8: 11 Purok 8 Sampaguita Site | O8: San Luis Village | Q8: 0910-882-0715 | S8: 28065 | T8: =IF(S8="","",DATEDIF(S8,TODAY(),"Y")) -> 49 | U8: Ilocos Sur | V8: Aquino, Samuel | W8: Cofolan, Virginia | X8: Yes | Y8: December 1998 | Z8: Yes | AA8: December 1998 | AB8: Assembly of God | AC8: Vocational Course | AD8: Vendor | AE8: LM Cellgroup Secretary | AF8: Ushering Secretary | AI8: Tailoring | AJ8: Alarcio, Marcial | AK8: Driver | AL8: Yes | AM8: Yes | AN8: Alarcio, Marcial | AO8: 11 Purok 8 Sampaguita Site San Luis Village | AP8: Spouse | AQ8: 0950-516-2515
D9: Yes | F9: Acacia | H9: Member | I9: =IF(AND(K9="",J9=""),"",CONCATENATE(J9,", ",K9)) -> Alarcio, Kaye Cee | J9: Alarcio | K9: Kaye Cee | L9: D | M9: Female | N9: 11 Purok 8 Sampaguita Site | O9: San Luis Village | Q9: 0948-589-8500 | R9: kayeceedangca@gmail.com | S9: 35948 | T9: =IF(S9="","",DATEDIF(S9,TODAY(),"Y")) -> 28 | U9: Rosario, La Union | V9: Dangca, Edgardo | W9: Dangca, Tessie | X9: Yes | Y9: 2025 | Z9: Yes | AA9: February 23, 2025 | AB9: Roman Catholic | AC9: College Level | AD9: Vendor | AJ9: Alarcio, Laurence | AK9: Vendor | AL9: Yes | AM9: Yes | AN9: Alarcio, Laurence | AO9: Baguio City | AP9: Spouse | AQ9: 0963-888-1378
D10: Yes | F10: Cedar | H10: Assistant Leader | I10: =IF(AND(K10="",J10=""),"",CONCATENATE(J10,", ",K10)) -> Alcoriza, Jocelyn | J10: Alcoriza | K10: Jocelyn | M10: Female | O10: Goldfield, Itogon | Q10: 0946-625-8081 | S10: 27167 | T10: =IF(S10="","",DATEDIF(S10,TODAY(),"Y")) -> 52 | U10: Goldfield | V10: Estoe, Rudy | W10: Estoe, Teodora | X10: Yes | Y10: --- 19, 1994 | Z10: Yes | AA10: --- 19, 1994 | AJ10: Alcoriza, Reynaldo | AK10: Taxi Driver | AL10: Yes | AM10: Yes | AN10: Bentrez, Genera | AO10: Goldfield Itogon | AP10: Auntie
D11: Yes | F11: Almond | H11: Leader | I11: =IF(AND(K11="",J11=""),"",CONCATENATE(J11,", ",K11)) -> Aleo, Nena | J11: Aleo | K11: Nena | M11: Female | N11: AP 06B | O11: Ambiong Central, La Trinidad | Q11: 0949-820-4911 | S11: 20294 | T11: =IF(S11="","",DATEDIF(S11,TODAY(),"Y")) -> 71 | U11: Sagada Mt. Province | V11: Mastere, Eduardo | W11: Mastere, Neno Ogues | X11: Yes | Y11: August 1999 | Z11: Yes | AB11: Anglican | AC11: B.S. Commerce | AD11: Housewife | AG11: Photography, Gardening | AH11: Volleyball | AI11: Cooking | AJ11: Aleo, Alexander | AK11: Retired Military Officer | AL11: Not Yet | AN11: Aleo, Alexander | AO11: AP 06B Ambiong Central | AP11: Spouse
D12: Yes | F12: Almond | H12: Member | I12: =IF(AND(K12="",J12=""),"",CONCATENATE(J12,", ",K12)) -> Amistad, Hadassah Olive | J12: Amistad | K12: Hadassah Olive | L12: C | M12: Female | N12: 7 Purok 1 | O12: Irisan | Q12: 0946-457-5445 | R12: lovedatsima@gmail.com | S12: 31028 | T12: =IF(S12="","",DATEDIF(S12,TODAY(),"Y")) -> 41 | U12: Olongapo City | V12: Castro, Simplicio Jr. | W12: Castro, Rizalina | X12: Yes | Y12: November 1998 | Z12: Yes | AA12: December 1998 | AC12: College Undergrad | AE12: Children's Ministries | AF12: Ushering | AG12: Teaching, Arts and Deco, Baking | AH12: Volleyball | AI12: Cooking | AJ12: Amistad, Joseph Sinesin | AK12: Virtual Assistant | AL12: Yes | AM12: Yes | AN12: Amistad, Joseph Sinesin | AO12: 7 Purok 1 Irisan | AP12: Spouse | AQ12: 0918-502-8785
D13: No | F13: Sycamore | H13: Member | I13: =IF(AND(K13="",J13=""),"",CONCATENATE(J13,", ",K13)) -> Amistad, Jolie Mae | J13: Amistad | K13: Jolie Mae | M13: Female | T13: =IF(S13="","",DATEDIF(S13,TODAY(),"Y"))
D14: Yes | I14: =IF(AND(K14="",J14=""),"",CONCATENATE(J14,", ",K14)) -> Amplogio, Gina | J14: Amplogio | K14: Gina | L14: Odalio | M14: Female | N14: JB 51-G Capharan | O14: Pico, La Trinidad | R14: ginaamplogio4@gmail.com | S14: 24761 | T14: =IF(S14="","",DATEDIF(S14,TODAY(),"Y")) -> 59 | U14: Bauko, Mt. province | V14: Odalio, Carlos | W14: Odalio, Lolita | X14: Yes | Y14: 39371 | Z14: Yes | AB14: Roman Catholic | AC14: College Graduate | AD14: Self-employed | AG14: Teaching | AH14: Volleyball | AI14: Cooking | AJ14: Amplogio, Charlie | AK14: Self-employed | AL14: Yes | AM14: Yes | AN14: Naimes, Melecia | AO14: Lubas, La Trinidad | AP14: Sibling | AQ14: 0960-652-4642
D15: No | F15: Oak | H15: Member | I15: =IF(AND(K15="",J15=""),"",CONCATENATE(J15,", ",K15)) -> Ancheta, Jennylyn | J15: Ancheta | K15: Jennylyn | M15: Female | N15: 29 Avelino St | O15: Andres Bonifacio | Q15: 0945-094-6242 | S15: 22678 | T15: =IF(S15="","",DATEDIF(S15,TODAY(),"Y")) -> 64
D16: No | F16: Oak | H16: Member | I16: =IF(AND(K16="",J16=""),"",CONCATENATE(J16,", ",K16)) -> Andrada, Lolita | J16: Andrada | K16: Lolita | M16: Female | T16: =IF(S16="","",DATEDIF(S16,TODAY(),"Y"))
D17: Yes | F17: Sycamore | H17: Member | I17: =IF(AND(K17="",J17=""),"",CONCATENATE(J17,", ",K17)) -> Ano, Emiliana | J17: Ano | K17: Emiliana | L17: Cudlas | M17: Female | N17: 520 Purok 8 Badihoy St. | O17: Pinsao Proper | Q17: 0946-023-0167 | S17: 22090 | T17: =IF(S17="","",DATEDIF(S17,TODAY(),"Y")) -> 66 | U17: Burgos La Union | V17: Cudlas, Velasco Padilla | W17: Cayat, Marcelina Gacao | X17: Yes | Y17: June 28, 1998 | AB17: Roman Catholic | AC17: College Level | AD17: Personal Collection Dealer | AF17: LM Cellgroup Leader | AJ17: Ano, Albert Capuyan | AN17: Tagudin, Amie Ano | AO17: 520 Purok 8 Badihoy St. Pinsao Proper | AP17: Daughter
D18: Yes | F18: Almond | H18: Assistant Leader | I18: =IF(AND(K18="",J18=""),"",CONCATENATE(J18,", ",K18)) -> Apilada, Susan | J18: Apilada | K18: Susan | L18: B | M18: Female | N18: 057 Sitio Paltingan | O18: Ambiong, La Trinidad | P18: Tayug Pangasinan | Q18: 0935-997-6857 | S18: 23277 | T18: =IF(S18="","",DATEDIF(S18,TODAY(),"Y")) -> 63 | U18: Tayug Pangasinan | V18: Bermudez, Marcelo (+) | X18: Yes | Y18: February 2004 | Z18: Yes | AA18: March 2005 | AB18: Roman Catholic | AC18: High school level | AD18: Online selling direct | AI18: Cooking | AJ18: Apilada, Armando R. | AK18: Security Officer | AL18: Yes | AM18: Yes | AN18: Apilada, Armando R. | AO18: 057 Sitio Paltingan Ambiong La Trinidad | AP18: Spouse | AQ18: 0909-572-3317
D19: Yes | F19: Olive | H19: Member | I19: =IF(AND(K19="",J19=""),"",CONCATENATE(J19,", ",K19)) -> Aragon, Elaine Marie | J19: Aragon | K19: Elaine Marie | L19: W | M19: Female | N19: 8 De Tesis St | O19: Aurora Hill | Q19: 0994-157-8818 | S19: 33402 | T19: =IF(S19="","",DATEDIF(S19,TODAY(),"Y")) -> 35 | U19: Baguio City | V19: Wong, Benjamin Jr. | W19: Wong, Teofila | X19: Yes | Y19: July 14, 2000 | Z19: Yes | AC19: College Level | AD19: HR Officer at Good taste Otek | AE19: Music Ministry - Choir | AF19: Music Ministry - Choir, Youth adviser | AG19: Teaching, Singing | AH19: Volleyball | AI19: Cooking | AJ19: Aragon, Marc Andrew Revi | AK19: Dedurr Operator | AL19: Yes | AM19: Yes | AN19: Aragon, Marc Andrew Revi | AO19: 8 De Tesis St Aurora Hill | AP19: Spouse | AQ19: 0994-371-9691
D20: Yes | I20: =IF(AND(K20="",J20=""),"",CONCATENATE(J20,", ",K20)) -> Arcangel, Delia | J20: Arcangel | K20: Delia | L20: Larida | M20: Female | N20: Padre Zamora St Purok 2 | O20: Zamora St | P20: Negros Occidental | S20: 24473 | T20: =IF(S20="","",DATEDIF(S20,TODAY(),"Y")) -> 59 | U20: San Carlos Negros Occidental | V20: Larida, Hilardo Gripo | W20: Larida, Lovepta Cantojos | X20: Yes | Y20: March 13,2005 | Z20: Yes | AA20: September 18, 2005 | AB20: Protestant | AC20: Grade 2 | AD20: Beautician / Cooking | AG20: Singing | AH20: Basketball | AI20: Cooking, Tailoring | AJ20: Arcangel, Ramon Sr. | AL20: Not Yet | AM20: Not Yet | AN20: Mailare, Mona Jessica | AO20: Teachers Camp | AP20: Daughter
D21: No | F21: Mulberry | H21: Member | I21: =IF(AND(K21="",J21=""),"",CONCATENATE(J21,", ",K21)) -> Ayson, Cora | J21: Ayson | K21: Cora | M21: Female | T21: =IF(S21="","",DATEDIF(S21,TODAY(),"Y"))
D22: Yes | F22: Sycamore | H22: Member | I22: =IF(AND(K22="",J22=""),"",CONCATENATE(J22,", ",K22)) -> Ayungo, Ailene | J22: Ayungo | K22: Ailene | L22: Baydal | M22: Female | N22: 9 Tangerine Lane Avelino St. | O22: Fairview | P22: Antipolo Rizal | Q22: 0923-942-4149 / 0912-112-1123 | R22: ailenebaydal80@gmail.com | S22: 29483 | T22: =IF(S22="","",DATEDIF(S22,TODAY(),"Y")) -> 46 | U22: Putatan Muntinlupa Manila | V22: Baydal, Alejandro Mata | W22: Baydal, Evelyn España | X22: Yes | Z22: Yes | AC22: First year college | AD22: 4Life Research / Suntrust Properties Inc | AE22: Music Ministry - Choir | AF22: Music Ministry - Choir, Ushering | AG22: Arts and Deco, Photography | AH22: Volleyball | AI22: Cooking | AJ22: Ayungo, Martin Jr. | AK22: Personal driver, Project specialist | AL22: Yes | AM22: Yes | AN22: Ayungo, Martin Jr. | AO22: 9 Tangerine Lane Avelino St. Fairview | AP22: Spouse
D23: Yes | F23: Mulberry | H23: Member | I23: =IF(AND(K23="",J23=""),"",CONCATENATE(J23,", ",K23)) -> Bacsa, Hyneth Gwenn | J23: Bacsa | K23: Hyneth Gwenn | L23: B | M23: Female | N23: 048-B Boted | O23: Tawang, La Trinidad | Q23: 0967-301-6762 | R23: bryllevhien@gmail.com | S23: 37844 | T23: =IF(S23="","",DATEDIF(S23,TODAY(),"Y")) -> 23 | U23: La Trinidad Benguet | V23: Badilla, Brenson (+) | W23: Badilla, Beverly | X23: Yes | Z23: Yes | AC23: Tesda Graduate | AH23: Volleyball, Badminton | AI23: Baking | AJ23: Bacsa, Vhal | AL23: Yes | AM23: Not Yet | AN23: Badilla, Beverly | AO23: 048-B Boted Tawang La Trinidad | AP23: Mother
D24: Yes | F24: Pomegranate | H24: Assistant Leader | I24: =IF(AND(K24="",J24=""),"",CONCATENATE(J24,", ",K24)) -> Bagtilay, Lety | J24: Bagtilay | K24: Lety | M24: Female | N24: IC-121 KM 6 | O24: Betag, La Trinidad | Q24: 0912-190-4528 / 422-3285 | R24: letybagtilay9@gmail.com | S24: 22615 | T24: =IF(S24="","",DATEDIF(S24,TODAY(),"Y")) -> 64 | U24: Baguio City | V24: Mejia, Felix Sr. (+) | W24: Mejia, Virginia A (+) | X24: Yes | Y24: 40409 | Z24: Yes | AA24: 43784 | AB24: Roman Catholic | AC24: Secretarial Graduate | AE24: LM Cellgroup Assistant Leader | AG24: Singing | AJ24: Bagtilay, Jimmy (+) | AN24: Onalan, Milagros | AO24: IC-121 KM 6 Betag La Trinidad | AP24: Sister-in-law | AQ24: 0925-746-5573
D25: No | F25: Palm | H25: Member | I25: =IF(AND(K25="",J25=""),"",CONCATENATE(J25,", ",K25)) -> Balbino, Beverly | J25: Balbino | K25: Beverly | M25: Female | N25: Apugan | O25: Sto. Tomas | Q25: 0927-062-6427 | T25: =IF(S25="","",DATEDIF(S25,TODAY(),"Y"))
D26: No | F26: Sycamore | H26: Member | I26: =IF(AND(K26="",J26=""),"",CONCATENATE(J26,", ",K26)) -> Balinggan, Deborah | J26: Balinggan | K26: Deborah | M26: Female | T26: =IF(S26="","",DATEDIF(S26,TODAY(),"Y"))
D27: Yes | F27: Juniper | H27: Member | I27: =IF(AND(K27="",J27=""),"",CONCATENATE(J27,", ",K27)) -> Balinggan, Gene | J27: Balinggan | K27: Gene | M27: Female | N27: 154 BPI CPD | O27: Cresencia Village | P27: Shilan La Trinidad | Q27: 0939-918-6017 / 424-8932 | R27: gbalinggan@gmail.com | S27: 30952 | T27: =IF(S27="","",DATEDIF(S27,TODAY(),"Y")) -> 42 | U27: La Trinidad Benguet | V27: Tampoa, Rex | W27: Tampoa, Rufina | X27: Yes | Y27: December 2025 | Z27: Yes | AA27: 2006 | AB27: SDA | AC27: MA Psych | AD27: Instructor in UC | AG27: Teaching | AJ27: Balinggan, Jenkinson | AL27: Yes | AM27: Yes | AN27: Balinggan, Jenkinson | AO27: 154 BPI CPD Cresencia Village | AP27: Spouse | AQ27: 0939-918-6025
D28: No | F28: Oak | H28: Member | I28: =IF(AND(K28="",J28=""),"",CONCATENATE(J28,", ",K28)) -> Balinggan, Jubilee | J28: Balinggan | K28: Jubilee | L28: Bañez | M28: Female | N28: 154 BPI CPD | O28: Cresencia Village | Q28: 0998-988-8046 | S28: 31872 | T28: =IF(S28="","",DATEDIF(S28,TODAY(),"Y")) -> 39
D29: Yes | F29: Palm | H29: Member | I29: =IF(AND(K29="",J29=""),"",CONCATENATE(J29,", ",K29)) -> Balinggan, Mercedes | J29: Balinggan | K29: Mercedes | L29: Lucando | M29: Female | N29: Kabuyao | O29: Poblacion, Tuba | Q29: 0918-366-1587 | S29: 21269 | T29: =IF(S29="","",DATEDIF(S29,TODAY(),"Y")) -> 68 | U29: Kabuyao Pob. Tuba Benguet | V29: Lucando, Picoy (+) | W29: Lucando, Margarita (+) | X29: Yes | Z29: Yes | AB29: Roman Catholic | AC29: Midwifery Graduate | AE29: Church Elder | AF29: LM President | AH29: Volleyball | AJ29: Balinggan, Paul | AL29: Yes | AM29: Yes | AN29: Balinggan, Paul | AO29: Kabuyao Pob. Tuba Benguet | AP29: Spouse | AQ29: 0918-422-3882
D30: Yes | F30: Cedar | H30: Member | I30: =IF(AND(K30="",J30=""),"",CONCATENATE(J30,", ",K30)) -> Balneg, Rose | J30: Balneg | K30: Rose | L30: U | M30: Female | N30: Blk Lot 19B NHA | O30: Tadiangan, Tuba | Q30: 09219-75-9585 | S30: 26904 | T30: =IF(S30="","",DATEDIF(S30,TODAY(),"Y")) -> 53 | U30: Union, Madrid Surigao Del Sur | V30: Urbiztondo, Walfredo | W30: Urbiztondo, Pepita | X30: Yes | Y30: February 2, 2025 | AB30: Jesus is Lord | AI30: Cooking | AJ30: Balneg, Alfredo | AK30: Farmer | AL30: Yes | AM30: Yes | AN30: Balneg, Queen Crystalee | AO30: Blk Lot 19B NHA Housing | AP30: Daughter | AQ30: 0912-521-4964
D31: Yes | F31: Tamarisk | H31: Assistant Leader | I31: =IF(AND(K31="",J31=""),"",CONCATENATE(J31,", ",K31)) -> Bambao, Joanna | J31: Bambao | K31: Joanna | M31: Female | N31: 15 Balacbac Central | O31: Sto. Tomas Proper | S31: 29031 | T31: =IF(S31="","",DATEDIF(S31,TODAY(),"Y")) -> 47 | U31: Dagupan City, Pangasinan | V31: Caneng, Feliciano | W31: Caneng, Tomasa | X31: Yes | Y31: November 2, 2001 | Z31: Yes | AA31: June 1, 2002 | AB31: Roman Catholic | AC31: College Graduate | AJ31: Bambao, Angel Jr. | AK31: OFW | AL31: Yes | AM31: Yes | AN31: Bambao, Joanna / Bambao, KC | AO31: Balacbac | AP31: Spouse / Daughter | AQ31: 0912-186-2964 / 0969-386-4628
D32: No | F32: Hazelnut | H32: Secretary | I32: =IF(AND(K32="",J32=""),"",CONCATENATE(J32,", ",K32)) -> Banaag, Marjorie | J32: Banaag | K32: Marjorie | M32: Female | O32: Bakakeng Central | Q32: 0949-848-4774 | S32: 31130 | T32: =IF(S32="","",DATEDIF(S32,TODAY(),"Y")) -> 41
D33: No | F33: Tamarisk | H33: Member | I33: =IF(AND(K33="",J33=""),"",CONCATENATE(J33,", ",K33)) -> Bañares, Alicia Hafalla | J33: Bañares | K33: Alicia Hafalla | M33: Female | T33: =IF(S33="","",DATEDIF(S33,TODAY(),"Y"))
D34: No | F34: Sycamore | H34: Member | I34: =IF(AND(K34="",J34=""),"",CONCATENATE(J34,", ",K34)) -> Bañez, Gemma | J34: Bañez | K34: Gemma | M34: Female | T34: =IF(S34="","",DATEDIF(S34,TODAY(),"Y"))
D35: No | F35: Sycamore | H35: Member | I35: =IF(AND(K35="",J35=""),"",CONCATENATE(J35,", ",K35)) -> Bañez, Lucina | J35: Bañez | K35: Lucina | M35: Female | T35: =IF(S35="","",DATEDIF(S35,TODAY(),"Y"))
D36: No | F36: Almond | H36: Member | I36: =IF(AND(K36="",J36=""),"",CONCATENATE(J36,", ",K36)) -> Bangibang, Mila | J36: Bangibang | K36: Mila | M36: Female | N36: Block 21 NHA | O36: Tadiangan, Tuba | Q36: 0916-159-1002 | S36: 29953 | T36: =IF(S36="","",DATEDIF(S36,TODAY(),"Y")) -> 44
D37: Yes | F37: Pomegranate | H37: Member | I37: =IF(AND(K37="",J37=""),"",CONCATENATE(J37,", ",K37)) -> Bas-ilan, Benita | J37: Bas-ilan | K37: Benita | L37: B | M37: Female | N37: 048-B Boted | O37: Tawang, La Trinidad | Q37: 0909-576-2084 | S37: 21213 | T37: =IF(S37="","",DATEDIF(S37,TODAY(),"Y")) -> 68 | U37: Bangao, Buguias, Benguet | V37: Badilla, Pakito | W37: Badilla, Lumina | X37: Yes | Y37: November 18, 1998 | Z37: Yes | AA37: August 23, 1998 | AB37: Anglican | AC37: High school level | AI37: Cooking
D38: No | F38: Mulberry | H38: Member | I38: =IF(AND(K38="",J38=""),"",CONCATENATE(J38,", ",K38)) -> Batacan, Diane | J38: Batacan | K38: Diane | M38: Female | T38: =IF(S38="","",DATEDIF(S38,TODAY(),"Y"))
D39: No | F39: Cedar | H39: Member | I39: =IF(AND(K39="",J39=""),"",CONCATENATE(J39,", ",K39)) -> Bayla, Denise | J39: Bayla | K39: Denise | M39: Female | T39: =IF(S39="","",DATEDIF(S39,TODAY(),"Y"))
D40: Yes | F40: Cedar | H40: Member | I40: =IF(AND(K40="",J40=""),"",CONCATENATE(J40,", ",K40)) -> Bayla, Elizabeth | J40: Bayla | K40: Elizabeth | L40: L | M40: Female | N40: 27 Purok 4 | O40: Irisan | Q40: 0920-983-4258 | R40: elizabethbayla@gmail.com | S40: 25135 | T40: =IF(S40="","",DATEDIF(S40,TODAY(),"Y")) -> 58 | U40: Tuba, Benguet | V40: Lay-at, Samson Sr. | W40: Sugel, Francisca | X40: Yes | Y40: September 26, 1993 | Z40: Yes | AA40: September 26, 1993 | AB40: Roman Catholic | AC40: College Level | AD40: Athlete under PSC | AF40: Teaching, Bible Study | AG40: Teaching, Singing, Playing musical instrument, Literary Composition | AH40: Archery | AJ40: Bayla,Raigirando | AK40: OFW | AM40: Not Yet | AN40: Bayla, Kevin Anthony | AO40: 27 Purok 4 Irisan | AP40: Son | AQ40: 0927-765-1999
D41: Yes | I41: =IF(AND(K41="",J41=""),"",CONCATENATE(J41,", ",K41)) -> Bayla, Camile | J41: Bayla | K41: Camile | L41: F | M41: Female | N41: 27 Purok 4 | O41: Irisan | Q41: 0915-954-6909 | R41: sheethalfrigill@gmail.com | S41: 35100 | T41: =IF(S41="","",DATEDIF(S41,TODAY(),"Y")) -> 30 | U41: Baguio City | V41: Frigillana, Moreno | W41: Frigillana, Elizabeth | X41: Yes | Y41: 46102 | Z41: Yes | AA41: 46180 | AD41: Admin Officer - TESDA | AG41: Arts & Deco | AH41: Billiards | AI41: Welding | AJ41: Bayla, Eldrin Raig | AK41: Aircraft Mechanic | AL41: Yes | AM41: Yes | AN41: Bayla, Elrdin Raig | AO41: Same as home address | AP41: Spouse | AQ41: 0961-910-2180
D42: No | F42: Mulberry | H42: Member | I42: =IF(AND(K42="",J42=""),"",CONCATENATE(J42,", ",K42)) -> Belarmino, Ranelda | J42: Belarmino | K42: Ranelda | M42: Female | T42: =IF(S42="","",DATEDIF(S42,TODAY(),"Y"))
D43: Yes | I43: =IF(AND(K43="",J43=""),"",CONCATENATE(J43,", ",K43)) -> Belleza, Rosie | J43: Belleza | K43: Rosie | L43: O | M43: Female | N43: 53 Badihoy St | O43: Guisad Surong | P43: Blk 82 Lot 116 Area D Sapang Palay San Jose Del Monte City Bulacan | Q43: 0955-318-8513 | R43: iamrosiebee@gmail.com | S43: 26952 | T43: =IF(S43="","",DATEDIF(S43,TODAY(),"Y")) -> 53 | U43: Goa, Camarines Sur | V43: Belleza, Jaime B. (+) | W43: Belleza, Marita O. (+) | X43: Yes | Y43: March 4, 2004 | Z43: Yes | AA43: 2005 | AB43: Roman Catholic | AC43: High school level | AD43: Househelper | AF43: Singing, Song Lead, Back-up | AG43: Singing | AH43: Volleyball, Badminton | AI43: Cooking | AJ43: Castillo, Antonino B. | AL43: Yes | AM43: Yes | AN43: Yap, Erson | AO43: Mrr. Queen of Peace, Baguio | AP43: Son
D44: Yes | F44: Mulberry | H44: Member | I44: =IF(AND(K44="",J44=""),"",CONCATENATE(J44,", ",K44)) -> Bentrez, Genera | J44: Bentrez | K44: Genera | L44: Salve | M44: Female | N44: 354 Goldfield | O44: Poblacion, Itogon | Q44: 0929-182-0905 | S44: 21466 | T44: =IF(S44="","",DATEDIF(S44,TODAY(),"Y")) -> 68 | U44: Ucab, Itogon | V44: Salve, Anastacio (+) | W44: Salve, Beatriz Balacdan | X44: Yes | Y44: November 8, 1981 | Z44: Yes | AA44: September 1982 | AB44: UCCP | AC44: High school level | AE44: Church Elder | AF44: LM President, Sunday School Teacher (Beginner Class) | AG44: Singing, Playing Musical instruments | AH44: Volleyball | AI44: Cooking | AJ44: Bentrez, Larry (+) | AL44: Yes | AM44: Yes | AN44: Bentrez, Isaac | AO44: 123 Blk 3 Middle Quirino Hill | AP44: Son | AQ44: 0977-822-5999
D45: Yes | F45: Juniper | H45: Member | I45: =IF(AND(K45="",J45=""),"",CONCATENATE(J45,", ",K45)) -> Bentrez, Jacqueline | J45: Bentrez | K45: Jacqueline | L45: R | M45: Female | N45: 123 Blk 3 | O45: Middle Quirino Hill | Q45: 0927-211-0251 | R45: jacquelinebentrez2016@gmail.com | S45: 29570 | T45: =IF(S45="","",DATEDIF(S45,TODAY(),"Y")) -> 45 | U45: Floridablanca Pampanga | V45: Regala, Pablo | W45: Regala, Emie | X45: Yes | Z45: Yes | AC45: BEED | AE45: CM Directress | AG45: Teaching, Arts and Deco | AI45: Cooking | AJ45: Bentrez, Isaac | AK45: Teacher | AL45: Yes | AM45: Yes | AN45: Bentrez, Isaac | AO45: 123 Blk 3 Middle Quirino Hill | AP45: Spouse | AQ45: 0977-822-5999
D46: Yes | F46: Sycamore | H46: Secretary | I46: =IF(AND(K46="",J46=""),"",CONCATENATE(J46,", ",K46)) -> Bokket, Maria Rita | J46: Bokket | K46: Maria Rita | L46: B | M46: Female | N46: 134 Blk 2 | O46: East Quirino Hill | Q46: 0930-185-7642 | S46: 30786 | T46: =IF(S46="","",DATEDIF(S46,TODAY(),"Y")) -> 42 | U46: San Esteban Pilar Capiz | V46: Bacanto, Isedro | W46: Bacanto, Josepina | X46: Yes | Y46: 2009 | Z46: Yes | AB46: Roman Catholic | AC46: Elementary | AD46: Weaving | AE46: Sunday School Teacher, LM Secretary | AF46: Sunday School Teacher, LM Secretary | AG46: Teaching | AJ46: Bokket, Victor | AK46: Truck Driver | AL46: Not Yet | AM46: Not Yet | AN46: Bokket, Victor | AO46: 134 Blk 2 East Quirino Hill | AP46: Spouse | AQ46: 0948-713-3512
D47: Yes | F47: Olive | H47: Member | I47: =IF(AND(K47="",J47=""),"",CONCATENATE(J47,", ",K47)) -> Boteng, Angeline | J47: Boteng | K47: Angeline | M47: Female | N47: FC 323 | O47: Central Balili, La Trinidad | Q47: 0928-412-5014 | R47: anzeraf@gmail.com | S47: 29829 | T47: =IF(S47="","",DATEDIF(S47,TODAY(),"Y")) -> 45 | U47: Tuba, Benguet | V47: Boteng, Jaime | W47: Boteng, Sofia | X47: Yes | Y47: June 1997 | Z47: Yes | AB47: Anglican | AC47: Post Graduate | AD47: Teacher - DepEd | AF47: Music Ministry - Choir, Sunday School Teacher | AG47: Teaching | AH47: Volleyball, Badminton | AI47: Cooking | AN47: Boteng, Jaime | AO47: FC 323 Central Balili, La Trinidad | AP47: Father | AQ47: 0949-647-5784
D48: No | F48: Hazelnut | H48: Member | I48: =IF(AND(K48="",J48=""),"",CONCATENATE(J48,", ",K48)) -> Boteng, Zandra | J48: Boteng | K48: Zandra | M48: Female | T48: =IF(S48="","",DATEDIF(S48,TODAY(),"Y"))
D49: Yes | F49: Sycamore | H49: Member | I49: =IF(AND(K49="",J49=""),"",CONCATENATE(J49,", ",K49)) -> Broqueza, Maylene Miles | J49: Broqueza | K49: Maylene Miles | L49: P | M49: Female | P49: Sorsogon City | Q49: 0945-508-6556 | S49: 29466 | T49: =IF(S49="","",DATEDIF(S49,TODAY(),"Y")) -> 46 | U49: Sorsogon City | V49: Broqueza, Manuel | W49: Broqueza, Pacita | X49: Yes | Y49: 1999 | Z49: Yes | AA49: 1999 | AB49: Pentecostal | AC49: Bachelor of Secretarial Administration | AD49: Manager of Personal Collection | AE49: Teaching | AF49: Teaching | AG49: Teaching, Singing | AH49: Volleyball, Basketball | AI49: Cooking
D50: No | F50: Mulberry | H50: Member | I50: =IF(AND(K50="",J50=""),"",CONCATENATE(J50,", ",K50)) -> Bulalin, Lita | J50: Bulalin | K50: Lita | M50: Female | T50: =IF(S50="","",DATEDIF(S50,TODAY(),"Y"))
D51: No | F51: Mulberry | H51: Member | I51: =IF(AND(K51="",J51=""),"",CONCATENATE(J51,", ",K51)) -> Cabalfin, Jennifer | J51: Cabalfin | K51: Jennifer | M51: Female | T51: =IF(S51="","",DATEDIF(S51,TODAY(),"Y"))
D52: Yes | F52: Mulberry | H52: Assistant Leader | I52: =IF(AND(K52="",J52=""),"",CONCATENATE(J52,", ",K52)) -> Cabay, Alice | J52: Cabay | K52: Alice | L52: M | M52: Female | N52: 70 | O52: Magsaysay Private Road | P52: Sagada Mt. Province | Q52: 0910-386-7673 | R52: alicecabay031267@gmail.com | S52: 24543 | T52: =IF(S52="","",DATEDIF(S52,TODAY(),"Y")) -> 59 | U52: Sagada Mt. Province | X52: Yes | Y52: July 1990 | Z52: Yes | AA52: 1990 | AB52: Anglican | AC52: Second year college | AH52: Badminton | AI52: Cooking | AJ52: Cabay, Peter | AK52: Business Man | AL52: Yes | AN52: Cabay, Peter | AO52: 70 Magsaysay Private Road Baguio City | AP52: Spouse | AQ52: 0985-542-3884
D53: Yes | F53: Chestnut | H53: Secretary | I53: =IF(AND(K53="",J53=""),"",CONCATENATE(J53,", ",K53)) -> Cabay, Arlyn | J53: Cabay | K53: Arlyn | L53: Doligas | M53: Female | N53: Purok 2 Km 3 | O53: Asin Road | P53: Dacudac, Tadian, Mt. Province | Q53: 0938-806-4029 | R53: cabayarlyn@gmail.com | S53: 31158 | T53: =IF(S53="","",DATEDIF(S53,TODAY(),"Y")) -> 41 | U53: Tadian, Mt. Province | W53: Doligan, Juliet Soliman | X53: Yes | Y53: August 23, 1998 | Z53: Yes | AA53: August 1998 | AB53: Palti-ing | AC53: College Level | AD53: Teacher - San Luis Elementary School | AG53: Teaching | AH53: Volleyball | AJ53: Cabay, Charles Pingian | AK53: Brgy. Kagawad - BLGU Duagan, Tadian | AL53: Yes | AM53: Yes | AN53: Cabay, Peter | AO53: 36 Private Rd. Trancoville | AP53: Brother-in-law
D54: Yes | F54: Pomegranate | H54: Member | I54: =IF(AND(K54="",J54=""),"",CONCATENATE(J54,", ",K54)) -> Cabay, Fermina | J54: Cabay | K54: Fermina | M54: Female | N54: 348 Banig | O54: Tawang, La Trinidad | Q54: 0930-228-1744 / 0991-112-0281 | S54: 21523 | T54: =IF(S54="","",DATEDIF(S54,TODAY(),"Y")) -> 67 | U54: Tadian, Mt. Province | V54: Ladilad, Gregorio | W54: Ladilad, Lingdan | X54: Yes | Y54: March 1994 | Z54: Yes | AB54: Anglican | AC54: Elementary | AJ54: Cabay, Rogelio | AL54: Yes | AM54: Yes | AN54: De Guzman, Marissa | AO54: Tawang La Trinidad | AP54: Daughter | AQ54: 0968-509-7545
D55: No | F55: Palm | H55: Member | I55: =IF(AND(K55="",J55=""),"",CONCATENATE(J55,", ",K55)) -> Cadiay, Merriam | J55: Cadiay | K55: Merriam | M55: Female | N55: Badiwan | O55: Poblacion, Tuba | Q55: 0928-374-5381 | S55: 27944 | T55: =IF(S55="","",DATEDIF(S55,TODAY(),"Y")) -> 50
D56: No | F56: Palm | H56: Member | I56: =IF(AND(K56="",J56=""),"",CONCATENATE(J56,", ",K56)) -> Cadiay, Vivian | J56: Cadiay | K56: Vivian | M56: Female | N56: Badiwan | O56: Poblacion, Tuba | S56: 32363 | T56: =IF(S56="","",DATEDIF(S56,TODAY(),"Y")) -> 38
D57: Yes | I57: =IF(AND(K57="",J57=""),"",CONCATENATE(J57,", ",K57)) -> Calias, Pilora | J57: Calias | K57: Pilora | L57: P | M57: Female | N57: Purok Dumilos | O57: Tuding Proper, Itogon | P57: Dalupirip Uling Itogon Benguet | Q57: 0910-589-2276 | S57: 20056 | T57: =IF(S57="","",DATEDIF(S57,TODAY(),"Y")) -> 71 | U57: Itogon Benguet | V57: Calias, Maroy | W57: Calias, Terina Pokdo | X57: Yes | Y57: 1985 | Z57: Yes | AA57: 1985 | AB57: Roman Catholic | AC57: Vocational Course | AN57: Calias, Mercy | AP57: Sister
D58: Yes | I58: =IF(AND(K58="",J58=""),"",CONCATENATE(J58,", ",K58)) -> Calimlim, Jamielyn | J58: Calimlim | K58: Jamielyn | L58: R. | N58: 1 Purok 5 | O58: Holy Ghost Proper | P58: 524 Penged Nangalisan Tuba Benguet | Q58: 0963-888-1394 | R58: calimlimjamiely18@gmail.com | S58: 34204 | T58: =IF(S58="","",DATEDIF(S58,TODAY(),"Y")) -> 33 | U58: La Trinidad | V58: Robles, Jimmy N. | W58: Robles, Arcelie T. | X58: Yes | Y58: 43408 | Z58: Yes | AA58: 43418 | AB58: Roman Catholic & Oneness Pioneering Church | AC58: Vocational | AG58: Teaching; Playing Musical AInstruments | AH58: Volleyball | AI58: Cooking | AJ58: Calimlim, Jared B. | AK58: Facilities Operation & Maintenance Tech. | AL58: Yes | AM58: Yes | AN58: Calimlim, Jared B. | AO58: Same as Home Address | AP58: Spouse
D59: Yes | F59: Hazelnut | H59: Assistant Leader | I59: =IF(AND(K59="",J59=""),"",CONCATENATE(J59,", ",K59)) -> Camil, Marissa | J59: Camil | K59: Marissa | L59: S | M59: Female | N59: Apugan | O59: Sto. Tomas | Q59: 0907-150-6329 | S59: 28974 | T59: =IF(S59="","",DATEDIF(S59,TODAY(),"Y")) -> 47 | U59: Baguio City | V59: Simeon, Salvador | W59: Simeon, Jean | AB59: Roman Catholic | A.G. | AC59: College Level | AE59: Music Ministry - Choir | AF59: Sunday School Teacher | AJ59: Camil, Rogelio | AK59: Driver | AL59: Not Yet | AM59: Not Yet | AN59: Camil, Rogelio | AO59: Apugan Sto. Tomas | AP59: Spouse
D60: No | F60: Acacia | H60: Member | I60: =IF(AND(K60="",J60=""),"",CONCATENATE(J60,", ",K60)) -> Camodag, Juliet | J60: Camodag | K60: Juliet | M60: Female | T60: =IF(S60="","",DATEDIF(S60,TODAY(),"Y"))
D61: Yes | F61: Almond | H61: Member | I61: =IF(AND(K61="",J61=""),"",CONCATENATE(J61,", ",K61)) -> Camora, Cheril | J61: Camora | K61: Cheril | L61: C | M61: Female | N61: Purok 1 | O61: Irisan | Q61: 0985-805-9140 | R61: camoracheril07@gmail.com | S61: 26901 | T61: =IF(S61="","",DATEDIF(S61,TODAY(),"Y")) -> 53 | U61: Baguio City | X61: Yes | Z61: Yes | AC61: High school level | AD61: Vendor
D62: No | F62: Palm | H62: Member | I62: =IF(AND(K62="",J62=""),"",CONCATENATE(J62,", ",K62)) -> Camora, Glenda | J62: Camora | K62: Glenda | L62: Tingdan | M62: Female | N62: 04 Lower Balacbac | O62: Sto. Tomas Proper | Q62: 0919-563-5186 | S62: 25759 | T62: =IF(S62="","",DATEDIF(S62,TODAY(),"Y")) -> 56
D63: Yes | F63: Palm | H63: Member | I63: =IF(AND(K63="",J63=""),"",CONCATENATE(J63,", ",K63)) -> Camora, Marlyn | J63: Camora | K63: Marlyn | M63: Female | N63: 774 | O63: Green Valley Village | Q63: 0949-500-0010 | S63: 25250 | T63: =IF(S63="","",DATEDIF(S63,TODAY(),"Y")) -> 57 | U63: La Trinidad Benguet | V63: Camora, Leonardo | W63: Camora, Camila Cabinta | X63: Yes | Z63: Yes | AC63: High school level
D64: No | F64: Palm | H64: Member | I64: =IF(AND(K64="",J64=""),"",CONCATENATE(J64,", ",K64)) -> Cano, Rena | J64: Cano | K64: Rena | M64: Female | N64: 2nd Cave, Crystal Cave | O64: Bakakeng Central | Q64: 0916-542-1730 | S64: 35171 | T64: =IF(S64="","",DATEDIF(S64,TODAY(),"Y")) -> 30
D65: No | F65: Acacia | H65: Member | I65: =IF(AND(K65="",J65=""),"",CONCATENATE(J65,", ",K65)) -> Caragay, Cita | J65: Caragay | K65: Cita | M65: Female | T65: =IF(S65="","",DATEDIF(S65,TODAY(),"Y"))
D66: No | F66: Oak | H66: Member | I66: =IF(AND(K66="",J66=""),"",CONCATENATE(J66,", ",K66)) -> Caragay, Erla | J66: Caragay | K66: Erla | M66: Female | N66: Purok 126 Sunny Side | O66: Fairview | Q66: 0966-360-3518 | S66: 29153 | T66: =IF(S66="","",DATEDIF(S66,TODAY(),"Y")) -> 47
D67: No | F67: Mulberry | H67: Secretary | I67: =IF(AND(K67="",J67=""),"",CONCATENATE(J67,", ",K67)) -> Caragay, Kimberly | J67: Caragay | K67: Kimberly | L67: Barlaan | M67: Female | T67: =IF(S67="","",DATEDIF(S67,TODAY(),"Y"))
D68: Yes | F68: Olive | H68: Member | I68: =IF(AND(K68="",J68=""),"",CONCATENATE(J68,", ",K68)) -> Cariño, Emelita | J68: Cariño | K68: Emelita | M68: Female | N68: 53 | O68: Ledesma St | Q68: 0912-714-7007 / 445-3201 | S68: 22543 | T68: =IF(S68="","",DATEDIF(S68,TODAY(),"Y")) -> 65 | U68: Baguio City | X68: Yes | Y68: February 14, 2013 | Z68: Yes | AA68: February 27, 2013 | AB68: Roman Catholic | AC68: High school level | AG68: Playing Musical Instruments
D69: Yes | F69: Juniper | H69: Assistant Leader | I69: =IF(AND(K69="",J69=""),"",CONCATENATE(J69,", ",K69)) -> Castro, Ellen | J69: Castro | K69: Ellen | L69: B | M69: Female | N69: OC-074 | O69: Central Tawang, La Trinidad | Q69: 0909-383-8570 | S69: 26067 | T69: =IF(S69="","",DATEDIF(S69,TODAY(),"Y")) -> 55 | U69: Bangao, Buguias, Benguet | X69: Yes | Z69: Yes | AA69: April 24, 1994 | AB69: Anglican | AC69: College Level | AD69: Self-employed | AE69: LM Cellgroup Assistant Leader, Treasurer | AF69: Treasurer | AJ69: Castro, Harold | AN69: Harnelle, Harell, Henzy | AO69: OC-074 Central Tawang La Trinidad | AP69: Sons | AQ69: 0963-991-0741 / 0945-375-1608
D70: No | F70: Almond | H70: Member | I70: =IF(AND(K70="",J70=""),"",CONCATENATE(J70,", ",K70)) -> Castro, Rizalina | J70: Castro | K70: Rizalina | M70: Female | N70: 7 Purok 1 | O70: Irisan | Q70: 0917-176-0408 | S70: 23908 | T70: =IF(S70="","",DATEDIF(S70,TODAY(),"Y")) -> 61
D71: No | F71: Juniper | H71: Member | I71: =IF(AND(K71="",J71=""),"",CONCATENATE(J71,", ",K71)) -> Catacutan, Jurina | J71: Catacutan | K71: Jurina | M71: Female | N71: 49710.285 | O71: Upper Pinget | Q71: 0985-033-9905 | S71: 25569 | T71: =IF(S71="","",DATEDIF(S71,TODAY(),"Y")) -> 56
D72: Yes | F72: Chestnut | H72: Leader | I72: =IF(AND(K72="",J72=""),"",CONCATENATE(J72,", ",K72)) -> Cayandag, Marilou | J72: Cayandag | K72: Marilou | M72: Female | N72: P2-#224 | O72: Poliwes | Q72: 0910-807-5193 | R72: maloucayandag701@gmail.com | S72: 29768 | T72: =IF(S72="","",DATEDIF(S72,TODAY(),"Y")) -> 45 | U72: Lepanto Mankayan | V72: Palitayan, Stephen Sr. | W72: Palitayan, Elizabeth | X72: Yes | Y72: November 1998 | Z72: Yes | AA72: November 1998 | AB72: Anglican | AC72: College Level | AD72: Pharmacist - BGH | AF72: Sunday School Teacher | AG72: Singing | AJ72: Cayandag, Jimmy | AK72: Zoning Inspector | AL72: Yes | AM72: Yes | AN72: Cayandag, Jimmy | AO72: P2-#224 Poliwes | AP72: Spouse
D73: Yes | I73: =IF(AND(K73="",J73=""),"",CONCATENATE(J73,", ",K73)) -> Ciriaco, Ginalyn | J73: Ciriaco | K73: Ginalyn | L73: P | M73: Female | N73: 151 Takay Sunnyside | O73: Fairview | P73: Dipaculao, Baler | Q73: 0927-272-6079 | S73: 28955 | T73: =IF(S73="","",DATEDIF(S73,TODAY(),"Y")) -> 47 | U73: Dipaculao, Baler | V73: Ciriaco, Patricio | W73: Joaquin, Teresita | X73: Yes | Z73: Yes
D74: Yes | F74: Chestnut | H74: Member | I74: =IF(AND(K74="",J74=""),"",CONCATENATE(J74,", ",K74)) -> Coraza, Jean | J74: Coraza | K74: Jean | L74: P | M74: Female | N74: Sapsing | O74: Beckel, La Trinidad | Q74: 0968-758-2372 | S74: 22547 | T74: =IF(S74="","",DATEDIF(S74,TODAY(),"Y")) -> 65 | U74: Sagada Mt. Province | V74: Pacyaya, David | W74: Matias, Rose Lagmay (+) | X74: Yes | Y74: April 1993 | Z74: Yes | AA74: December 1993 | AB74: Anglican | AC74: High school level | AF74: LM Cellgroup Leader | AH74: Volleyball, Badminton | AI74: Gardening | AJ74: Coraza, Arnulfo | AK74: Laborer | AL74: Yes | AM74: Not Yet | AN74: Coraza, Ameeran | AO74: Loakan, Baguio City | AP74: Daughter | AQ74: 0918-414-0717
D75: Yes | F75: Olive | H75: Member | I75: =IF(AND(K75="",J75=""),"",CONCATENATE(J75,", ",K75)) -> Coyasan, Mary Joe | J75: Coyasan | K75: Mary Joe | L75: Cosme | M75: Female | N75: AB006 | O75: Ambiong, La Trinidad | P75: Pingad, Sabangan, Mt. Province | Q75: 0928-194-5799 | S75: 27516 | T75: =IF(S75="","",DATEDIF(S75,TODAY(),"Y")) -> 51 | U75: Pingad, Sabangan, Mt. Province | V75: Cosme, Godfrey | W75: Banggiwak, Ana | X75: Yes | Z75: Yes | AB75: Roman Catholic | AC75: College Level | AG75: Teaching | AI75: Cleaning | AJ75: Coyasan, Priston | AK75: Driver / Construction | AL75: Yes | AM75: Yes | AN75: Coyasan, Priston | AO75: AB006 Ambiong La Trinidad | AP75: Spouse | AQ75: 0918-620-3449
D76: Yes | F76: Oak | H76: Secretary | I76: =IF(AND(K76="",J76=""),"",CONCATENATE(J76,", ",K76)) -> Coyasan, Sonia | J76: Coyasan | K76: Sonia | L76: Rala | M76: Female | N76: OE26 Dengsi | O76: Tawang, La Trinidad | P76: Malasiqui, Pangasinan | Q76: 0939-468-7391 | R76: coyasansonia@gmail.com | S76: 19770 | T76: =IF(S76="","",DATEDIF(S76,TODAY(),"Y")) -> 72 | U76: Pangasinan | V76: Rala, Gregorio | W76: Gamayen, Susana | X76: Yes | Y76: December 26, 1990 | Z76: Yes | AA76: January 1, 1991 | AB76: Roman Catholic | AC76: High school level | AD76: Housewife | AF76: Soul winning | AG76: Soul winning | AI76: Cooking | AJ76: Coyasan, Julio | AK76: Reflexology / Driver | AL76: Yes | AM76: Yes | AN76: Coyasan, Julio | AO76: OE26 Dengsi Tawang La Trinidad | AP76: Spouse | AQ76: 0939-567-3119
D77: Yes | F77: Almond | H77: Member | I77: =IF(AND(K77="",J77=""),"",CONCATENATE(J77,", ",K77)) -> Cruz, Juanita | J77: Cruz | K77: Juanita | L77: Neverida | M77: Female | N77: 47 Purok 5 | O77: Upper Fairview | P77: Sta. Rita Aringay La Union | Q77: 0921-935-2642 | S77: 19720 | T77: =IF(S77="","",DATEDIF(S77,TODAY(),"Y")) -> 72 | U77: Aringay, La Union | V77: Neverida, Florencio (+) | W77: Neverida, Magdalena (+) | X77: Yes | Y77: February 11, 1988 | Z77: Yes | AA77: April 1988 | AB77: Roman Catholic | AC77: High school level | AE77: LM Cellgroup Assistant Leader | AF77: Sunday School Teacher, Singing, Ushering | AG77: Singing, Playing Musical instruments | AH77: Volleyball | AI77: Crochet making | AJ77: Cruz, Alberto (+) | AN77: Cruz, Kim Michael | AO77: 47 Purok 5 Upper Fairview | AP77: Son | AQ77: 0927-727-5059
D78: Yes | F78: Hazelnut | H78: Member | I78: =IF(AND(K78="",J78=""),"",CONCATENATE(J78,", ",K78)) -> Cruz, Kristine | J78: Cruz | K78: Kristine | L78: D | M78: Female | N78: 123 Blk3 | O78: Middle Quirino Hill | Q78: 0945-770-8142 | R78: kristinedcruz@gmail.com | S78: 30266 | T78: =IF(S78="","",DATEDIF(S78,TODAY(),"Y")) -> 43 | U78: La Trinidad Benguet | V78: De Vera, Jaime Sr. (+) | W78: Deloterio, Veronica | X78: Yes | Y78: September 23, 1999 | Z78: Yes | AD78: IELTS Teacher | AE78: Sunday School Ministry, Choir | AF78: Ushering Department, Youth Leader | AJ78: Cruz, Marlon | AK78: Delivery Rider | AL78: Yes | AM78: Yes | AN78: Cruz, Marlon | AO78: 123 Blk3 Middle Quirino Hill | AP78: Spouse
D79: Yes | F79: Cedar | H79: Member | I79: =IF(AND(K79="",J79=""),"",CONCATENATE(J79,", ",K79)) -> Cutay, Freda | J79: Cutay | K79: Freda | L79: Fintad | M79: Female | N79: 26 F Cutay Drive Purok 5 | O79: Irisan | P79: Pob. Tuba Benguet | Q79: 0950-666-4257 | S79: 24178 | T79: =IF(S79="","",DATEDIF(S79,TODAY(),"Y")) -> 60 | U79: Tuba Benguet | V79: Fintad, Peter | W79: Bansulay, Pilar | X79: Yes | Y79: February 1993 | Z79: Yes | AA79: 1993 | AB79: Roman Catholic | AC79: College Level | AD79: Farmer | AE79: Prayer Warrior | AF79: Ushering, Home Bible Study | AH79: Badminton | AN79: Cutay, John Timothy | AO79: R5 Irisan | AP79: Son | AQ79: 0991-137-8722
D80: No | F80: Mulberry | H80: Leader | I80: =IF(AND(K80="",J80=""),"",CONCATENATE(J80,", ",K80)) -> Cutay, Johanna Faith | J80: Cutay | K80: Johanna Faith | L80: Banez | M80: Female | T80: =IF(S80="","",DATEDIF(S80,TODAY(),"Y"))
D81: Yes | F81: Juniper | H81: Leader | I81: =IF(AND(K81="",J81=""),"",CONCATENATE(J81,", ",K81)) -> Cutay, Regina | J81: Cutay | K81: Regina | M81: Female | N81: 27 Purok 5 F Cutay Drive | O81: Irisan | Q81: 0929-847-3880 | S81: 25820 | T81: =IF(S81="","",DATEDIF(S81,TODAY(),"Y")) -> 56 | U81: Mankayan, Benguet | V81: Andoy, Pedro | W81: Andoy, Martina Perez | X81: Yes | Y81: December 23, 1990 | Z81: Yes | AA81: March 10, 1992 | AB81: Roman Catholic | AC81: High school level | AD81: Farmer | AH81: Volleyball, Softball | AI81: Cooking, Planting | AJ81: Cutay, Digno | AK81: Driver | AL81: Yes | AM81: Yes | AN81: Cutay, Digno | AO81: 27 Purok 5 F Cutay Drive Irisan | AP81: Spouse | AQ81: 0910-922-5223
D82: Yes | F82: Juniper | H82: Member | I82: =IF(AND(K82="",J82=""),"",CONCATENATE(J82,", ",K82)) -> Dacanay, Lanie | J82: Dacanay | K82: Lanie | L82: T | M82: Female | N82: Blk 96 Lot 16 | O82: West Quirino Hill | Q82: 0927-768-5016 | S82: 28131 | T82: =IF(S82="","",DATEDIF(S82,TODAY(),"Y")) -> 49 | U82: Baler, Aurora | V82: Torda, Nonito | W82: Joaquin, Teresita | X82: Yes | Z82: Yes | AC82: College Level | AJ82: Dacanay, Romil | AK82: PNP retired | AL82: Yes | AM82: Yes | AN82: Dacanay, Romil | AO82: Blk 96 Lot 16 West Quirino Hill | AP82: Spouse | AQ82: 0905-285-3092
D83: Yes | F83: Hazelnut | H83: Member | I83: =IF(AND(K83="",J83=""),"",CONCATENATE(J83,", ",K83)) -> Dagupen, Josephine | J83: Dagupen | K83: Josephine | M83: Female | N83: 19 Purok 28 | O83: Irisan | P83: Patiacan Quirino Ilocos Sur | Q83: 0919-226-4571 | S83: 24916 | T83: =IF(S83="","",DATEDIF(S83,TODAY(),"Y")) -> 58 | U83: Sta. Lucia, Ilocos Sur | V83: Caslangen, Sergio | W83: Caslangen, Emilia | X83: Yes | Y83: August 1993 | Z83: Yes | AA83: August 1993 | AB83: Roman Catholic | INC | AC83: College Level | AD83: Business Woman | AI83: Cooking | AJ83: Dagupen, Franklin | AK83: Electrician | AL83: Yes | AM83: Yes | AN83: Dagupen, Franklin | AO83: 19 Purok 28 Upper Irisan | AP83: Spouse | AQ83: 0918-358-7028
D84: No | F84: Hazelnut | H84: Member | I84: =IF(AND(K84="",J84=""),"",CONCATENATE(J84,", ",K84)) -> Daiwey, Babet | J84: Daiwey | K84: Babet | M84: Female | N84: Blk D Lot 3 Diamond St Irisville | O84: Irisan | T84: =IF(S84="","",DATEDIF(S84,TODAY(),"Y"))
D85: No | F85: Acacia | H85: Secretary | I85: =IF(AND(K85="",J85=""),"",CONCATENATE(J85,", ",K85)) -> Dalisan, Jenifer Apple | J85: Dalisan | K85: Jenifer Apple | M85: Female | T85: =IF(S85="","",DATEDIF(S85,TODAY(),"Y"))
D86: No | F86: Palm | H86: Member | I86: =IF(AND(K86="",J86=""),"",CONCATENATE(J86,", ",K86)) -> Danganon, Analyn | J86: Danganon | K86: Analyn | M86: Female | N86: 38 Crystal Cave | O86: Bakakeng Central | Q86: 0927-363-7613 | S86: 29156 | T86: =IF(S86="","",DATEDIF(S86,TODAY(),"Y")) -> 46
D87: Yes | F87: Oak | H87: Leader | I87: =IF(AND(K87="",J87=""),"",CONCATENATE(J87,", ",K87)) -> Dangla, Nancy | J87: Dangla | K87: Nancy | L87: Buya | M87: Female | N87: Blk 1 Lot 46 NHA | O87: Tadiangan, Tuba | Q87: 0961-491-3067 | S87: 23993 | T87: =IF(S87="","",DATEDIF(S87,TODAY(),"Y")) -> 61 | U87: Camp 1 Kennon Tuba Benguet | V87: Buya, William Sr. (+) | W87: Buya, Bregita Inso (+) | X87: Yes | Y87: August 1990 | Z87: Yes | AA87: 1983 | AB87: Espiritista | AC87: High school level | AE87: LM Cellgroup Leader | AF87: LM Cellgroup Secretary | AJ87: Dangla, Constancio Sr. | AK87: Laborer | AL87: Yes | AM87: Yes | AN87: Dangla, Hiede Cattleyah | AO87: Blk 1 Lot 46 NHA Tadiangan Tuba Benguet | AP87: Daughter | AQ87: 0921-743-2975
D88: Yes | F88: Olive | H88: Member | I88: =IF(AND(K88="",J88=""),"",CONCATENATE(J88,", ",K88)) -> Daskeo, May | J88: Daskeo | K88: May | L88: Guiamas | M88: Female | N88: Prk 6 Brookspoint | O88: Aurora Hill | P88: Pob. Tadian Mt. Province | Q88: 0960-613-3613 | R88: mgdaskeo@gmail.com | S88: 30458 | T88: =IF(S88="","",DATEDIF(S88,TODAY(),"Y")) -> 43 | U88: Tadian, Mt. Province | V88: Guiamas, Maurice (+) | W88: Guiamas, Fortunata | AB88: Anglican | AC88: College Level | AD88: Teacher - DepEd | AG88: Teaching | AH88: Chess/Dama | AI88: Cooking | AJ88: Daskeo, Klient Patrick | AK88: ESL Online Tutor | AL88: Yes | AM88: Yes | AN88: Daskeo, Klient Patrick | AO88: Brokkspoint, Baguio City | AP88: Spouse | AQ88: 0932-740-4983
D89: No | F89: Chestnut | H89: Assistant Leader | I89: =IF(AND(K89="",J89=""),"",CONCATENATE(J89,", ",K89)) -> De Castro, Rebecca | J89: De Castro | K89: Rebecca | L89: F | M89: Female | N89: 25B Purok 4 | O89: Bakakeng Norte | Q89: 0907-378-5711 | S89: 29700 | T89: =IF(S89="","",DATEDIF(S89,TODAY(),"Y")) -> 45
D90: No | F90: Pomegranate | H90: Member | I90: =IF(AND(K90="",J90=""),"",CONCATENATE(J90,", ",K90)) -> De Guzman, Marissa | J90: De Guzman | K90: Marissa | M90: Female | T90: =IF(S90="","",DATEDIF(S90,TODAY(),"Y"))
D91: No | F91: Olive | H91: Leader | I91: =IF(AND(K91="",J91=""),"",CONCATENATE(J91,", ",K91)) -> Dela Peña, Imelda | J91: Dela Peña | K91: Imelda | M91: Female | N91: 051 Purok 27 Upper San Carlos Heights | O91: Irisan | Q91: 0927-076-0387 | S91: 25120 | T91: =IF(S91="","",DATEDIF(S91,TODAY(),"Y")) -> 58
D92: No | F92: Oak | H92: Member | I92: =IF(AND(K92="",J92=""),"",CONCATENATE(J92,", ",K92)) -> Delos Trinos, Julieta | J92: Delos Trinos | K92: Julieta | M92: Female | T92: =IF(S92="","",DATEDIF(S92,TODAY(),"Y"))
D93: Yes | F93: Olive | H93: Member | I93: =IF(AND(K93="",J93=""),"",CONCATENATE(J93,", ",K93)) -> Deloterio, Veronica | J93: Deloterio | K93: Veronica | M93: Female | N93: 9 | O93: Upper Brookside | P93: Kapangan Benguet | Q93: 0929-325-5422 | S93: 22280 | T93: =IF(S93="","",DATEDIF(S93,TODAY(),"Y")) -> 65 | U93: Kapangan, Benguet | V93: Dayao, Tobanio | W93: Bentrez, Corazon | X93: Yes | Y93: 1984 | Z93: Yes | AA93: 1984 | AB93: Roman Catholic | Pagan | AC93: High school level | AD93: Vendor | AJ93: Deloterio, Edgar | AL93: Not Yet | AM93: Not Yet | AN93: Cruz, Kristine | AP93: Daughter
D94: No | F94: Hazelnut | H94: Member | I94: =IF(AND(K94="",J94=""),"",CONCATENATE(J94,", ",K94)) -> Diamsay, Alma | J94: Diamsay | K94: Alma | L94: A | M94: Female | N94: Purok 4 | O94: Balsigan Rd | Q94: 0910-697-4106 | S94: 32720 | T94: =IF(S94="","",DATEDIF(S94,TODAY(),"Y")) -> 37
D95: Yes | F95: Pomegranate | H95: Member | I95: =IF(AND(K95="",J95=""),"",CONCATENATE(J95,", ",K95)) -> Domigsi, Rosemarie | J95: Domigsi | K95: Rosemarie | M95: Female | N95: LA 147 Inselbeg | O95: Lubas, La Trinidad | Q95: 0948-338-3051 | S95: 24943 | T95: =IF(S95="","",DATEDIF(S95,TODAY(),"Y")) -> 58 | U95: Sabangan, Mt. Province | V95: Paleyan, Fernando | W95: Paleyan, Dominga | X95: Yes | Y95: 1998 | Z95: Yes | AA95: 1998 | AJ95: Domigsi, Lydio
D96: No | F96: Sycamore | H96: Member | I96: =IF(AND(K96="",J96=""),"",CONCATENATE(J96,", ",K96)) -> Donaire, Romelie | J96: Donaire | K96: Romelie | M96: Female | T96: =IF(S96="","",DATEDIF(S96,TODAY(),"Y"))
D97: Yes | F97: Pomegranate | H97: Member | I97: =IF(AND(K97="",J97=""),"",CONCATENATE(J97,", ",K97)) -> Dongpoen, Zeny | J97: Dongpoen | K97: Zeny | M97: Female | O97: Pico, La Trinidad | Q97: 0910-836-1017 | S97: 22899 | T97: =IF(S97="","",DATEDIF(S97,TODAY(),"Y")) -> 64 | U97: La Trinidad Benguet | V97: Uson, Carlos | W97: Uson, Catherine Mang-oy | X97: Yes | Y97: 1991 | Z97: Yes | AA97: 1991 | AB97: Anglican | AC97: College Level | AJ97: Dongpoen, Nardo | AK97: Business Man | AL97: Yes | AM97: Not Yet | AN97: Labiano, Karen | AO97: Pico | AP97: Niece | AQ97: 0920-409-1132
D98: No | F98: Cedar | H98: Member | I98: =IF(AND(K98="",J98=""),"",CONCATENATE(J98,", ",K98)) -> Dulnuan, Helen | J98: Dulnuan | K98: Helen | M98: Female | T98: =IF(S98="","",DATEDIF(S98,TODAY(),"Y"))
D99: Yes | F99: Tamarisk | H99: Member | I99: =IF(AND(K99="",J99=""),"",CONCATENATE(J99,", ",K99)) -> Dy, Mary Antonette | J99: Dy | K99: Mary Antonette | L99: Taloban | M99: Female | N99: 025 Avelino St | O99: Guisad | Q99: 0945-351-3819 | S99: 24342 | T99: =IF(S99="","",DATEDIF(S99,TODAY(),"Y")) -> 60 | U99: Dagupan City, Pangasinan | V99: Taloban, Antonio Jimenez Sr (+) | W99: Taloban, Rosita Rosario | X99: Yes | Y99: 2020 | Z99: Yes | AB99: Roman Catholic | AC99: BS Accounting | AD99: Part Time | AJ99: Dy, Jaime Mendoza Sr. | AK99: Business Man | AL99: Yes | AM99: Not Yet | AN99: Taloban, Antonio Jr. | AO99: 08 Avelino St. Guisad | AP99: Brother | AQ99: 619-6051
D100: No | F100: Almond | H100: Member | I100: =IF(AND(K100="",J100=""),"",CONCATENATE(J100,", ",K100)) -> Esteban, Teresita | J100: Esteban | K100: Teresita | M100: Female | Q100: 0909-564-2663 | S100: 22872 | T100: =IF(S100="","",DATEDIF(S100,TODAY(),"Y")) -> 64
D101: Yes | I101: =IF(AND(K101="",J101=""),"",CONCATENATE(J101,", ",K101)) -> Estipular, Corazon | J101: Estipular | K101: Corazon | M101: Female | N101: 89 Amsing Siapno Rd | O101: Pacdal | P101: Naguilian La Union | Q101: 0915-332-5884 | S101: 20914 | T101: =IF(S101="","",DATEDIF(S101,TODAY(),"Y")) -> 69 | U101: Naguilian La Union | V101: Ayson, Bernardo (+) | W101: Ayson, Felicidad (+) | X101: Yes | Y101: July 2019 | Z101: No | AB101: Roman Catholic | AC101: High school level | AJ101: Estipular, Oscar | AK101: Retired / Employee | AL101: Yes | AM101: Yes | AN101: Estipular, Oscar Jr. | AO101: 89 Amsing Siapno Rd Pacdal | AP101: Son | AQ101: 0927-379-7031
...

Sheet AMM
A1: APOSTOLIC MEN'S MINISTRIES
A3: Count per filter | B3: =SUBTOTAL(3,AMM!$K$5:$K$299) -> 76
D4: With Profiling Forn | E4: Status | F4: Cell Group | G4: Age Group | H4: CG Position | I4: Full Name (Last, First) | J4: Last Name | K4: First Name | L4: Middle Initial | M4: Gender | N4: Street | O4: City Address | P4: Provincial Address | Q4: Contact Number | R4: Email | S4: Birthdate | T4: Age | U4: Birthplace | V4: Father | W4: Mother | X4: Baptized in Water | Y4: Date | Z4: Baptized in Holy Ghost | AA4: Date2 | AB4: Former Religious Affiliation | AC4: Educational Attaintment | AD4: Current Occupation | AE4: Church ministries (Present) | AF4: Church ministries (Past) | AG4: Personal skills | AH4: Sports Interest | AI4: Other skills | AJ4: Spouse Name | AK4: Spouse Occupation | AL4: Is your spouse a believer? | AM4: Do both of you attend the same church? | AN4: Emergency Contact | AO4: Address | AP4: Relationship | AQ4: Contact Number2
D5: Yes | F5: Judah | H5: Assistant Leader | I5: =IF(AND(K5="",J5=""),"",CONCATENATE(J5,", ",K5)) -> Abuan, Jomar | J5: Abuan | K5: Jomar | L5: C | M5: Male | N5: 14 Purok 8 Upper Km 5 | O5: Asin Road | P5: Baguio City | Q5: 0946-168-8476 | R5: shimaru26@gmail.com | S5: 33842 | T5: =IF(S5="","",DATEDIF(S5,TODAY(),"Y")) -> 34 | U5: Baguio City | V5: Abuan, Ricardo A. | W5: Abuan, Maria Fe C | X5: Yes | Z5: Yes | AE5: Music, BQC | AJ5: Abuan, Christine V. | AL5: Yes | AM5: Yes | AN5: Abuan, Christine V. | AO5: Same as Home Address | AP5: Spouse | AQ5: 0927-393-4928
D6: Yes | F6: Joseph | H6: Member | I6: =IF(AND(K6="",J6=""),"",CONCATENATE(J6,", ",K6)) -> Abuan, Ricardo | J6: Abuan | K6: Ricardo | L6: A | M6: Male | N6: 14 Purok 8 Upper Km 5 | O6: Asin Road | Q6: 0928-967-5947 | S6: 21665 | T6: =IF(S6="","",DATEDIF(S6,TODAY(),"Y")) -> 67
D7: Yes | F7: Issachar | H7: Member | I7: =IF(AND(K7="",J7=""),"",CONCATENATE(J7,", ",K7)) -> Alarcio, Marcial | J7: Alarcio | K7: Marcial | L7: L | M7: Male | N7: 11 Purok 8 Sampaguita Site | O7: San Luis Village | Q7: 0950-516-2515 | S7: 27089 | T7: =IF(S7="","",DATEDIF(S7,TODAY(),"Y")) -> 52 | U7: Manaoag, Pangasinan | W7: Lockiao, Paulina | X7: Yes | Z7: Yes | AB7: Roman Catholic | AC7: High School | AD7: Driver, Veg. Dealer | AJ7: Alarcio, Grace | AK7: Vendor | AL7: Yes | AM7: Yes | AN7: Alarcio, Grace | AO7: Same as Home Address | AP7: Spouse | AQ7: 0910-882-0715
D8: No | F8: Issachar | H8: Member | I8: =IF(AND(K8="",J8=""),"",CONCATENATE(J8,", ",K8)) -> Alcoriza, Reynaldo | J8: Alcoriza | K8: Reynaldo | M8: Male | N8: Goldfield | O8: Poblacion, Itogon | Q8: 0909-187-8704 | S8: 26467 | T8: =IF(S8="","",DATEDIF(S8,TODAY(),"Y")) -> 54
D9: No | H9: Member | I9: =IF(AND(K9="",J9=""),"",CONCATENATE(J9,", ",K9)) -> Alfornon, Bobby | J9: Alfornon | K9: Bobby | L9: A | M9: Male | N9: BULACAN | Q9: 0926-803-3837 | S9: 25305 | T9: =IF(S9="","",DATEDIF(S9,TODAY(),"Y")) -> 57
D10: Yes | F10: Benjamin | H10: Member | I10: =IF(AND(K10="",J10=""),"",CONCATENATE(J10,", ",K10)) -> Amistad, Joseph Sinesin | J10: Amistad | K10: Joseph Sinesin | L10: H | M10: Male | N10: 7 Purok 1 | O10: Irisan | Q10: 0918-502-8785 | R10: jamistad82@gmail.com | S10: 30079 | T10: =IF(S10="","",DATEDIF(S10,TODAY(),"Y")) -> 44 | U10: Baguio City | V10: Amistad, Snider Sr. | W10: Amistad, Rosemarie H. | X10: Yes | Y10: December 1996 | Z10: Yes | AA10: April 1997 | AB10: Roman Catholic | AC10: B.S.A. | AD10: V.A. - LG (Australia) | AE10: AMD, Music, Discipleship | AG10: Teaching | AJ10: Amistad, Hadassah Olive C. | AL10: Yes | AM10: Yes | AN10: Amistad, Hadassah Olive C. | AO10: Same as Home Address | AP10: Spouse | AQ10: 0946-457-5445
D11: No | I11: =IF(AND(K11="",J11=""),"",CONCATENATE(J11,", ",K11)) -> Amplogio, Charlie | J11: Amplogio | K11: Charlie | T11: =IF(S11="","",DATEDIF(S11,TODAY(),"Y"))
D12: No | F12: Dan | H12: Assistant Leader | I12: =IF(AND(K12="",J12=""),"",CONCATENATE(J12,", ",K12)) -> Ancheta, Cris | J12: Ancheta | K12: Cris | M12: Male | N12: 29 Avelino Street | O12: Fairview | Q12: 0942-040-6959 | R12: crisancheta@yahoo.com | S12: 23085 | T12: =IF(S12="","",DATEDIF(S12,TODAY(),"Y")) -> 63
D13: Yes | F13: Reuben | H13: Leader | I13: =IF(AND(K13="",J13=""),"",CONCATENATE(J13,", ",K13)) -> Apilada, Armando | J13: Apilada | K13: Armando | L13: R | M13: Male | N13: #057 Sitio Paltingan | O13: Ambiong, La Trinidad | P13: Brgy. Lipit Norte, Manaoag, Pangasinan | Q13: 0909-572-3317 | S13: 19731 | T13: =IF(S13="","",DATEDIF(S13,TODAY(),"Y")) -> 72 | U13: Manaoag, Pangasinan | V13: Apilada, Adriano N. | W13: Apilada, Gregoria R. | X13: Yes | Y13: February 2004 | Z13: Yes | AA13: March 2004 | AB13: Pentecostal Church of God | AC13: MSCRIM | AD13: Security Officer - UB | AE13: Bible Study - Ambiong and Bineng | AH13: Chess/ Dama | AI13: Painting, Cooking | AJ13: Apilada, Susan B. | AK13: Online Selling | AL13: Yes | AM13: Yes | AN13: Apilada, Susan B. | AO13: Same as Home Address | AP13: Spouse | AQ13: 0935-997-6857
D14: Yes | F14: Benjamin | H14: Member | I14: =IF(AND(K14="",J14=""),"",CONCATENATE(J14,", ",K14)) -> Aragon, Marc Andrew Reli | J14: Aragon | K14: Marc Andrew Reli | L14: M | M14: Male | N14: 8 De Tesis St | O14: Aurora Hill | P14: Los Banos, Laguna | Q14: 0994-371-9691 | S14: 34599 | T14: =IF(S14="","",DATEDIF(S14,TODAY(),"Y")) -> 32 | U14: Athens, Greece | V14: Aragon, Marcelino G. | W14: Aragon, Evangeline M. | X14: Yes | Z14: Yes | AC14: College Level | AD14: MOOG | AE14: CHOIR, Midweek Musician | AF14: Musician | AG14: Singing, Playing Musical Instruments | AH14: Volleyball, Basketball, Badminton, Chess | AI14: Carpentry, Painting, Cooking | AJ14: Aragon, Elaine Marie | AK14: HR Officer | AL14: Yes | AM14: Yes | AN14: Aragon, Elaine Marie | AO14: Same as Home Address | AP14: Spouse | AQ14: 0994-157-8808
D15: Yes | F15: Benjamin | H15: Member | I15: =IF(AND(K15="",J15=""),"",CONCATENATE(J15,", ",K15)) -> Ating, Dwight Paul | J15: Ating | K15: Dwight Paul | L15: C | M15: Male | N15: 33 Purok 8 | O15: Upper Pinget | Q15: 0968-686-9204 | R15: 06dwightpaul@gmail.com | S15: 36189 | T15: =IF(S15="","",DATEDIF(S15,TODAY(),"Y")) -> 27 | U15: Baguio City | V15: Ating, Domingo | W15: Cruz, Liza D. | X15: No | Z15: No | AB15: Roman Catholic | AC15: College Graduate | AD15: DENR - EMB ; EMS I | AH15: Baseball | AI15: Cooking
D16: Yes | F16: Levi | H16: Member | I16: =IF(AND(K16="",J16=""),"",CONCATENATE(J16,", ",K16)) -> Ayungo, Martin Jr | J16: Ayungo | K16: Martin Jr | L16: Charpang | M16: Male | N16: 421 Wednesday Alley | O16: Guisad Central | P16: Baguio City | Q16: 0916-936-4705 | R16: yogmartin@gmail.com | S16: 29831 | T16: =IF(S16="","",DATEDIF(S16,TODAY(),"Y")) -> 45 | U16: Natonin, Mt. Province | V16: Ayungo, Martin K. Sr. | W16: Ayungo, Margarita C. | X16: Yes | Z16: Yes | AB16: Roman Catholic | AC16: High School | AD16: On-Call Driver | AH16: Basketball, Chess/Dama | AJ16: Ayungo, Ailene Baydal | AK16: Entrepreneur | AL16: Yes | AM16: Yes | AN16: Ayungo, Ailene Baydal | AO16: Same as Home Address | AP16: Spouse
D17: Yes | F17: Benjamin | H17: Member | I17: =IF(AND(K17="",J17=""),"",CONCATENATE(J17,", ",K17)) -> Bacsa, Vhal | J17: Bacsa | K17: Vhal | M17: Male | N17: 048-B Boted | O17: Tawang, La Trinidad | P17: La Trinidad, Benguet | Q17: 0967-301-6762 | R17: bryllevhien@gmail.com | S17: 37666 | T17: =IF(S17="","",DATEDIF(S17,TODAY(),"Y")) -> 23 | U17: Baguio City | V17: Santos, Leonardo | W17: Bacsa, Theresa | X17: Yes | Y17: 45536 | Z17: Yes | AA17: 45505 | AC17: High School | AD17: Painter | AG17: Singing, Arts & Deco | AH17: Basketball, badminton | AI17: Painting, Cooking | AJ17: Bacsa, Hyneth Gwenn | AK17: Caregiver | AL17: Yes | AM17: Yes
D18: Yes | F18: Reuben | H18: Member | I18: =IF(AND(K18="",J18=""),"",CONCATENATE(J18,", ",K18)) -> Balinggan, Paul | J18: Balinggan | K18: Paul | L18: D | M18: Male | N18: Kabuyao | O18: Poblacion, Tuba | P18: Tuba, Benguet | Q18: 0918-722-5882 | S18: 19791 | T18: =IF(S18="","",DATEDIF(S18,TODAY(),"Y")) -> 72 | U18: Bakun, Benguet | V18: Balinggan, Pudico | W18: Pongga-as, Apinna | X18: Yes | Z18: Yes | AB18: Roman Catholic | AC18: B.S.N. | AJ18: Balinggan, Mercedes | AL18: Yes | AM18: Yes | AN18: Balinggan, Jurickson | AO18: 7 Lower P. Burgos Street, B.C. | AP18: Son
D19: No | I19: =IF(AND(K19="",J19=""),"",CONCATENATE(J19,", ",K19)) -> Balinggan, Jurickson | J19: Balinggan | K19: Jurickson | T19: =IF(S19="","",DATEDIF(S19,TODAY(),"Y"))
D20: No | H20: Member | I20: =IF(AND(K20="",J20=""),"",CONCATENATE(J20,", ",K20)) -> Bambao, Angel Jr | J20: Bambao | K20: Angel Jr | M20: Male | N20: Balacbac Central | O20: Sto. Tomas Proper | Q20: 0961-921-4697 | S20: 28859 | T20: =IF(S20="","",DATEDIF(S20,TODAY(),"Y")) -> 47
D21: No | F21: Dan | H21: Member | I21: =IF(AND(K21="",J21=""),"",CONCATENATE(J21,", ",K21)) -> Banaag, Gerald | J21: Banaag | K21: Gerald | M21: Male | N21: 120d Lower Kitma | O21: Bakakeng Central | Q21: 0920-858-9898 | R21: aldger8mj@yahoo.com | S21: 28459 | T21: =IF(S21="","",DATEDIF(S21,TODAY(),"Y")) -> 48
D22: No | I22: =IF(AND(K22="",J22=""),"",CONCATENATE(J22,", ",K22)) -> Bañez, Eugene | J22: Bañez | K22: Eugene | L22: C | N22: 7 | O22: Lower Padre Burgos St | T22: =IF(S22="","",DATEDIF(S22,TODAY(),"Y")) | X22: Yes | Z22: Yes | AJ22: Bañez, Gemma | AL22: Yes | AM22: Yes | AO22: Same as Home Address
D23: No | F23: Issachar | H23: Member | I23: =IF(AND(K23="",J23=""),"",CONCATENATE(J23,", ",K23)) -> Bayrante, Ramon | J23: Bayrante | K23: Ramon | L23: B | M23: Male | N23: CHURCH | Q23: 0992-207-7945 | R23: bayranteramon@gmail.com | S23: 24855 | T23: =IF(S23="","",DATEDIF(S23,TODAY(),"Y")) -> 58
D24: Yes | F24: Levi | H24: Leader | I24: =IF(AND(K24="",J24=""),"",CONCATENATE(J24,", ",K24)) -> Bentrez, Isaac | J24: Bentrez | K24: Isaac | M24: Male | N24: 123 Blk 3 | O24: Middle Quirino Hill | Q24: 0977-822-5999 | R24: bentrez231isaac@gmail.com | S24: 29823 | T24: =IF(S24="","",DATEDIF(S24,TODAY(),"Y")) -> 45 | U24: Poblacion, Itogon | V24: Bentrez, Larry Sr. | W24: Bentrez, Genera S. | X24: Yes | Z24: Yes | AC24: College Graduate | AD24: Teacher | AE24: BQM | AG24: Teaching, Literary Composition | AH24: Basketball, Chess/Dama | AI24: Cooking | AJ24: Bentrez, Jacqueline R. | AK24: Teacher | AL24: Yes | AM24: Yes | AN24: Bentrez, Jacqueline R. | AO24: Same as Home Address | AP24: Spouse | AQ24: 0927-211-0251
D25: Yes | F25: Reuben | H25: Member | I25: =IF(AND(K25="",J25=""),"",CONCATENATE(J25,", ",K25)) -> Boteng, Jaime | J25: Boteng | K25: Jaime | L25: S | M25: Male | O25: La Trinidad | P25: La Trinidad, Benguet | Q25: 0949-647-5784 | S25: 16789 | T25: =IF(S25="","",DATEDIF(S25,TODAY(),"Y")) -> 80 | U25: Tadian, Mountain Province | V25: Boteng, Peter | W25: Sibayan, Anita | X25: Yes | Y25: 35235 | Z25: Yes | AA25: 35235 | AB25: Anglican | AC25: Elementary | AI25: Carpentry Works | AJ25: Boteng, Sofia | AN25: Boteng, Angeline | AP25: Daughter | AQ25: 0949-647-5984
D26: Yes | F26: Joseph | H26: Member | I26: =IF(AND(K26="",J26=""),"",CONCATENATE(J26,", ",K26)) -> Cajigal, Rogelio | J26: Cajigal | K26: Rogelio | L26: O | M26: Male | N26: 4 AU/NPC | O26: Central Ambiong, La Trinidad | P26: Infanta, Pangasinan | Q26: 0906-245-1523 / 0994-659-8370 | R26: rogeliogaljica@gmail.com | S26: 22568 | T26: =IF(S26="","",DATEDIF(S26,TODAY(),"Y")) -> 65 | U26: Baguio City | V26: Cajigal, Melanio A. | W26: Cajigal, Erlinda O. | X26: Yes | Y26: 2023 | Z26: Yes | AB26: Roman Catholic | AC26: BS Civil Engineering Graduate | AD26: Retired | AG26: Teaching, Singing, Playing Musical instruments, Arts & Deco | AH26: Chess/ Dama | AI26: Carpentry Works, Mason, Painting, Cooking | AJ26: Cajigal, Nona | AK26: Housekeeper | AL26: Yes | AM26: Not Yet | AN26: Mago, Genno | AO26: 142 Purok 4, Lower Pinget | AP26: Co-employee
D27: Yes | H27: Member | I27: =IF(AND(K27="",J27=""),"",CONCATENATE(J27,", ",K27)) -> Calimlim, Jared | J27: Calimlim | K27: Jared | L27: B. | M27: Male | N27: 1 Purok 5 | O27: Holy Ghost Proper | P27: 524 Penged Nangalisan Tuba Benguet | Q27: 0945-976-6133 | R27: calimlimjared@yahoo.com.ph | S27: 32218 | T27: =IF(S27="","",DATEDIF(S27,TODAY(),"Y")) -> 38 | U27: Itogon Benguet | V27: Calimlim, Romulo | W27: Calimlim, Juliana | X27: Yes | Y27: 43408 | Z27: Yes | AA27: 43485 | AB27: Roman Catholic | AC27: College Graduate | AD27: Facilities Operations & Maintenance Tech. - T.I. | AE27: AMD; Choir | AG27: Singing; Playing Musical Instruments | AH27: Basketball | AI27: Building Wiring | AJ27: Calimlim, Jamielyn R. | AK27: House Wife | AL27: Yes | AM27: Yes | AN27: Calimlim, Jamielyn R. | AO27: Same as Home Address | AP27: Spouse | AQ27: 0963-888-1394
D28: No | F28: Dan | H28: Member | I28: =IF(AND(K28="",J28=""),"",CONCATENATE(J28,", ",K28)) -> Camodag, Audie | J28: Camodag | K28: Audie | M28: Male | O28: Middle Quirino Hill | Q28: 0938-627-6215 | S28: 26067 | T28: =IF(S28="","",DATEDIF(S28,TODAY(),"Y")) -> 55
D29: No | F29: Issachar | H29: Assistant Leader | I29: =IF(AND(K29="",J29=""),"",CONCATENATE(J29,", ",K29)) -> Caragay, Dennis | J29: Caragay | K29: Dennis | L29: A | M29: Male | N29: 126 | O29: Central Fairview | Q29: 0906-077-3464 | R29: denniscaragay34@gmail.com | S29: 29934 | T29: =IF(S29="","",DATEDIF(S29,TODAY(),"Y")) -> 44
D30: Yes | F30: Joseph | H30: Member | I30: =IF(AND(K30="",J30=""),"",CONCATENATE(J30,", ",K30)) -> Castro, Simplicio Jr | J30: Castro | K30: Simplicio Jr | L30: L | M30: Male | N30: 7 Purok 1 | O30: Irisan | Q30: 0946-051-3945 | S30: 21877 | T30: =IF(S30="","",DATEDIF(S30,TODAY(),"Y")) -> 66 | U30: Baguio City | V30: Castro, Simplicio Sr. | W30: Castro, Brigida | X30: Yes | Y30: 1998 | Z30: Yes | AA30: 1998 | AB30: Roman Catholic | AC30: High School | AD30: Businessman | AG30: Driver/Mechanic | AH30: Chess/ Dama | AI30: Carpentry Works, Mason, Welding | AJ30: Castro, Rizalina, Camora | AL30: Yes | AM30: Yes | AN30: Castro, Rizalina, Camora | AO30: Same as Home Address | AP30: Spouse
D31: Yes | F31: Judah | H31: Leader | I31: =IF(AND(K31="",J31=""),"",CONCATENATE(J31,", ",K31)) -> Cayandag, Jimmy | J31: Cayandag | K31: Jimmy | M31: Male | N31: 224 | O31: Poliwes | S31: 29168 | T31: =IF(S31="","",DATEDIF(S31,TODAY(),"Y")) -> 46 | U31: Itogon, Benguet | V31: Cayandag, Julian Sr. | W31: Cayandag, Lolita | X31: Yes | Y31: 2005 | Z31: Yes | AA31: 2005 | AB31: Roman Catholic | AC31: College Level | AD31: Gov't Employee - Baguio City Hall | AJ31: Cayandag, Marilou | AK31: Gov't Employee | AL31: Yes | AM31: Yes | AN31: Cayandag, Marilou | AO31: Same as Home Address | AP31: Spouse | AQ31: 0918-807-5193
D32: Yes | F32: Reuben | H32: Member | I32: =IF(AND(K32="",J32=""),"",CONCATENATE(J32,", ",K32)) -> Coyasan, Julio | J32: Coyasan | K32: Julio | L32: M | M32: Male | N32: OE26 Dengsi | O32: Tawang, La Trinidad | P32: Tawang, La Trinidad | Q32: 0939-567-3119 | S32: 23196 | T32: =IF(S32="","",DATEDIF(S32,TODAY(),"Y")) -> 63 | U32: Mankayan, Benguet | V32: Coyasan, Quintin | W32: Coyasan, Magdalina M. | X32: Yes | Y32: 34570 | Z32: Yes | AA32: 34570 | AC32: Vocational Graduate | AD32: Reflexologist | AG32: Singin, Playing Musical Instruments | AH32: Badminton, Chess/Dama | AI32: Carpentry Works, Welding | AJ32: Coyasan, Auxcinia R. | AK32: Housekeeper | AL32: Yes | AM32: Yes | AN32: Coyasan, Jayson | AO32: Same as Home Address | AP32: Son
D33: Yes | F33: Judah | H33: Member | I33: =IF(AND(K33="",J33=""),"",CONCATENATE(J33,", ",K33)) -> Coyasan, Priston | J33: Coyasan | K33: Priston | M33: Male | N33: 7 | O33: Pinsao Pilot Project | P33: Ambiong, La Trinidad | Q33: 0918-620-3449 | S33: 28111 | T33: =IF(S33="","",DATEDIF(S33,TODAY(),"Y")) -> 49 | U33: Mankayan, Benguet | V33: Coyasan, Quintin | W33: Coyasan, Magdalina M. | X33: Yes | Y33: 1998 | Z33: Yes | AA33: 2001 | AG33: Singing | AH33: Basketball | AI33: Carpentry Works | AJ33: Coyasan, Mary Jhoe | AL33: Yes | AM33: Yes | AN33: Coyasan, Mary Jhoe | AP33: Spouse
D34: No | F34: Levi | H34: Member | I34: =IF(AND(K34="",J34=""),"",CONCATENATE(J34,", ",K34)) -> Cruz, Aron | J34: Cruz | K34: Aron | M34: Male | N34: Block 3, 123 | O34: Middle Quirino Hill | Q34: 0956-276-5500 | S34: 30235 | T34: =IF(S34="","",DATEDIF(S34,TODAY(),"Y")) -> 44
D35: Yes | F35: Joseph | H35: Member | I35: =IF(AND(K35="",J35=""),"",CONCATENATE(J35,", ",K35)) -> Cutay, Digno | J35: Cutay | K35: Digno | L35: Gawec | M35: Male | N35: 27 Purok 5 F Cutay Drive | O35: Irisan | P35: Tadiangan Tuba, Benguet | Q35: 0910-922-5223 / 661-7508 | R35: cutaydigno@gmail.com | S35: 25149 | T35: =IF(S35="","",DATEDIF(S35,TODAY(),"Y")) -> 57 | U35: Tadian, Mountain Province | V35: Cutay, Frnandi Sr. | W35: Cutay, Fely | X35: Yes | Y35: 34337 | Z35: Yes | AA35: August 1994 | AB35: Roman Catholic | AC35: High School Graduate | AD35: Driver | AE35: AMM President | AF35: AMM Vice President | AH35: Volleyball | AJ35: Cutay, Regina A. | AK35: Housekeeper | AL35: Yes | AM35: Yes | AN35: Cutay, Regina A. | AO35: Same as Home Address | AP35: Spouse | AQ35: 0910-449-5756
D36: No | F36: Benjamin | H36: Assistant Leader | I36: =IF(AND(K36="",J36=""),"",CONCATENATE(J36,", ",K36)) -> Cutay, John Mark | J36: Cutay | K36: John Mark | L36: A | M36: Male | N36: CHURCH | P36: Suyoc Mankayan, Benguet | Q36: 0930-652-3111 | R36: cutayjohnmark@gmail.com | S36: 35600 | T36: =IF(S36="","",DATEDIF(S36,TODAY(),"Y")) -> 29 | U36: Mankayan, Benguet | V36: Cutay, Digno G. | W36: Cutay, Regina A. | X36: Yes | Y36: 2011 | Z36: Yes | AA36: 2011 | AC36: College Graduate | AD36: Quality Inspector - MOOG | AE36: Media Team | AF36: Ushering/Choir | AG36: Playing Musical Instruments | AH36: Basketball, Badminton, Chess/Dama | AJ36: Cutay, Johanna Faith B. | AK36: Finance/Teacher | AL36: Yes | AM36: Yes
D37: Yes | F37: Dan | H37: Member | I37: =IF(AND(K37="",J37=""),"",CONCATENATE(J37,", ",K37)) -> Dagupen, Franklin | J37: Dagupen | K37: Franklin | L37: C | M37: Male | N37: 19 Purok 28 | O37: Irisan | P37: Balakbak Kapangan, Benguet | Q37: 0918-358-7028 | R37: frada_eleot.sern@yahoo.com | S37: 26695 | T37: =IF(S37="","",DATEDIF(S37,TODAY(),"Y")) -> 53 | U37: Kapangan, Benguet | V37: Dagupen, Valdez | W37: Dagupen, Aurea Calpio | X37: Yes | Y37: 1994 | Z37: Yes | AA37: 2002 | AD37: Electrician | AJ37: Dagupen, Josephine | AK37: Vendor | AL37: Yes | AM37: Yes | AN37: Dagupen, Josephine | AO37: Same as Home Address | AP37: Spouse | AQ37: 0919-226-4571
D38: Yes | F38: Reuben | H38: Member | I38: =IF(AND(K38="",J38=""),"",CONCATENATE(J38,", ",K38)) -> Dangla, Constancio Jr | J38: Dangla | K38: Constancio Jr | L38: C | M38: Male | N38: NHA | O38: Tadiangan, Tuba | P38: Tadiangan Tuba, Benguet | Q38: 0901-491-3067 | S38: 23464 | T38: =IF(S38="","",DATEDIF(S38,TODAY(),"Y")) -> 62 | U38: Cervantes, Ilocos Sur | V38: Dangla, Paulino | W38: Dangla, Carmen | X38: Yes | Y38: August 1990 | Z38: Yes | AA38: 1998 | AB38: Roman Catholic | AC38: College Graduate | AI38: Mason, Laborer | AJ38: Dangla, Nancy Buya | AK38: Housekeeper | AL38: Yes | AM38: Yes | AN38: Dangla, Hiede Cattleyah | AO38: Same as Home Address | AP38: Daughter | AQ38: 0921-743-2975
D39: Yes | F39: Judah | H39: Member | I39: =IF(AND(K39="",J39=""),"",CONCATENATE(J39,", ",K39)) -> Daskeo, Klient Patrick | J39: Daskeo | K39: Klient Patrick | M39: Male | N39: Prk 6 Brookspoint | O39: Aurora Hill | P39: Tadian, Mt. Province | Q39: 0932-740-4983 | R39: klintong3766@gmail.com | S39: 30635 | T39: =IF(S39="","",DATEDIF(S39,TODAY(),"Y")) -> 42 | U39: Makati City | V39: Daskeo, Patrick | W39: Daskeo, Emma | X39: Yes | Y39: 41624 | Z39: Yes | AA39: 41594 | AC39: College Level | AD39: Online ESL Teacher | AE39: Choir, AMM | AF39: AMM | AG39: Teaching, Singing, Arts & Deco | AH39: Volleyball, Basketball | AI39: Mason, Cooking | AJ39: Daskeo, May | AK39: Elementary Teacher | AL39: Yes | AM39: Yes | AN39: Daskeo, May | AO39: Same as Home Address | AP39: Spouse | AQ39: 0960-613-3613
D40: Yes | F40: Issachar | H40: Leader | I40: =IF(AND(K40="",J40=""),"",CONCATENATE(J40,", ",K40)) -> De Castro, Marlon | J40: De Castro | K40: Marlon | L40: B | M40: Male | N40: 25B Purok 4 | O40: Bakakeng Norte | P40: Baguio City | Q40: 0917-972-0679 | S40: 29889 | T40: =IF(S40="","",DATEDIF(S40,TODAY(),"Y")) -> 44 | U40: Antipolo, Rizal | V40: De Castro, Alejandro | W40: De Castro, Nenita B. | X40: Yes | Y40: 35328 | Z40: Yes | AA40: 35426 | AB40: Apostolic Pentecostal Church | AC40: College Level | AD40: Apartment/ Transient Manager | AE40: Music, Sunday School | AF40: Ushering | AG40: Teaching, Singing | AH40: Volleyball, Chess/Dama | AI40: Carpentry Works, Cooking | AJ40: De Castro, Rebecca | AK40: Apartment/ Transient Manager | AL40: Yes | AM40: Yes | AN40: De Castro, Rebecca | AO40: Same as Home Address | AP40: Spouse | AQ40: 0906-378-5711
D41: No | F41: Judah | H41: Member | I41: =IF(AND(K41="",J41=""),"",CONCATENATE(J41,", ",K41)) -> De Guzman, Randy | J41: De Guzman | K41: Randy | L41: L | M41: Male | N41: OD 348 Banig | O41: Tawang, La Trinidad | R41: msjdeguzman07@gmail.com | S41: 26213 | T41: =IF(S41="","",DATEDIF(S41,TODAY(),"Y")) -> 55
D42: Yes | F42: Levi | H42: Member | I42: =IF(AND(K42="",J42=""),"",CONCATENATE(J42,", ",K42)) -> De Vera, Jaime Jr | J42: De Vera | K42: Jaime Jr | M42: Male | N42: 9 | O42: Upper Brookside | P42: Benguet | Q42: 0999-876-9801 | R42: jaimedevera@gmail.com | S42: 30990 | T42: =IF(S42="","",DATEDIF(S42,TODAY(),"Y")) -> 41 | U42: Benguet | V42: De Vera, Jaime Sr. | W42: Dayao, Veronica | X42: Yes | AC42: High School Graduate
D43: No | F43: Benjamin | H43: Member | I43: =IF(AND(K43="",J43=""),"",CONCATENATE(J43,", ",K43)) -> Devera, Junar | J43: Devera | K43: Junar | M43: Male | T43: =IF(S43="","",DATEDIF(S43,TODAY(),"Y"))
D44: Yes | I44: =IF(AND(K44="",J44=""),"",CONCATENATE(J44,", ",K44)) -> Eraldo, Federico Jr | J44: Eraldo | K44: Federico Jr | L44: T | N44: 120 Purok 5 Amparo Heights | O44: Camp 7 | P44: Hinoba-an Negros Occidental | Q44: 0955-751-4955 | S44: 23228 | T44: =IF(S44="","",DATEDIF(S44,TODAY(),"Y")) -> 63 | U44: Negros Occidental | V44: Eraldo, Federico Sr. | W44: Eraldo, Engracia T. | X44: Yes | Y44: 30300 | Z44: Yes | AA44: 36353 | AC44: Gigh School Graduate | AD44: Carpenter; Mason | AG44: Singing | AH44: Basketball | AI44: Carpentry Works; Mason | AJ44: Eraldo, Jenelyn P. | AK44: House Wife | AL44: Yes | AM44: Yes | AN44: Eraldo, Jenelyn | AO44: Same as Home Address | AP44: Wife | AQ44: 0994-184-9783
D45: Yes | H45: Member | I45: =IF(AND(K45="",J45=""),"",CONCATENATE(J45,", ",K45)) -> Esteban, Clint | J45: Esteban | K45: Clint | M45: Male | N45: 5026 Purok 5 | O45: Kias | P45: Abatan Buguias, Benguet | Q45: 0995-189-4962 | R45: clintse29@gmail.com | S45: 32902 | T45: =IF(S45="","",DATEDIF(S45,TODAY(),"Y")) -> 36 | U45: Abatan Buguias, Benguet | V45: Esteban, Leopoldo | W45: Esteban, Duela | X45: Yes | Y45: 37759 | Z45: Yes | AA45: 35221 | AC45: BS Nursing | AH45: Basketball | AJ45: Esteban, Juvette Ann | AK45: Physician | AL45: Yes | AM45: Yes | AN45: Esteban, Juvette Ann | AO45: Same as Home Address | AP45: Spouse | AQ45: 0917-125-6408
D46: No | H46: Member | I46: =IF(AND(K46="",J46=""),"",CONCATENATE(J46,", ",K46)) -> Estipular, Oscar Sr | J46: Estipular | K46: Oscar Sr | M46: Male | N46: 089 Amsing, Siapnon Rd. | O46: Pacdal | P46: Naguilian, La Union | Q46: 0945-823-8754 | S46: 20052 | T46: =IF(S46="","",DATEDIF(S46,TODAY(),"Y")) -> 71 | U46: Naguilian, La Union | V46: Estipular, Rufo | W46: Estipular, Manuela | AB46: Roman Catholic | AC46: High School Graduate | AD46: Retired | AH46: Volleyball, Basketball, Chess/Dama | AI46: Cooking | AJ46: Estipular, Corazon | AK46: Housekeeper | AL46: Yes | AM46: Yes | AN46: Estipular, Corazon | AO46: Same as Home Address | AP46: Spouse | AQ46: 0915-332-5884
D47: No | F47: Issachar | H47: Member | I47: =IF(AND(K47="",J47=""),"",CONCATENATE(J47,", ",K47)) -> Garcia, Manuel | J47: Garcia | K47: Manuel | M47: Male | N47: Buted, Tawang | O47: La Trinidad | P47: Benguet | Q47: 0993-114-7199 | S47: 29680 | T47: =IF(S47="","",DATEDIF(S47,TODAY(),"Y")) -> 45 | U47: Sison, Pangasinan
D48: Yes | F48: Benjamin | H48: Member | I48: =IF(AND(K48="",J48=""),"",CONCATENATE(J48,", ",K48)) -> Ibañez, Ramel | J48: Ibañez | K48: Ramel | L48: P | M48: Male | N48: Ph2 | O48: Dreamland | Q48: 0929-197-2755 | R48: ramelibanez03@gmail.com | S48: 32114 | T48: =IF(S48="","",DATEDIF(S48,TODAY(),"Y")) -> 38 | U48: Capiz | V48: Ibañez, Ramon | W48: Miralles, Salvacion | X48: Yes | Y48: 1999 | Z48: Yes | AA48: 2004 | AC48: High School Graduate | AE48: Musician, Sunday School | AF48: AMM President, Music, Worship Leader | AG48: Singing, Playing Musical Instruments, Literary Composition | AH48: Chess/ Dama | AJ48: Ibañez, Julie | AK48: Virtual Assistant | AL48: Yes | AM48: Yes | AN48: Ibañez, Julie | AO48: Same as Home Address | AP48: Spouse | AQ48: 0908-949-3553
D49: No | F49: Joseph | H49: Member | I49: =IF(AND(K49="",J49=""),"",CONCATENATE(J49,", ",K49)) -> Joaquin, Domingo | J49: Joaquin | K49: Domingo | L49: F | M49: Male | N49: 151 Chamomile St. Sunnyside | O49: Fairview | Q49: 0908-984-0285 | S49: 18208 | T49: =IF(S49="","",DATEDIF(S49,TODAY(),"Y")) -> 76
D50: Yes | F50: Joseph | H50: Member | I50: =IF(AND(K50="",J50=""),"",CONCATENATE(J50,", ",K50)) -> Kebasen, Boni | J50: Kebasen | K50: Boni | M50: Male | N50: 82 Amistad | O50: Camp 7 | Q50: 0908-202-7848 | R50: bkebasen@yahoo.com | S50: 19356 | T50: =IF(S50="","",DATEDIF(S50,TODAY(),"Y")) -> 73 | U50: Tadian, Mountain Province | V50: Kebasen, George | W50: Kebasen, Rufina | X50: Yes | Y50: June 1980 | Z50: Yes | AA50: June 1980 | AC50: College Graduate | AD50: Retired | AF50: Teaching | AG50: Teaching | AJ50: Kebasen, Dorothy | AK50: Housekeeper | AL50: Yes | AM50: Yes | AN50: Kebasen, Dorothy | AO50: Same as Home Address | AP50: Spouse
D51: Yes | F51: Reuben | H51: Member | I51: =IF(AND(K51="",J51=""),"",CONCATENATE(J51,", ",K51)) -> Kiwil, Dampo | J51: Kiwil | K51: Dampo | M51: Male | O51: Bineng, La Trinidad | P51: Bineng, La Trinidad | Q51: 0981-015-1086 | T51: =IF(S51="","",DATEDIF(S51,TODAY(),"Y")) | X51: Yes | AB51: Trinity | AD51: Farmer | AJ51: Kiwil, Betty
D52: Yes | F52: Judah | H52: Member | I52: =IF(AND(K52="",J52=""),"",CONCATENATE(J52,", ",K52)) -> Kiwil, Jonie | J52: Kiwil | K52: Jonie | M52: Male | O52: Bineng, La Trinidad | P52: Bineng, La Trinidad | Q52: 0963-115-1724 | S52: 30309 | T52: =IF(S52="","",DATEDIF(S52,TODAY(),"Y")) -> 43 | U52: Bineng, La Trinidad | V52: Kiwil, Dampa | W52: Kiwil, Betty | X52: Yes | Z52: Yes | AA52: 45431 | AB52: Trinity | AD52: Farmer | AJ52: Kiwil, Dailyn | AN52: Kiwil, Dailyn | AP52: Spouse
D53: No | F53: Joseph | H53: Assistant Leader | I53: =IF(AND(K53="",J53=""),"",CONCATENATE(J53,", ",K53)) -> Langgoy, Marvin | J53: Langgoy | K53: Marvin | L53: C | M53: Male | N53: Luneta Loacan | O53: Itogon | Q53: 0966-455-8758 | S53: 28286 | T53: =IF(S53="","",DATEDIF(S53,TODAY(),"Y")) -> 49
D54: Yes | H54: Member | I54: =IF(AND(K54="",J54=""),"",CONCATENATE(J54,", ",K54)) -> Laresma, Nestor Jr | J54: Laresma | K54: Nestor Jr | L54: M | N54: AR 132-E Riverside | O54: Ambiong, La Trinidad | Q54: 0935-741-2313 | R54: nestorlaresmajr022531@gmail.com | S54: 32758 | T54: =IF(S54="","",DATEDIF(S54,TODAY(),"Y")) -> 37 | U54: Isaberlla | V54: Laresma, Nestor Sr. | W54: Laresma, Lirio M. | X54: Yes | Y54: 42295 | Z54: Yes | AA54: 43059 | AB54: Catholic; AG | AC54: College Graduate - BS Mechanical Engr. | AD54: Facilities O&M Mngr. - T.I. | AF54: Minister (Preacher/Teacher) | AG54: Teaching | AH54: Basketball; Billiards | AI54: Aircon/Fire Pro - Design & Sign & Seal | AJ54: Laresma, Arlene G. | AK54: Housewife | AL54: Yes | AM54: Yes | AN54: Laresma, Arlene G. | AO54: Same as Home Address | AP54: Spouse | AQ54: 0910-249-6621
D55: No | F55: Joseph | H55: Leader | I55: =IF(AND(K55="",J55=""),"",CONCATENATE(J55,", ",K55)) -> Lipaen, Rosario | J55: Lipaen | K55: Rosario | L55: D | M55: Male | N55: AC-017C | O55: Central Ambiong, La Trinidad | Q55: 0927-486-4406 | R55: drosariol@gmail.com | S55: 25101 | T55: =IF(S55="","",DATEDIF(S55,TODAY(),"Y")) -> 58
D56: No | I56: =IF(AND(K56="",J56=""),"",CONCATENATE(J56,", ",K56)) -> Lipaen, Sonny | J56: Lipaen | K56: Sonny | T56: =IF(S56="","",DATEDIF(S56,TODAY(),"Y"))
D57: No | F57: Benjamin | H57: Member | I57: =IF(AND(K57="",J57=""),"",CONCATENATE(J57,", ",K57)) -> Liwana, Harvey | J57: Liwana | K57: Harvey | L57: G | M57: Male | N57: Purok 20 NPC Subd. | O57: Irisan | P57: Poblacion Kabayan, Benguet | Q57: 0947-426-4761 | R57: hliwana@gmail.com | S57: 32223 | T57: =IF(S57="","",DATEDIF(S57,TODAY(),"Y")) -> 38 | U57: Kabayan, Benguet | V57: Liwana Billy T. | W57: Liwana, Myriana Delia | X57: Yes | Y57: 2016 | AB57: UCCPC | AC57: College Level | AD57: Business | AG57: Singing | AH57: Volleyball, baseball | AI57: Cooking
D58: No | F58: Dan | H58: Leader | I58: =IF(AND(K58="",J58=""),"",CONCATENATE(J58,", ",K58)) -> Mago, Genno | J58: Mago | K58: Genno | L58: P | M58: Male | N58: 142 Purok 4 | O58: Lower Pinget | Q58: 0926-215-8054 | R58: genyes88@gmail.com | S58: 24429 | T58: =IF(S58="","",DATEDIF(S58,TODAY(),"Y")) -> 59
D59: Yes | F59: Reuben | H59: Member | I59: =IF(AND(K59="",J59=""),"",CONCATENATE(J59,", ",K59)) -> Matias, Demetrio | J59: Matias | K59: Demetrio | M59: Male | N59: 35 Smith Drive Purok 8 | O59: Asin Road | Q59: 0909-566-4629 | S59: 20513 | T59: =IF(S59="","",DATEDIF(S59,TODAY(),"Y")) -> 70 | U59: Atok, Benguet | X59: Yes | Y59: November 1980 | Z59: Yes | AA59: December 1980 | AD59: Retired | AF59: Teaching, Singing, Ushering | AG59: Teaching | AJ59: Matias, Remedios | AK59: Housekeeper | AL59: Yes | AM59: Yes | AN59: Matias, Remedios | AP59: Spouse
D60: Yes | F60: Issachar | H60: Member | I60: =IF(AND(K60="",J60=""),"",CONCATENATE(J60,", ",K60)) -> Naimes, Gaston | J60: Naimes | K60: Gaston | L60: T | M60: Male | N60: Rocky Side | O60: Lubas, La Trinidad | P60: Lubas La Trinidad, Benguet | Q60: 0965-254-9915 | R60: gastonnaimes5247@gmail.com | S60: 26169 | T60: =IF(S60="","",DATEDIF(S60,TODAY(),"Y")) -> 55 | U60: Natonin, Mt. Province | V60: Naimes, Martin | W60: Naimes, Primitiva | X60: Yes | Y60: 1996 | Z60: Yes | AA60: 1996 | AB60: Roman Catholic | AC60: College Level | AD60: Community Dev't Worker - DSWD CAR | AF60: AMF Secretary, Choir Member | AG60: Singing | AH60: Volleyball | AI60: Carpentry Works | AJ60: Naimes, Melecia | AK60: Teaching | AL60: Yes | AM60: Yes | AN60: Naimes, Melecia | AO60: Same as Home Address | AP60: Spouse | AQ60: 0960-652-4642
D61: Yes | F61: Judah | H61: Member | I61: =IF(AND(K61="",J61=""),"",CONCATENATE(J61,", ",K61)) -> Pacsi, Randy | J61: Pacsi | K61: Randy | M61: Male | N61: 54A Dapiting | O61: Alapang, La Trinidad | P61: Benguet | Q61: 0948-498-9310 | R61: rhanzdoc575@gmail.com | S61: 27890 | T61: =IF(S61="","",DATEDIF(S61,TODAY(),"Y")) -> 50 | U61: Mankayan, Benguet | X61: Yes | Y61: 2007 | Z61: Yes | AA61: 1999 | AB61: Roman Catholic, Baptist | AC61: College Degree | AD61: Faculty - BSU | AG61: Teaching, Singing, Playing Musical instruments | AH61: Badminton | AJ61: Pacsi, Maricel | AL61: Yes | AM61: Yes
D62: Yes | F62: Dan | H62: Member | I62: =IF(AND(K62="",J62=""),"",CONCATENATE(J62,", ",K62)) -> Pay-an, Joel | J62: Pay-an | K62: Joel | L62: Inayos | M62: Male | N62: 01-B Purok 1 | O62: Irisan | P62: Lamtang La Trinidad, benguet | Q62: 0927-263-2864 | S62: 24677 | T62: =IF(S62="","",DATEDIF(S62,TODAY(),"Y")) -> 59 | U62: Baguio City | V62: Pay-an, Samuel | W62: Pay-an, Pelomina | X62: Yes | Y62: 2003 | Z62: Yes | AB62: Roman Catholic | AC62: College Graduate | AJ62: Pay-an, Elizabeth Cutay | AK62: Housekeeper | AL62: Yes | AM62: Yes | AN62: Pay-an, Elizabeth Cutay | AO62: Same as Home Address | AP62: Spouse | AQ62: 0908-328-5494
D63: Yes | F63: Reuben | H63: Assistant Leader | I63: =IF(AND(K63="",J63=""),"",CONCATENATE(J63,", ",K63)) -> Prado, Ramon | J63: Prado | K63: Ramon | M63: Male | N63: 266 Lower Cypress Purok 14 | O63: Irisan | P63: Baguio City | Q63: 0948-702-4869 | S63: 21428 | T63: =IF(S63="","",DATEDIF(S63,TODAY(),"Y")) -> 68 | U63: Negros, Occidental | V63: Prado, Alex | W63: Prado, Rosita | X63: Yes | Y63: 33779 | AB63: Roman Catholic | AC63: College Undergraduate | AD63: Taxi Driver | AE63: AMM, Driver | AF63: AMM Secretary | AG63: Singing | AH63: Basketball | AI63: Driving | AJ63: Prado, Phebe | AK63: Housekeeper | AL63: Yes | AM63: Yes | AN63: Prado, Phebe | AO63: Same as Home Address | AP63: Spouse | AQ63: 0950-583-3317
D64: Yes | H64: Member | I64: =IF(AND(K64="",J64=""),"",CONCATENATE(J64,", ",K64)) -> Pulicay, Mark Angelo | J64: Pulicay | K64: Mark Angelo | L64: A | M64: Male | N64: Ap31 Sitio Paltingan | O64: Ambiong, La Trinidad | P64: Sta. Barbara, Panasinan | Q64: 0912-918-0646 | S64: 29502 | T64: =IF(S64="","",DATEDIF(S64,TODAY(),"Y")) -> 46 | U64: Sta. Barbara, Panasinan | V64: Pulicay, Marcelino | W64: Pulicay, Lilia | X64: Yes | Z64: Yes | AB64: Roman Catholic | AC64: High School Graduate | AD64: Ison Company | AJ64: Pulicay, Janice | AK64: Housekeeper | AL64: Yes | AM64: Yes | AN64: Pulicay, Janice | AO64: Same as Home Address | AP64: Spouse | AQ64: 0919-890-9185
D65: Yes | F65: Benjamin | H65: Member | I65: =IF(AND(K65="",J65=""),"",CONCATENATE(J65,", ",K65)) -> Quezon, Chris John | J65: Quezon | K65: Chris John | M65: Male | O65: Bineng, La Trinidad | P65: Bineng, La Trinidad | Q65: 0909-983-3811 | S65: 34598 | T65: =IF(S65="","",DATEDIF(S65,TODAY(),"Y")) -> 32 | U65: Baguio City | V65: Robert | W65: Christina | X65: Yes | Y65: 43639 | Z65: Yes | AC65: College Level | AD65: Farming | AJ65: Quezon, Prescilla | AK65: Housekeeper | AL65: Yes | AM65: Yes | AN65: Christina | AO65: Loakan
D66: Yes | H66: Member | I66: =IF(AND(K66="",J66=""),"",CONCATENATE(J66,", ",K66)) -> Reyes, Manolo | J66: Reyes | K66: Manolo | L66: A | M66: Male | P66: Hagonoy, Bulacan | Q66: 0927-716-1227 | S66: 28575 | T66: =IF(S66="","",DATEDIF(S66,TODAY(),"Y")) -> 48 | U66: Hagonoy, Bulacan | V66: Reyes, Carlos S. | W66: Reyes, Anicia Galang | X66: Yes | Z66: Yes | AG66: Singing, Playing Musical Instruments | AH66: Basketball | AI66: Cooking | AJ66: Reyes, Virjelyn | AL66: Yes | AM66: Not Yet
D67: Yes | F67: Levi | H67: Member | I67: =IF(AND(K67="",J67=""),"",CONCATENATE(J67,", ",K67)) -> Rivera, Jay | J67: Rivera | K67: Jay | L67: J | M67: Male | N67: Apugan | O67: Sto. Tomas | P67: Benguet | Q67: 0926-096-0236 | S67: 32239 | T67: =IF(S67="","",DATEDIF(S67,TODAY(),"Y")) -> 38 | U67: Baguio City | V67: Rivera, Rizaldy | W67: Rivera, Evangeline | X67: Yes | Z67: Yes | AC67: High School Graduate | AH67: Basketball | AI67: Welding | AJ67: Imbang, Aileen | AL67: Yes | AM67: Yes | AN67: Imbang, Aileen | AO67: Same as Home Address
D68: No | F68: Judah | H68: Member | I68: =IF(AND(K68="",J68=""),"",CONCATENATE(J68,", ",K68)) -> Sawad, Arthur | J68: Sawad | K68: Arthur | M68: Male | N68: 139C San Carlos Heights Rd | O68: Irisan | Q68: 0976-000-2618 | R68: arthur.sawad@yahoo.com | S68: 27603 | T68: =IF(S68="","",DATEDIF(S68,TODAY(),"Y")) -> 51
D69: Yes | F69: Benjamin | H69: Member | I69: =IF(AND(K69="",J69=""),"",CONCATENATE(J69,", ",K69)) -> Sayan, Scheychelles Aries | J69: Sayan | K69: Scheychelles Aries | M69: Male | N69: L-B11 Roadside 1 | O69: Lubas, La Trinidad | Q69: 0917-620-8243 | R69: aries.sai.007@gmail.com | S69: 33000 | T69: =IF(S69="","",DATEDIF(S69,TODAY(),"Y")) -> 36 | U69: Baguio City | V69: Sayan, Domingo Sr. | W69: Sayan, Grace | X69: Yes | Y69: November 2015 | Z69: Yes | AA69: 2024 | AB69: Roman Catholic, Baptist | AC69: College | AD69: Manulife IT Delivery | AG69: Photography | AH69: Basketball | AJ69: Sayan, Jovelyn | AK69: Housekeeper | AL69: Yes | AM69: Yes | AN69: Sayan, Jovelyn | AO69: Same as Home Address | AP69: Spouse | AQ69: 0998-578-5773
D70: Yes | F70: Benjamin | H70: Member | I70: =IF(AND(K70="",J70=""),"",CONCATENATE(J70,", ",K70)) -> Soriano, Cedric Antonio | J70: Soriano | K70: Cedric Antonio | L70: H | M70: Male | N70: Ap31 Sitio Paltingan | O70: Ambiong, La Trinidad | P70: Caloocan City, NCR | Q70: 0906-084-9244 | S70: 32163 | T70: =IF(S70="","",DATEDIF(S70,TODAY(),"Y")) -> 38 | U70: Baguio City | V70: Soriano, Isidro G. | W70: Soriano, Carmen H. | X70: Yes | Y70: September 2022 | Z70: Yes | AA70: April 2021 | AB70: Jehovah's Witnesses | AC70: BSHRM College Graduate | AD70: Inline English Tutor | AE70: Choir | AG70: Teaching, Singing | AH70: Chess/ Dama | AI70: Cooking | AJ70: Soriano, Esmeralda A. | AK70: Self-employed | AL70: Yes | AM70: Yes | AN70: Soriano, Esmeralda A. | AO70: Same as Home Address | AP70: Spouse | AQ70: 0999-706-2328
D71: No | F71: Issachar | H71: Member | I71: =IF(AND(K71="",J71=""),"",CONCATENATE(J71,", ",K71)) -> Talbo, Tony | J71: Talbo | K71: Tony | M71: Male | O71: Navy Base | P71: Sta. Maria, Pangasinan | Q71: 0930-919-6308 | S71: 24960 | T71: =IF(S71="","",DATEDIF(S71,TODAY(),"Y")) -> 58 | U71: Sta. Maria, Pangasinan | X71: Yes | AB71: Firstborn Church, Sta. Maria
D72: No | F72: Levi | H72: Assistant Leader | I72: =IF(AND(K72="",J72=""),"",CONCATENATE(J72,", ",K72)) -> Talbo, Michael | J72: Talbo | K72: Michael | M72: Male | N72: 086 Purok 6 St. Joseph | O72: Lower Navy Base | Q72: 0905-700-0499 | S72: 29401 | T72: =IF(S72="","",DATEDIF(S72,TODAY(),"Y")) -> 46
D73: No | F73: Issachar | H73: Member | I73: =IF(AND(K73="",J73=""),"",CONCATENATE(J73,", ",K73)) -> Taloban, Antonio Jr | J73: Taloban | K73: Antonio Jr | L73: R | M73: Male | N73: 8 Avelino Street | O73: Guisad | Q73: 0917-835-4755 | R73: talobantony@gmail.com | S73: 26172 | T73: =IF(S73="","",DATEDIF(S73,TODAY(),"Y")) -> 55
D74: Yes | F74: Levi | H74: Member | I74: =IF(AND(K74="",J74=""),"",CONCATENATE(J74,", ",K74)) -> Tamo, Allan Edward | J74: Tamo | K74: Allan Edward | L74: O | M74: Male | N74: 348 Purok 7 Interior | O74: New Lucban | Q74: 0999-902-1703 | S74: 32092 | T74: =IF(S74="","",DATEDIF(S74,TODAY(),"Y")) -> 38 | U74: Baguio City | V74: Tamo, Albert M. | W74: Tamo, Raquel O. | X74: Yes | Y74: 44258 | Z74: Yes | AA74: 45327 | AB74: Roman Catholic | AC74: Culinary Graduate | AD74: Business owner - Chop's Bowl | AH74: Basketball | AI74: Cooking | AJ74: Tamo, Kathlene T. | AK74: Business owner - Chop's Bowl | AL74: Yes | AM74: Yes | AN74: Tamo, Kathlene T. | AO74: Same as Home Address | AP74: Spouse | AQ74: 0910-964-0224
D75: Yes | F75: Reuben | H75: Member | I75: =IF(AND(K75="",J75=""),"",CONCATENATE(J75,", ",K75)) -> Tomas, Rolly | J75: Tomas | K75: Rolly | L75: B | M75: Male | N75: Bangko | O75: Daclan, Tublay | Q75: 0950-655-3468 | S75: 22792 | T75: =IF(S75="","",DATEDIF(S75,TODAY(),"Y")) -> 64 | U75: Tublay, Benguet | X75: Yes | Y75: 1991 | Z75: Yes | AB75: Anglican | AC75: High School | AD75: Farmer | AJ75: Tomas, Andrea | AK75: Farmer | AL75: Yes | AM75: Yes | AN75: Tomas, Andrea | AP75: Spouse | AQ75: 0909-200-1765
D76: Yes | F76: Judah | H76: Member | I76: =IF(AND(K76="",J76=""),"",CONCATENATE(J76,", ",K76)) -> Torcuato, Arnulfo | J76: Torcuato | K76: Arnulfo | L76: Balneg | M76: Male | N76: 38 | O76: Central Fairview | P76: Abra, Dolores | Q76: 0999-694-0537 | S76: 23437 | T76: =IF(S76="","",DATEDIF(S76,TODAY(),"Y")) -> 62 | U76: Abra | X76: Yes | Y76: 45711 | Z76: No | AB76: Roman Catholic | AJ76: Torcuato, Violeta | AK76: Housekeeper | AL76: Not Yet | AM76: Not Yet | AN76: Torcuato, Violeta | AO76: Same as Home Address | AP76: Spouse | AQ76: 0995-208-8750
D77: Yes | F77: Benjamin | H77: Leader | I77: =IF(AND(K77="",J77=""),"",CONCATENATE(J77,", ",K77)) -> Wagang, Andres | J77: Wagang | K77: Andres | M77: Male | N77: AE 217 Western Buyagan | O77: Poblacion, La Trinidad | P77: Poblacion, La Trinidad | Q77: 0998-595-9551 | S77: 30650 | T77: =IF(S77="","",DATEDIF(S77,TODAY(),"Y")) -> 42 | U77: La Trinidad | V77: Wagang, Daniel | W77: Wagang, Evangeline | X77: Yes | Y77: 1995 | Z77: Yes | AA77: 1996 | AG77: Teaching, Playing Musical Instruments | AJ77: Wagang, Vilma T. | AL77: Yes | AM77: Yes | AN77: Wagang, Vilma T. | AO77: Same as Home Address | AP77: Spouse
D78: Yes | F78: Dan | H78: Member | I78: =IF(AND(K78="",J78=""),"",CONCATENATE(J78,", ",K78)) -> Wakit, Benjamin | J78: Wakit | K78: Benjamin | M78: Male | O78: Goldfield, Itogon | S78: 22620 | T78: =IF(S78="","",DATEDIF(S78,TODAY(),"Y")) -> 64 | U78: Wangal, La Trinidad | V78: Wakit, Lorenzo | W78: Wakit, Benita | X78: Yes | Y78: 1984 | AJ78: Wakit, Tese
D79: Yes | F79: Dan | H79: Member | I79: =IF(AND(K79="",J79=""),"",CONCATENATE(J79,", ",K79)) -> Wong, Benjamin Jr | J79: Wong | K79: Benjamin Jr | L79: K | M79: Male | N79: 54 South Central | O79: Aurora Hill | P79: Baguio City | Q79: 0928-892-6858 / 0908-793-6956 | R79: jingjr67@gmail.com | S79: 24764 | T79: =IF(S79="","",DATEDIF(S79,TODAY(),"Y")) -> 59 | U79: Baguio City | V79: Wong, Benjamin Sr. | W79: Wong, Rosa | X79: Yes | Y79: 1990 | Z79: Yes | AA79: 1990 | AB79: Assemblies of God | AC79: College Level | AD79: Seafarer | AG79: Snging | AH79: Baseball | AI79: Cooking | AJ79: Wong, Teofila M. | AL79: Yes | AM79: Yes | AN79: Wong, Teofila M. | AO79: Same as Home Address | AP79: Spouse | AQ79: 0908-793-6956
D80: Yes | F80: Judah | H80: Member | I80: =IF(AND(K80="",J80=""),"",CONCATENATE(J80,", ",K80)) -> Zapata, Rando | J80: Zapata | K80: Rando | M80: Male | N80: 33 | O80: Central Fairview | P80: Abra, Dolores | Q80: 0999-426-4459 | S80: 26630 | T80: =IF(S80="","",DATEDIF(S80,TODAY(),"Y")) -> 53 | U80: Bangued, Abra | V80: Zapata, Romeo | W80: Zapata, Erlinda B. | X80: Yes | AA80: 45000 | AB80: INC | AC80: College Undergraduate | AD80: Bus Driver - Pines Garage | AE80: AMM Member, Traffic Enforcer | AG80: Singing | AI80: Cooking | AJ80: Zapata, Florencia | AK80: Freelance Housekeeping | AL80: Yes | AM80: Yes | AN80: Zapata, Florencia | AO80: Same as Home Address | AP80: Spouse | AQ80: 0999-694-0537
I81: =IF(AND(K81="",J81=""),"",CONCATENATE(J81,", ",K81)) | T81: =IF(S81="","",DATEDIF(S81,TODAY(),"Y"))
T82: =IF(S82="","",DATEDIF(S82,TODAY(),"Y"))
I83: =IF(AND(K83="",J83=""),"",CONCATENATE(J83,", ",K83)) | T83: =IF(S83="","",DATEDIF(S83,TODAY(),"Y"))
I84: =IF(AND(K84="",J84=""),"",CONCATENATE(J84,", ",K84)) | T84: =IF(S84="","",DATEDIF(S84,TODAY(),"Y"))
I85: =IF(AND(K85="",J85=""),"",CONCATENATE(J85,", ",K85)) | T85: =IF(S85="","",DATEDIF(S85,TODAY(),"Y"))
I86: =IF(AND(K86="",J86=""),"",CONCATENATE(J86,", ",K86)) | T86: =IF(S86="","",DATEDIF(S86,TODAY(),"Y"))
I87: =IF(AND(K87="",J87=""),"",CONCATENATE(J87,", ",K87)) | T87: =IF(S87="","",DATEDIF(S87,TODAY(),"Y"))
I88: =IF(AND(K88="",J88=""),"",CONCATENATE(J88,", ",K88)) | T88: =IF(S88="","",DATEDIF(S88,TODAY(),"Y"))
I89: =IF(AND(K89="",J89=""),"",CONCATENATE(J89,", ",K89)) | T89: =IF(S89="","",DATEDIF(S89,TODAY(),"Y"))
I90: =IF(AND(K90="",J90=""),"",CONCATENATE(J90,", ",K90)) | T90: =IF(S90="","",DATEDIF(S90,TODAY(),"Y"))
I91: =IF(AND(K91="",J91=""),"",CONCATENATE(J91,", ",K91)) | T91: =IF(S91="","",DATEDIF(S91,TODAY(),"Y"))
I92: =IF(AND(K92="",J92=""),"",CONCATENATE(J92,", ",K92)) | T92: =IF(S92="","",DATEDIF(S92,TODAY(),"Y"))
I93: =IF(AND(K93="",J93=""),"",CONCATENATE(J93,", ",K93)) | T93: =IF(S93="","",DATEDIF(S93,TODAY(),"Y"))
I94: =IF(AND(K94="",J94=""),"",CONCATENATE(J94,", ",K94)) | T94: =IF(S94="","",DATEDIF(S94,TODAY(),"Y"))
... I299: =IF(AND(K299="",J299=""),"",CONCATENATE(J299,", ",K299)) | T299: =IF(S299="","",DATEDIF(S299,TODAY(),"Y"))

Sheet Youth
A1: YOUTH MINISTRIES
A3: Count per filter | B3: =SUBTOTAL(3,Youth!$K$5:$K$401) -> 192
D4: With Profiling Forn | E4: Status | F4: Cell Group | G4: Age Group | H4: CG Position | I4: Full Name (Last, First) | J4: Last Name | K4: First Name | L4: Middle Initial | M4: Gender | N4: Street | O4: City Address | P4: Provincial Address | Q4: Contact Number | R4: Email | S4: Birthdate | T4: Age | U4: Birthplace | V4: Father | W4: Mother | X4: Baptized in Water | Y4: Date | Z4: Baptized in Holy Ghost | AA4: Date2 | AB4: Former Religious Affiliation | AC4: Home Church | AD4: Pastor's Name | AE4: Educational Attainment | AF4: School Name | AG4: School Organization | AH4: Occupation (if working) | AI4: Church ministries (Present) | AJ4: Ministry You Want To Be Part Of | AK4: Personal skills | AL4: Sports Interest | AM4: Other skills | AN4: YLTS/Sectional Youth Con - Times Attended | AO4: Y.C./District Youth Con - Times Attended | AP4: Emergency Contact | AQ4: Address | AR4: Relationship | AS4: Contact Number2
D5: No | E5: Other Church | F5: Joshua | H5: Member | I5: =IF(AND(K5="",J5=""),"",CONCATENATE(J5,", ",K5)) -> Agpalo, Charles | J5: Agpalo | K5: Charles | M5: Male | T5: =IF(S5="","",DATEDIF(S5,TODAY(),"Y"))
D6: No | E6: Sunday Goer | F6: Samuel | H6: Member | I6: =IF(AND(K6="",J6=""),"",CONCATENATE(J6,", ",K6)) -> Akiapat, Femy | J6: Akiapat | K6: Femy | M6: Female | T6: =IF(S6="","",DATEDIF(S6,TODAY(),"Y"))
D7: No | E7: Inactive | F7: Elijah | G7: Hyphen | H7: Member | I7: =IF(AND(K7="",J7=""),"",CONCATENATE(J7,", ",K7)) -> Albing, John Lee | J7: Albing | K7: John Lee | M7: Male | T7: =IF(S7="","",DATEDIF(S7,TODAY(),"Y"))
D8: Yes | E8: Active | F8: Paul | H8: Assistant Leader | I8: =IF(AND(K8="",J8=""),"",CONCATENATE(J8,", ",K8)) -> Albing, Amela Grace | J8: Albing | K8: Amela Grace | L8: W | M8: Female | N8: 15 Moran St | O8: Gibraltar | P8: Tadian, Mt. Province | Q8: 0985-088-5808 | R8: graziawazian@gmail.com | S8: 36187 | T8: =IF(S8="","",DATEDIF(S8,TODAY(),"Y")) -> 27 | U8: La Trinidad, Benguet | V8: Albing, Melanio Nga-an | W8: Albing, Agustina Wasian | X8: Yes | Y8: 39726 | Z8: Yes | AA8: 39558 | AE8: College Graduate | AF8: U.B. | AI8: Music, Children's Ministry | AP8: Albing, John Lee | AQ8: Same as Home Address | AR8: Brother | AS8: 0948-490-2424
D9: Yes | E9: Active | F9: Elijah | G9: Hyphen | H9: Leader | I9: =IF(AND(K9="",J9=""),"",CONCATENATE(J9,", ",K9)) -> Albing, Alpha May | J9: Albing | K9: Alpha May | L9: W | M9: Female | N9: 15 Moran St | O9: Gibraltar | P9: Tadian, Mt. Province | Q9: 0930-545-7458 | R9: alparito13@gmail.com | S9: 33888 | T9: =IF(S9="","",DATEDIF(S9,TODAY(),"Y")) -> 34 | U9: La Trinidad, Benguet | V9: Albing, Melanio Nga-an | W9: Albing, Agustina Wasian | X9: Yes | Z9: Yes | AB9: Roman Catholic | AE9: College | AF9: U.B. | AI9: Music, Children's Ministry | AP9: Albing, John Lee | AQ9: Same as Home Address | AR9: Brother | AS9: 0948-490-2424
D10: No | E10: Sunday Goer | F10: Samuel | H10: Member | I10: =IF(AND(K10="",J10=""),"",CONCATENATE(J10,", ",K10)) -> Alcantara, Axel | J10: Alcantara | K10: Axel | M10: Male | T10: =IF(S10="","",DATEDIF(S10,TODAY(),"Y"))
D11: No | E11: Inactive | F11: Elijah | H11: Member | I11: =IF(AND(K11="",J11=""),"",CONCATENATE(J11,", ",K11)) -> Alcoriza, Renalyn | J11: Alcoriza | K11: Renalyn | M11: Female | T11: =IF(S11="","",DATEDIF(S11,TODAY(),"Y"))
D12: No | E12: Inactive | F12: Elisha | H12: Member | I12: =IF(AND(K12="",J12=""),"",CONCATENATE(J12,", ",K12)) -> Alister, Jun | J12: Alister | K12: Jun | M12: Male | T12: =IF(S12="","",DATEDIF(S12,TODAY(),"Y"))
D13: No | E13: Sunday Goer | F13: Paul | H13: Member | I13: =IF(AND(K13="",J13=""),"",CONCATENATE(J13,", ",K13)) -> Amplogio, Zhoilo | J13: Amplogio | K13: Zhoilo | M13: Male | T13: =IF(S13="","",DATEDIF(S13,TODAY(),"Y"))
D14: No | E14: Sunday Goer | F14: Paul | H14: Member | I14: =IF(AND(K14="",J14=""),"",CONCATENATE(J14,", ",K14)) -> Amplogio, Harvey | J14: Amplogio | K14: Harvey | M14: Male | T14: =IF(S14="","",DATEDIF(S14,TODAY(),"Y"))
D15: No | E15: Inactive | F15: Samuel | H15: Member | I15: =IF(AND(K15="",J15=""),"",CONCATENATE(J15,", ",K15)) -> Antonio, Froxh Zion | J15: Antonio | K15: Froxh Zion | L15: a | M15: Male | T15: =IF(S15="","",DATEDIF(S15,TODAY(),"Y"))
D16: No | E16: Active | F16: Moses | H16: Member | I16: =IF(AND(K16="",J16=""),"",CONCATENATE(J16,", ",K16)) -> Apilada, Jairah May | J16: Apilada | K16: Jairah May | M16: Female | N16: Ap31 Sitio Paltingan | O16: Ambiong, La Trinidad | Q16: 0964-142-3946 | S16: 39863 | T16: =IF(S16="","",DATEDIF(S16,TODAY(),"Y")) -> 17 | U16: Cavite | V16: Apilada, Arnel B. | W16: Cañada, Joana R. | X16: Yes | Y16: 44394 | Z16: Yes | AA16: 44386 | AE16: Current | AF16: Doña Aurora NHS | AK16: Dancing | AL16: Volleyball | AP16: Apilada, Armando | AQ16: Same as Home Address | AR16: Grandfather | AS16: 0909-572-3317
D17: Yes | E17: Inactive | F17: Moses | H17: Member | I17: =IF(AND(K17="",J17=""),"",CONCATENATE(J17,", ",K17)) -> Apilada, Arman Angelo | J17: Apilada | K17: Arman Angelo | L17: B | M17: Male | N17: 057 Sitio Paltingan | O17: Ambiong, La Trinidad | P17: Manaoag, Pangasinan | Q17: 0966-533-0009 | S17: 37645 | T17: =IF(S17="","",DATEDIF(S17,TODAY(),"Y")) -> 23 | U17: Baguio City | V17: Apilada, Armando | W17: Apilada, Susan | X17: Yes | Z17: Yes | AB17: Roman Catholic | AE17: BS Architecture 5th Year | AF17: U.B. | AK17: Arts & Deco | AM17: Drawing | AP17: Apilada, Armando | AQ17: Same as Home Address | AR17: Father | AS17: 0909-572-3317
D18: No | I18: =IF(AND(K18="",J18=""),"",CONCATENATE(J18,", ",K18)) -> Apilada, Arbie | J18: Apilada | K18: Arbie | M18: Female | N18: AP31 Paltingan | O18: Ambiong, La Trinidad | P18: Tayug, Pangasinan | Q18: 0929-867-7178 | R18: arbie. apilada@gmail.com | T18: =IF(S18="","",DATEDIF(S18,TODAY(),"Y")) | U18: Tayug, Pangasinan | V18: Apilada, Armando | W18: Apilada, Susan | X18: Yes | Y18: 37605 | Z18: Yes | AA18: 37652 | AE18: College | AF18: U.B. | AH18: Tutor | AK18: Teaching | AL18: Volleyball | AN18: 1 | AO18: 1 | AP18: Apilada, Armando | AQ18: Same as Home Address | AR18: Father | AS18: 0909-572-3317
D19: No | E19: Sunday Goer | F19: Timothy | H19: Member | I19: =IF(AND(K19="",J19=""),"",CONCATENATE(J19,", ",K19)) -> Apolinario, Troy Kenneth | J19: Apolinario | K19: Troy Kenneth | M19: Male | T19: =IF(S19="","",DATEDIF(S19,TODAY(),"Y"))
D20: Yes | I20: =IF(AND(K20="",J20=""),"",CONCATENATE(J20,", ",K20)) -> Augusto, Guillian | J20: Augusto | K20: Guillian | L20: M | M20: Female | O20: Holy Ghost Extension | P20: Lagawe, Ifugao | Q20: 0949-601-7951 | R20: guillian.augusto@gmail.com | S20: 36910 | T20: =IF(S20="","",DATEDIF(S20,TODAY(),"Y")) -> 25 | U20: Lagawe, Ifugao | V20: Augusto, Gilbert P. | W20: Augusto, Janet M. | X20: Yes | Y20: 42005 | Z20: Yes | AC20: UPC Lagawe Church | AD20: Ptr. Joel Baracao | AE20: College Graduate | AF20: U.C. | AH20: Treasury, Chalet Baguio Hotel | AI20: Music | AK20: Singing, Playing Musical Instruments | AL20: Table Tennis | AM20: Crochet | AN20: 1 | AO20: 5 | AP20: Cabbigat, Jinky | AQ20: Same as Home Address | AR20: Church Mate | AS20: 0928-907-1302
D21: No | E21: Active | F21: Joseph | H21: Member | I21: =IF(AND(K21="",J21=""),"",CONCATENATE(J21,", ",K21)) -> Ayungo III, Martin Aileslee | J21: Ayungo III | K21: Martin Aileslee | L21: B | M21: Male | T21: =IF(S21="","",DATEDIF(S21,TODAY(),"Y"))
D22: Yes | E22: Active | F22: Joseph | H22: Assistant Leader | I22: =IF(AND(K22="",J22=""),"",CONCATENATE(J22,", ",K22)) -> Badilla, Hervie Kate | J22: Badilla | K22: Hervie Kate | M22: Female | N22: OB-048-B Bated | O22: Tawang, La Trinidad | P22: Tawang, La Trinidad | Q22: 0910-002-7493 | R22: bherviekate@gmail.com | S22: 36822 | T22: =IF(S22="","",DATEDIF(S22,TODAY(),"Y")) -> 26 | V22: Badilla, Brenson | W22: Badilla, Beverly | X22: Yes | Y22: October 2012 | Z22: Yes | AA22: 2013 | AE22: College TESDA Graduate | AH22: Caregiver | AI22: Ushering | AK22: Arts & Deco | AL22: Volleyball, Badminton | AM22: Cooking | AN22: 10 | AO22: 10 | AP22: Badilla, Beverly | AQ22: Same as Home Address | AR22: Mother
D23: Yes | I23: =IF(AND(K23="",J23=""),"",CONCATENATE(J23,", ",K23)) -> Bagaoisan, Divine Mercy | J23: Bagaoisan | K23: Divine Mercy | L23: R | M23: Female | N23: Salud Mitra | P23: Macanaya Aparri, Cagayan | Q23: 0961-705-8441 | R23: divinebagaoisan@gmail.com | S23: 39325 | T23: =IF(S23="","",DATEDIF(S23,TODAY(),"Y")) -> 19 | U23: Macanaya Aparri, Cagayan | V23: Bagaoisan, Charito | W23: Bagaoisan, Merlita | X23: Yes | Y23: 42102 | Z23: Yes | AA23: 42106 | AC23: UPC Tabernacle of Living Saints | AD23: Ptr. Charito Bagaoisan | AE23: College | AF23: U.B. | AI23: Music | AK23: Singing | AL23: Volleyball, Badminton | AM23: Cooking | AN23: 8 | AO23: 3 | AP23: Bagaoisan, Charito | AQ23: Macanaya Aparri, Cagayan | AR23: Father | AS23: 0975-322-8737
D24: No | I24: =IF(AND(K24="",J24=""),"",CONCATENATE(J24,", ",K24)) -> Baldoz, King Stevenlee | J24: Baldoz | K24: King Stevenlee | L24: C | M24: Male | P24: Paniqui, Tarla | Q24: 0912-280-6426 | S24: 38217 | T24: =IF(S24="","",DATEDIF(S24,TODAY(),"Y")) -> 22 | U24: Narvacan, Ilocos Sur | V24: Baldoz, Vincent B. | W24: Baldoz, Tewie C. | X24: Yes | Y24: 43330 | Z24: Yes | AC24: UPC Paniqui Church | AD24: Ptr. Lino Banaag | AE24: 1st Year College - Current | AF24: U.C. | AK24: Singing, Photographt | AL24: Volleyball, Badminton | AM24: Cooking | AN24: 3 | AO24: 5 | AP24: Baldoz, Queen Vite | AQ24: Same as Home Address | AR24: Sibling | AS24: 0910-612-6223
D25: Yes | E25: Sunday Goer | F25: Jacob | H25: Member | I25: =IF(AND(K25="",J25=""),"",CONCATENATE(J25,", ",K25)) -> Balinggan, Jadden Tredway | J25: Balinggan | K25: Jadden Tredway | M25: Male | N25: 154 BPI Cpd | O25: Cresencia Village | Q25: 0962-158-2646 | S25: 40957 | T25: =IF(S25="","",DATEDIF(S25,TODAY(),"Y")) -> 14 | U25: Baguio City | V25: Balinggan, Jenkinson | W25: Balinggan, Gene | X25: Yes | Y25: 45704 | Z25: Yes | AE25: Grade 7 - Current | AF25: U.C. | AL25: Basketball, Soccer, Karate | AP25: Balinggan, Gene | AQ25: Same as Home Address | AR25: Mother | AS25: 0939-918-6017
D26: No | E26: Sunday Goer | F26: Timothy | H26: Member | I26: =IF(AND(K26="",J26=""),"",CONCATENATE(J26,", ",K26)) -> Balinggan, Gabrielle Troi | J26: Balinggan | K26: Gabrielle Troi | L26: T | M26: Female | T26: =IF(S26="","",DATEDIF(S26,TODAY(),"Y"))
D27: No | I27: =IF(AND(K27="",J27=""),"",CONCATENATE(J27,", ",K27)) -> Balneg, Queen Crystalie | J27: Balneg | K27: Queen Crystalie | L27: U | M27: Female | N27: Blk 1 Lot 19B NHA | O27: Tadiangan, Tuba | P27: Tuba, Benguet | Q27: 0912-521-4964 | S27: 40641 | T27: =IF(S27="","",DATEDIF(S27,TODAY(),"Y")) -> 15 | V27: Balneg, Alfredo | W27: Balneg, Rose Urbiztundo | X27: Yes | Y27: 45697 | AE27: Grade 8 - Current | AF27: Educare College Inc. | AK27: Arts & Deco | AM27: Painting | AP27: Balneg, Rose | AQ27: Same as Home Address | AR27: Mother | AS27: 0921-975-9585
D28: Yes | E28: Active | F28: Timothy | H28: Member | I28: =IF(AND(K28="",J28=""),"",CONCATENATE(J28,", ",K28)) -> Bambao, Kristine Chloe | J28: Bambao | K28: Kristine Chloe | L28: C | M28: Female | N28: 15 Balacbac Central | O28: Sto. Tomas Proper | P28: Baguio City | Q28: 0969-386-4628 | R28: kc08bambao@gmail.com | S28: 39506 | T28: =IF(S28="","",DATEDIF(S28,TODAY(),"Y")) -> 18 | U28: Baguio City | V28: Bambao, Angel Jr. | W28: Bambao, Joanna | X28: Yes | Y28: 44828 | Z28: Yes | AA28: 44647 | AE28: Grade 11 - Current | AF28: UB High School | AG28: Girl Scout of the Phil. | AI28: Ushering | AK28: Speaker/Socialize | AL28: Badminton | AN28: 1 | AO28: 2 | AP28: Bambao, Joanna | AQ28: Same as Home Address | AR28: Mother | AS28: 0912-186-2964
D29: Yes | E29: Active | F29: Joseph | H29: Member | I29: =IF(AND(K29="",J29=""),"",CONCATENATE(J29,", ",K29)) -> Banaag, Geraldine Marijoe | J29: Banaag | K29: Geraldine Marijoe | L29: S | M29: Female | N29: 120D Lower Kitma Interior | O29: Bakakeng Central | Q29: 0910-519-3828 | R29: geraldine100908@gmail.com | S29: 39730 | T29: =IF(S29="","",DATEDIF(S29,TODAY(),"Y")) -> 18 | U29: Baguio City | V29: Banaag, Gerald C. | W29: Banaag, Marjorie S. | X29: Yes | Y29: 44765 | Z29: Yes | AA29: 45319 | AB29: UCCP | AE29: Grade 10 - Current | AF29: Phil. Science High School - CAR | AG29: PSHS CAR Baking Club Member | AI29: Ushering | AK29: Arts & Deco, Photography | AL29: Volleyball, Badminton | AN29: 1 | AO29: 3 | AP29: Banaag, Gerald | AQ29: Same as Home Address | AR29: Father | AS29: 0920-858-9898
D30: Yes | E30: Active | F30: Joseph | H30: Member | I30: =IF(AND(K30="",J30=""),"",CONCATENATE(J30,", ",K30)) -> Banaag, Aldgeryne Faith | J30: Banaag | K30: Aldgeryne Faith | L30: S | M30: Female | N30: 120D Lower Kitma Interior | O30: Bakakeng Central | Q30: 0910-519-3858 | R30: banaagaldgerynef@gmail.com | S30: 40722 | T30: =IF(S30="","",DATEDIF(S30,TODAY(),"Y")) -> 15 | U30: Baguio City | V30: Banaag, Gerald C. | W30: Banaag, Marjorie S. | X30: Yes | Y30: 44766 | Z30: Yes | AA30: 2023 | AB30: UCCP | AE30: Step Learning Academy | AF30: Phil. Science High School - CAR | AI30: Bible Quizzing | AK30: Playing Musical Instruments, Literary Composition | AL30: Volleyball, Chess/Dama | AN30: 1 | AO30: 0 | AP30: Banaag, Marjorie | AQ30: Same as Home Address | AR30: Mother | AS30: 0949-848-4774
D31: No | E31: Active | F31: Jacob | H31: Leader | I31: =IF(AND(K31="",J31=""),"",CONCATENATE(J31,", ",K31)) -> Bañez, Journey Ryan | J31: Bañez | K31: Journey Ryan | M31: Male | T31: =IF(S31="","",DATEDIF(S31,TODAY(),"Y"))
D32: Yes | E32: Active | F32: Isaac | H32: Assistant Leader | I32: =IF(AND(K32="",J32=""),"",CONCATENATE(J32,", ",K32)) -> Basilio, Gylrihs Gem | J32: Basilio | K32: Gylrihs Gem | L32: B | M32: Female | N32: Lot 7A Blk 2 Onyx St NPC | O32: Irisan | Q32: 0960-583-5959 | R32: ggem.bbasilio.2@gmail.com | S32: 37852 | T32: =IF(S32="","",DATEDIF(S32,TODAY(),"Y")) -> 23 | U32: Baguio City | V32: Basilio, George S. | W32: Basilio, Shirly B. | X32: Yes | Y32: 2016 | Z32: Yes | AA32: 2017 | AE32: 3rd Year College - Current | AF32: BSU La Trinidad | AG32: Enlgish Language & Literature Students Association | AI32: Sunday School, Media, Youth Ministires | AK32: Literary Composition, Arts & Deco | AM32: Painting, Tailoring/Dressmaking | AN32: 7 to 8 | AO32: 14 to 16 | AP32: Boteng, Jaime | AQ32: FC323 Central balili, L.T. | AR32: Grandfather | AS32: 0949-647-5784
D33: Yes | E33: Active | F33: Joshua | H33: Assistant Leader | I33: =IF(AND(K33="",J33=""),"",CONCATENATE(J33,", ",K33)) -> Basilio, Geryl Ann | J33: Basilio | K33: Geryl Ann | L33: B | M33: Female | N33: Lot 7A Blk 2 Onyx St NPC | O33: Irisan | P33: Benguet | Q33: 0969-225-9709 | R33: gerylbasilio2121@gmail.com | S33: 38350 | T33: =IF(S33="","",DATEDIF(S33,TODAY(),"Y")) -> 21 | U33: Baguio City | V33: Basilio, George S. | W33: Basilio, Shirly B. | X33: Yes | Y33: 2014 | Z33: Yes | AA33: 2014 | AE33: College | AF33: U.C. | AI33: Music, Youth Media | AK33: Playing Musical instruments, Arts & Deco | AN33: 3 + | AO33: 3 + | AP33: Basilio, Shirly B. | AR33: Mother | AS33: 0947-734-1549
D34: Yes | E34: Other Church | F34: Paul | H34: Member | I34: =IF(AND(K34="",J34=""),"",CONCATENATE(J34,", ",K34)) -> Batalao, Nathaniel | J34: Batalao | K34: Nathaniel | L34: S | M34: Male | N34: 44 | O34: New Lucban | P34: Loo Buguias Benguet | Q34: 0951-599-5210 | R34: nathanielbatalao@gmail.com | S34: 36703 | T34: =IF(S34="","",DATEDIF(S34,TODAY(),"Y")) -> 26 | U34: Buguias, Benguet | V34: Batalao, Jonathan Jr. | W34: Batalao, Doria | X34: Yes | Y34: 41421 | Z34: Yes | AC34: UPC Buguias | AD34: Ptr. Tony Mamolang | AE34: BSCE | AF34: S.L.U. | AI34: Music, Praise Team | AK34: Acting | AL34: Volleyball, basketball | AN34: 7 | AO34: 4 | AP34: Batalao, Jonathan B. | AQ34: Loo Buguias, Benguet | AR34: Sibling | AS34: 0950-142-8408
D35: Yes | E35: Other Church | F35: Joshua | H35: Member | I35: =IF(AND(K35="",J35=""),"",CONCATENATE(J35,", ",K35)) -> Batalao, Jonathan | J35: Batalao | K35: Jonathan | L35: S | M35: Male | N35: 44 | O35: New Lucban | P35: Loo Buguias Benguet | Q35: 0927-327-9192 | R35: batalaojonathan@gmail.com | S35: 35948 | T35: =IF(S35="","",DATEDIF(S35,TODAY(),"Y")) -> 28 | U35: Buguias, Benguet | V35: Batalao, Jonathan Jr. | W35: Batalao, Doria | X35: Yes | Y35: 2011 | Z35: Yes | AC35: UPC Buguias | AD35: Ptr. Tony Mamolang | AE35: Automotive Tech; BS Architecture | AF35: BSU Buguias; U.B. | AH35: Apprentice, Draftsman - B.C. | AI35: Usheing, Choir | AK35: Arts & Deco | AL35: Volleyball, Basketball | AN35: 7 | AO35: 2 | AP35: Batalao, Nathaniel B. | AQ35: Loo Buguias, Benguet | AR35: Sibling | AS35: 0951-599-5210
D36: No | E36: Sunday Goer | F36: Jacob | H36: Member | I36: =IF(AND(K36="",J36=""),"",CONCATENATE(J36,", ",K36)) -> Bokket, Nathaniel | J36: Bokket | K36: Nathaniel | M36: Male | T36: =IF(S36="","",DATEDIF(S36,TODAY(),"Y"))
D37: No | E37: Sunday Goer | F37: Joshua | H37: Member | I37: =IF(AND(K37="",J37=""),"",CONCATENATE(J37,", ",K37)) -> Bokket, Mark | J37: Bokket | K37: Mark | M37: Male | T37: =IF(S37="","",DATEDIF(S37,TODAY(),"Y"))
D38: No | E38: Bible Study | F38: Moses | H38: Member | I38: =IF(AND(K38="",J38=""),"",CONCATENATE(J38,", ",K38)) -> Bonilla, Mark Rener | J38: Bonilla | K38: Mark Rener | L38: C | M38: Male | T38: =IF(S38="","",DATEDIF(S38,TODAY(),"Y"))
D39: No | E39: Bible Study | F39: Moses | H39: Member | I39: =IF(AND(K39="",J39=""),"",CONCATENATE(J39,", ",K39)) -> Bonilla, Joshua | J39: Bonilla | K39: Joshua | L39: B | M39: Male | T39: =IF(S39="","",DATEDIF(S39,TODAY(),"Y"))
D40: Yes | I40: =IF(AND(K40="",J40=""),"",CONCATENATE(J40,", ",K40)) -> Bosque, Ara Mae | J40: Bosque | K40: Ara Mae | M40: Female | N40: San Mateo, South Luzon, Rizal | P40: San Mateo, South Luzon, Rizal | Q40: 0969-466-1551 | R40: arambosque@gmail.com | S40: 36334 | T40: =IF(S40="","",DATEDIF(S40,TODAY(),"Y")) -> 27 | U40: Quezon City | V40: Bosque, Wilfred | W40: Bosque, Vilma | X40: Yes | Y40: 40787 | Z40: Yes | AA40: 2012 | AC40: UPC-CAC San Ancdres Bukid Manila | AD40: Ptr. Justine Tagudin | AE40: Bachelors Degree | AH40: BMS Tech Suoervisor | AI40: Music, Youth Pres., Sunday School, Prayer Warrior, Ushering | AK40: Teaching, Arts & Deci | AN40: 5 | AO40: 3 | AP40: Bosque, Ara Maica | AQ40: San Mateo, South Luzon, Rizal | AR40: Sibling | AS40: 0916-422-3933
D41: No | E41: Bible Study | F41: Joshua | H41: Member | I41: =IF(AND(K41="",J41=""),"",CONCATENATE(J41,", ",K41)) -> Briones, Jonel | J41: Briones | K41: Jonel | M41: Male | T41: =IF(S41="","",DATEDIF(S41,TODAY(),"Y"))
D42: Yes | I42: =IF(AND(K42="",J42=""),"",CONCATENATE(J42,", ",K42)) -> Buhong, Melody | J42: Buhong | K42: Melody | L42: P | M42: Female | N42: Kasibu, Nueva Viscaya | P42: Kasibu, Nueva Viscaya | Q42: 0936-117-4548 | R42: melodybuhongcse@gmail.com | S42: 37317 | T42: =IF(S42="","",DATEDIF(S42,TODAY(),"Y")) -> 24 | U42: Bambang, Nueva Viscaya | V42: Buhong, Damiano | W42: Buhong, Rosa D. | Z42: Yes | AA42: 43720 | AC42: Dupac Del Norte UPC | AD42: Ptr. Joel Brojas
D43: Yes | E43: Active | F43: Paul | H43: Member | I43: =IF(AND(K43="",J43=""),"",CONCATENATE(J43,", ",K43)) -> Cabay, Chansen Dave | J43: Cabay | K43: Chansen Dave | L43: D | M43: Male | N43: Km 3 | O43: Asin Road | P43: Tadian, Mt. Province | S43: 40136 | T43: =IF(S43="","",DATEDIF(S43,TODAY(),"Y")) -> 16 | U43: La Trinidad, Benguet | V43: Cabay, Charles | W43: Cabay, Arlyn | X43: Yes | Y43: 45653 | Z43: Yes | AA43: 45653 | AE43: Grade 9 - Current | AF43: U.C. | AJ43: Music | AL43: Chess/Dama | AN43: 2 | AO43: 1 | AP43: Cabay, Arlyn | AQ43: Same as Home Address | AR43: Mother | AS43: 0938-806-4029
D44: Yes | E44: Active | F44: Paul | H44: Member | I44: =IF(AND(K44="",J44=""),"",CONCATENATE(J44,", ",K44)) -> Cabay, Caryl Kaye | J44: Cabay | K44: Caryl Kaye | L44: D | M44: Female | N44: Km 3 | O44: Asin Road | P44: Masla, Mt. Province | Q44: 0961-535-7583 | R44: carylkaycabay@gmail.com | T44: =IF(S44="","",DATEDIF(S44,TODAY(),"Y")) | U44: La Trinidad, Benguet | V44: Cabay, Charles | W44: Cabay, Arlyn | X44: Yes | Y44: 45663 | Z44: Yes | AA44: 44646 | AF44: U.C. | AG44: Class President, RSCEP Officer | AI44: Bible Quizzing | AK44: Arts & Deco | AL44: Chess/Dama | AM44: Cooking | AN44: 2 | AO44: 2 | AP44: Cabay, Arlyn | AQ44: Same as Home Address | AR44: Mother | AS44: 0938-806-4029
D45: Yes | E45: Other Church | F45: David | H45: Member | I45: =IF(AND(K45="",J45=""),"",CONCATENATE(J45,", ",K45)) -> Cabbigat, Jinky Mae | J45: Cabbigat | K45: Jinky Mae | L45: B | M45: Female | O45: Holy Ghost Extension | P45: Lagawe Ifugao | Q45: 0928-907-1302 | R45: cabbigatjinkymae@gmail.com | S45: 37634 | T45: =IF(S45="","",DATEDIF(S45,TODAY(),"Y")) -> 23 | U45: Lagawe, Ifugao | V45: Cabbigat, Julius A. | W45: Cabbigat, Josiefer B. | X45: Yes | Y45: 2019 | Z45: Yes | AB45: Roman Catholic | AC45: Jesus Tabernacle, UPC Lagawe, Ifugao | AD45: Ptr. Joel Baracao | AF45: S.L.U. | AJ45: Music | AK45: Singing, Arts & Deco | AL45: Table Tennis | AM45: Cooking | AN45: 0 | AO45: 2
D46: Yes | E46: Active | H46: Member | I46: =IF(AND(K46="",J46=""),"",CONCATENATE(J46,", ",K46)) -> Calimlim, Courtney Jhayne | J46: Calimlim | K46: Courtney Jhayne | L46: A | M46: Female | N46: 1 Purok 5 | O46: Holy Ghost Proper | P46: 524 Penged Nangalisan Tuba Benguet | Q46: 0945-243-1731 | S46: 41287 | T46: =IF(S46="","",DATEDIF(S46,TODAY(),"Y")) -> 13 | U46: La Trinidad | V46: Calimlim, Jared B. | W46: Calimlim, Jamielyn R. | X46: Yes | Y46: 2021 | Z46: Yes | AJ46: Ushering; Sunday School | AK46: Arts & Deco | AL46: Badminton | AO46: 1 | AP46: Calimlim, Jamielyn R. | AQ46: Same as Home Address | AR46: Mother | AS46: 0963-888-1394
D47: No | E47: Active | F47: Joshua | H47: Leader | I47: =IF(AND(K47="",J47=""),"",CONCATENATE(J47,", ",K47)) -> Camodag, Jonathan | J47: Camodag | K47: Jonathan | L47: P | M47: Male | T47: =IF(S47="","",DATEDIF(S47,TODAY(),"Y"))
D48: Yes | E48: Active | F48: Moses | H48: Assistant Leader | I48: =IF(AND(K48="",J48=""),"",CONCATENATE(J48,", ",K48)) -> Camodag, Glory Anne | J48: Camodag | K48: Glory Anne | L48: P | M48: Female | N48: 118 Blk 2 | O48: Middle Quirino Hill | Q48: 0928-999-8768 | R48: gloryanne7camodag@gmail.com | S48: 36366 | T48: =IF(S48="","",DATEDIF(S48,TODAY(),"Y")) -> 27 | U48: Baguio City | V48: Camodag, Audie D. | W48: Camodag, Julieta P. | X48: Yes | Y48: 2010 | Z48: Yes | AA48: May 2012 | AE48: College Graduate | AI48: Bible Quzzing, Media | AN48: 12 | AO48: 11 | AP48: Camodag, Audie D. | AQ48: Same as Home Address | AR48: Father
D49: No | E49: Active | F49: Moses | H49: Member | I49: =IF(AND(K49="",J49=""),"",CONCATENATE(J49,", ",K49)) -> Camodag, Athena Grace | J49: Camodag | K49: Athena Grace | M49: Female | T49: =IF(S49="","",DATEDIF(S49,TODAY(),"Y"))
D50: No | E50: Sunday Goer | F50: Timothy | H50: Member | I50: =IF(AND(K50="",J50=""),"",CONCATENATE(J50,", ",K50)) -> Caragay, Khraenzhell | J50: Caragay | K50: Khraenzhell | M50: Male | T50: =IF(S50="","",DATEDIF(S50,TODAY(),"Y"))
D51: Yes | E51: Active | F51: Timothy | H51: Member | I51: =IF(AND(K51="",J51=""),"",CONCATENATE(J51,", ",K51)) -> Caragay, Kate Ann | J51: Caragay | K51: Kate Ann | M51: Female | N51: 126 Sunny Side | O51: Fairview | P51: Pangasinan | Q51: 0956-412-9855 | S51: 39935 | T51: =IF(S51="","",DATEDIF(S51,TODAY(),"Y")) -> 17 | U51: Baguio City | V51: Caragay, Dennis | W51: Daragay, Kimberly | X51: Yes | Y51: May 2021 | Z51: Yes | AE51: Grade 10 - Current | AF51: PCNHS | AI51: Music, Media | AK51: Photography | AL51: Volleyball
D52: Yes | I52: =IF(AND(K52="",J52=""),"",CONCATENATE(J52,", ",K52)) -> Carpio, Zander | J52: Carpio | K52: Zander | L52: P | M52: Male | N52: Baler, Aurora | P52: Baler, Aurora | Q52: 0981-083-5558 | S52: 38399 | T52: =IF(S52="","",DATEDIF(S52,TODAY(),"Y")) -> 21 | U52: Baler, Aurora | X52: Yes | Y52: 2019 | Z52: Yes | AA52: 2023 | AC52: UPC Aurora | AE52: College | AF52: U.P. Baguio | AJ52: Technical, Ushering | AK52: Teaching, Arts & Deco, Canva, mostly tech-related | AL52: Badminton
D53: Yes | E53: Active | F53: Joseph | G53: Hyphen | H53: Member | I53: =IF(AND(K53="",J53=""),"",CONCATENATE(J53,", ",K53)) -> Castillejo, Jonaira | J53: Castillejo | K53: Jonaira | M53: Female | N53: Purok 10 | O53: Upper Pinget | P53: Dist. 2 San Manuel Isabela | Q53: 0965-369-5837 | R53: jonairacastillejo@gmail.com | S53: 34766 | T53: =IF(S53="","",DATEDIF(S53,TODAY(),"Y")) -> 31 | U53: San Manuel, Isabella | V53: Castillejo, Jhonny | W53: Castillejo, Jovita | X53: Yes | Y53: 40676 | Z53: Yes | AA53: October 2011 | AC53: San Manuel, Isabella | AD53: Ptr. Apollo Vino | AJ53: Music | AK53: Teaching, Singing | AL53: Volleyball | AM53: Cooking | AN53: 13 | AO53: 14 | AP53: Castillejo, Jamaica | AQ53: 154 BPI Compound, Guisad | AR53: Sibling | AS53: 0965-533-6645
D54: Yes | E54: Active | F54: Jacob | H54: Member | I54: =IF(AND(K54="",J54=""),"",CONCATENATE(J54,", ",K54)) -> Castillejo, Jeehan Jane | J54: Castillejo | K54: Jeehan Jane | L54: T | M54: Female | N54: Avelino St | O54: Andres Bonifacio | P54: Dist. 2 San Manuel Isabela | Q54: 0975-688-2492 | R54: jeehanjanecastillejo@gmail.com | S54: 35796 | T54: =IF(S54="","",DATEDIF(S54,TODAY(),"Y")) -> 28 | U54: Caloocan City | V54: Castillejo, Jhonny | W54: Castillejo, Jovita | X54: Yes | Y54: 40676 | Z54: Yes | AA54: 2011 | AC54: San Manuel, Isabella | AD54: Ptr. Apollo Vino | AE54: College Graduate | AF54: Isabella State University - Roxas Campus | AH54: Project Representative - Roman Ayson (Bokawkan Rd. B. C.) | AI54: Music, Children's Ministry | AK54: Teaching, Singing, Literary Composition | AL54: Volleyball | AN54: Alot | AO54: Alot | AP54: Castillejo, Jamaica | AQ54: 154 BPI Compound, Guisad | AR54: Sibling | AS54: 0965-533-6645
D55: Yes | E55: Active | F55: David | H55: Assistant Leader | I55: =IF(AND(K55="",J55=""),"",CONCATENATE(J55,", ",K55)) -> Castillejo, Jamaica | J55: Castillejo | K55: Jamaica | M55: Female | N55: 154 BPI Compoind Cresencia Village | O55: Guisad | P55: Dist. 2 San Manuel Isabela | Q55: 0965-533-6645 | R55: castillejojamaica0723@gmail.com | S55: 36730 | T55: =IF(S55="","",DATEDIF(S55,TODAY(),"Y")) -> 26 | U55: Morong, Rizal | V55: Castillejo, Jhonny | W55: Castillejo, Jovita | X55: Yes | Y55: 40676 | Z55: Yes | AC55: San Manuel, Isabella | AD55: Ptr. Apollo Vino | AI55: Music, Children's Ministry | AK55: Teaching, Singing | AL55: Volleyball | AN55: 13 | AO55: 13 | AP55: Castillejo, Jonaira | AQ55: Purok 10 Upper Pinget | AR55: Sibling | AS55: 0965-369-5837
D56: No | E56: Inactive | F56: Joseph | G56: Hyphen | H56: Member | I56: =IF(AND(K56="",J56=""),"",CONCATENATE(J56,", ",K56)) -> Castro, Oliver | J56: Castro | K56: Oliver | M56: Male | T56: =IF(S56="","",DATEDIF(S56,TODAY(),"Y"))
D57: No | E57: Other Church | F57: Moses | H57: Member | I57: =IF(AND(K57="",J57=""),"",CONCATENATE(J57,", ",K57)) -> Castro, Lysette Anne | J57: Castro | K57: Lysette Anne | M57: Female | T57: =IF(S57="","",DATEDIF(S57,TODAY(),"Y"))
D58: Yes | E58: Sunday Goer | F58: Paul | H58: Member | I58: =IF(AND(K58="",J58=""),"",CONCATENATE(J58,", ",K58)) -> Castro, Henzy Giovan | J58: Castro | K58: Henzy Giovan | L58: B | M58: Male | N58: OC-074 Central Tawang | O58: La Trinidad | P58: Benguet | Q58: 0909-077-6434 | R58: henzycastro@gmail.com | S58: 39169 | T58: =IF(S58="","",DATEDIF(S58,TODAY(),"Y")) -> 19 | U58: La Trinidad, Benguet | V58: Castro, Harold P. | W58: Castro, Ellen B. | AE58: SHS Graduate | AF58: BSU Secondary H.S. | AG58: Badminton Club - Member | AJ58: Music | AK58: Arts & Deco | AL58: Badminton | AM58: Painting | AN58: 2 | AO58: 2 | AP58: Castro, Ellen | AQ58: Same as Home Address | AR58: Mother | AS58: 0909-383-8570
D59: No | E59: Active | F59: Paul | H59: Member | I59: =IF(AND(K59="",J59=""),"",CONCATENATE(J59,", ",K59)) -> Castro, Harnelle | J59: Castro | K59: Harnelle | M59: Male | N59: OC-074 Central Tawang | O59: La Trinidad | P59: Benguet | T59: =IF(S59="","",DATEDIF(S59,TODAY(),"Y")) | U59: La Trinidad, Benguet | V59: Castro, Harold P. | W59: Castro, Ellen B. | X59: Yes | Y59: 43233 | Z59: Yes | AA59: 2019 | AP59: Castro, Ellen | AQ59: Same as Home Address | AR59: Mother | AS59: 0909-383-8570
D60: Yes | E60: Active | F60: Elisha | H60: Assistant Leader | I60: =IF(AND(K60="",J60=""),"",CONCATENATE(J60,", ",K60)) -> Castro, Harell Ethan Augh | J60: Castro | K60: Harell Ethan Augh | L60: B | M60: Male | N60: OC-074 Central Tawang | O60: La Trinidad | P60: Benguet | Q60: 0945-375-1608 | R60: castro.harell01@gmail.com | S60: 38223 | T60: =IF(S60="","",DATEDIF(S60,TODAY(),"Y")) -> 22 | U60: La Trinidad, Benguet | V60: Castro, Harold P. | W60: Castro, Ellen B. | X60: Yes | Y60: August 2015 | Z60: Yes | AA60: October 2016 | AE60: SHS Graduate | AF60: Cordillera Reg. Sci. H.S. | AH60: Deburr Operator MOOG | AI60: Music, Bible Quizzing | AK60: Teaching, Singing, Playing Musical Instruments | AL60: Volleyball, Basketball, Badminton, Chess/Dama, Golf | AM60: Painting, Driving | AN60: 8 | AO60: 6 | AP60: Castro, Ellen | AQ60: Same as Home Address | AR60: Mother | AS60: 0909-383-8570
D61: No | E61: Sunday Goer | F61: Timothy | H61: Member | I61: =IF(AND(K61="",J61=""),"",CONCATENATE(J61,", ",K61)) -> Cayat, Shadrac | J61: Cayat | K61: Shadrac | M61: Male | T61: =IF(S61="","",DATEDIF(S61,TODAY(),"Y"))
D62: Yes | I62: =IF(AND(K62="",J62=""),"",CONCATENATE(J62,", ",K62)) -> Copes, Vonlouie | J62: Copes | K62: Vonlouie | L62: Esteban | M62: Male | N62: 145 Purok 2 Dontogan | O62: Green Valley | P62: Abatan, Buguias | Q62: 0956-992-2055 | R62: vonlouiecopes@gmial.com | S62: 40113 | T62: =IF(S62="","",DATEDIF(S62,TODAY(),"Y")) -> 16 | U62: Baguio City | V62: Copes, Romeo Esteban | W62: Copes, K. Esteban | X62: Yes | Z62: Yes | AC62: UPC Buguias | AD62: Ptr. Tony Mamolang | AF62: SLU Senior High School BEDS | AI62: Choir; Music | AK62: Teaching; Singing; Playing Musical Instruments; Literary Composition; Arts & Deco | AL62: Volleyball; Badminton; Basketball; Chess/Dama; Swimming | AM62: Painting; Cooking | AP62: Copes, K. Esteban | AQ62: Same as Home Address | AR62: Mother | AS62: 0956-992-1099
D63: No | E63: Sunday Goer | F63: Moses | H63: Member | I63: =IF(AND(K63="",J63=""),"",CONCATENATE(J63,", ",K63)) -> Coyasan, Jhed | J63: Coyasan | K63: Jhed | M63: Male | T63: =IF(S63="","",DATEDIF(S63,TODAY(),"Y"))
D64: No | E64: Sunday Goer | F64: David | H64: Member | I64: =IF(AND(K64="",J64=""),"",CONCATENATE(J64,", ",K64)) -> Coyasan, Jhake Rhey | J64: Coyasan | K64: Jhake Rhey | M64: Male | T64: =IF(S64="","",DATEDIF(S64,TODAY(),"Y"))
D65: Yes | E65: Active | F65: Joshua | H65: Member | I65: =IF(AND(K65="",J65=""),"",CONCATENATE(J65,", ",K65)) -> Cruz, Krisha Camille | J65: Cruz | K65: Krisha Camille | L65: D | M65: Female | N65: Blk 3 123 | O65: Middle Quirino Hill | P65: Baguio City | Q65: 0962-250-9056 | R65: krishacamillecruz05@gmail.com | S65: 38458 | T65: =IF(S65="","",DATEDIF(S65,TODAY(),"Y")) -> 21 | U65: Baguio City | V65: Cruz, Marlon O. | W65: Crus, Kristine D. | X65: Yes | Y65: 2014 | Z65: Yes | AE65: 2nd Year College - Current | AF65: U.C. | AH65: ESL Teacher - Pineapple Talk | AI65: Childrens Ministry | AJ65: Music | AK65: Teaching, Singing | AN65: 6 | AO65: 2 | AP65: Cruz, Kristine D. | AQ65: Same as Home Address | AR65: Mother | AS65: 0945-770-8142
D66: Yes | E66: Active | F66: Samuel | H66: Member | I66: =IF(AND(K66="",J66=""),"",CONCATENATE(J66,", ",K66)) -> Cruz, Cedrick Aron | J66: Cruz | K66: Cedrick Aron | L66: D | M66: Male | N66: 123 Blk 3 | O66: Middle Quirino Hill | Q66: 0995-491-6874 | R66: cedrickcruz758@gmail.com | S66: 39529 | T66: =IF(S66="","",DATEDIF(S66,TODAY(),"Y")) -> 18 | V66: Cruz, Marlon O. | W66: Crus, Kristine D. | X66: Yes | Z66: Yes | AA66: 12-26-19 | AE66: Senior High - Current | AF66: Baguio City High School | AI66: Ushering | AK66: Photography, Digital Creatives | AL66: Basketball, Chess/Dama | AP66: Cruz, Kristine D. | AQ66: Same as Home Address | AR66: Mother | AS66: 0945-770-8142
D67: No | E67: Inactive | F67: Joseph | H67: Member | I67: =IF(AND(K67="",J67=""),"",CONCATENATE(J67,", ",K67)) -> Cutay, Timothy | J67: Cutay | K67: Timothy | M67: Male | T67: =IF(S67="","",DATEDIF(S67,TODAY(),"Y"))
D68: Yes | E68: Sunday Goer | F68: Joshua | H68: Member | I68: =IF(AND(K68="",J68=""),"",CONCATENATE(J68,", ",K68)) -> Dacanay, Trisha Joyce | J68: Dacanay | K68: Trisha Joyce | M68: Female | N68: Blk 9 16 | O68: West Quirino Hill | Q68: 0966-917-7140 | R68: tisadacanay29@gmail.com | S68: 37497 | T68: =IF(S68="","",DATEDIF(S68,TODAY(),"Y")) -> 24 | U68: Baguio City | V68: Dacanay, Romil | W68: Dacanay, Lanie | X68: Yes | Z68: Yes | AE68: 4th year College | AF68: U.B. | AK68: Arts & Deco | AP68: Dacanay, Lanie | AQ68: Same as Home Address | AR68: Mother | AS68: 0927-768-5016
D69: Yes | E69: Sunday Goer | F69: Joshua | H69: Member | I69: =IF(AND(K69="",J69=""),"",CONCATENATE(J69,", ",K69)) -> Dacanay, Arianah Venisse | J69: Dacanay | K69: Arianah Venisse | L69: T | M69: Female | N69: Blk 9 16 | O69: West Quirino Hill | Q69: 0927-211-1783 | R69: arianahdacanay05@gmail.com | S69: 40301 | T69: =IF(S69="","",DATEDIF(S69,TODAY(),"Y")) -> 16 | U69: Baguio City | V69: Dacanay, Romil | W69: Dacanay, Lanie | X69: Yes | Z69: Yes | AE69: Grade 9 - Current | AF69: U.B. | AK69: Singing | AL69: Gymnastics | AP69: Dacanay, Lanie | AQ69: Same as Home Address | AR69: Mother | AS69: 0927-768-5016
D70: No | E70: Active | F70: Jacob | H70: Member | I70: =IF(AND(K70="",J70=""),"",CONCATENATE(J70,", ",K70)) -> Dagupen, Lindsay | J70: Dagupen | K70: Lindsay | M70: Female | T70: =IF(S70="","",DATEDIF(S70,TODAY(),"Y"))
D71: Yes | E71: Sunday Goer | F71: Joseph | H71: Member | I71: =IF(AND(K71="",J71=""),"",CONCATENATE(J71,", ",K71)) -> Daiwey, Sherman AJ | J71: Daiwey | K71: Sherman AJ | L71: C | M71: Male | N71: Blk D Lot 3 Diamond St Irisville | O71: Irisan | P71: Baguio City | Q71: 0985-200-1318 | R71: shermanaj2008@gmail.com | S71: 39808 | T71: =IF(S71="","",DATEDIF(S71,TODAY(),"Y")) -> 17 | U71: Baguio City | V71: Daiwey, Joel T. | W71: Daiwey, Aida C. | X71: Yes | Y71: February 2022 | Z71: Yes | AA71: 2019 | AE71: High School - Current | AF71: BCNScienceHS | AG71: Youth Environment & Sustainability Org. | AI71: Childrens Ministry | AK71: Teaching, Singing, Playing Musical Instruments, Arts & Deco, Photography | AL71: Volleyball, Chess/Dama | AM71: Painting, Cooking | AN71: 1 | AO71: 1 | AP71: Daiwey, Aida | AQ71: Same as Home Address | AR71: Mother | AS71: 0919-563-6945
D72: Yes | E72: Sunday Goer | F72: Elijah | H72: Member | I72: =IF(AND(K72="",J72=""),"",CONCATENATE(J72,", ",K72)) -> Daiwey, Havilah Leigh | J72: Daiwey | K72: Havilah Leigh | L72: C | M72: Female | N72: Blk D Lot 3 Diamond St Irisville | O72: Irisan | Q72: 0938-611-7400 | R72: havileigh.daiwey@gmail.com | S72: 36638 | T72: =IF(S72="","",DATEDIF(S72,TODAY(),"Y")) -> 26 | U72: Baguio City | V72: Daiwey, Joel T. | W72: Daiwey, Aida C. | X72: Yes | Y72: 39858 | Z72: Yes | AE72: BSN | AI72: Sunday School | AK72: Teaching, Singing | AL72: Volleyball | AN72: 2 | AP72: Daiwey, Aida | AQ72: Same as Home Address | AR72: Mother | AS72: 0919-563-6945
D73: Yes | E73: Other Church | F73: Samuel | H73: Member | I73: =IF(AND(K73="",J73=""),"",CONCATENATE(J73,", ",K73)) -> Daliyong, Marvie | J73: Daliyong | K73: Marvie | L73: C | M73: Female | N73: Purok 11 | O73: Upper Pinget | P73: Bulanao Tabuk City Kalinga | Q73: 0953-699-5863 | R73: daliyongmarvie27fd@gmail.com | S73: 38074 | T73: =IF(S73="","",DATEDIF(S73,TODAY(),"Y")) -> 22 | U73: Tabuk City, Kalinga | V73: Daliyong, Edwin | W73: Daliyong, Lucina | X73: Yes | Y73: 42968 | Z73: Yes | AC73: Sunrise Tabuk Church | AD73: Rev. Ronald Allan Lubrin | AE73: 2nd Year College - Current | AF73: U.B. | AI73: Music | AK73: Singing | AL73: Volleyball, Chess/Dama | AN73: 7 | AO73: 4 | AP73: Daliyong, Lucina C. | AQ73: Purok 6 Hilltop Bulanao, Tabuk City, Kalinga | AR73: Mother | AS73: 0965-311-9260
D74: No | E74: Active | F74: Samuel | G74: Hyphen | H74: Member | I74: =IF(AND(K74="",J74=""),"",CONCATENATE(J74,", ",K74)) -> Dangla, Joshua Thans | J74: Dangla | K74: Joshua Thans | M74: Male | T74: =IF(S74="","",DATEDIF(S74,TODAY(),"Y"))
D75: Yes | E75: Active | F75: David | H75: Member | I75: =IF(AND(K75="",J75=""),"",CONCATENATE(J75,", ",K75)) -> Dangla, Hiede Cattleyah | J75: Dangla | K75: Hiede Cattleyah | M75: Female | N75: Blk 1 Lot 46 | O75: Tadiangan, Tuba | Q75: 0921-743-2975 | R75: hiedecattleyahdangla@gmail.com | S75: 38634 | T75: =IF(S75="","",DATEDIF(S75,TODAY(),"Y")) -> 21 | U75: Camp 1 Kennon, Tuba | V75: Dangla, Constancio Sr. | W75: Dangla, Nancy | X75: Yes | Y75: 42351 | Z75: Yes | AE75: 1st Year College - Current | AF75: U.C. | AG75: Phil. Institute of Civil Eng. - Member | AH75: S.A. - U.C. | AI75: Media, Childrens Ministry | AJ75: Singing | AK75: Singing | AL75: Badminton | AN75: 5 | AO75: 4 | AP75: Dangla, Nancy | AQ75: Same as Home Address | AR75: Mother | AS75: 0961-491-3067
D76: Yes | E76: Active | F76: David | H76: Member | I76: =IF(AND(K76="",J76=""),"",CONCATENATE(J76,", ",K76)) -> Daskeo, Kleinny May | J76: Daskeo | K76: Kleinny May | L76: G | M76: Female | N76: Prk 6 Brookspoint | O76: Aurora Hill | P76: Tadian, Mt. Province | Q76: 0963-9516424 | R76: kleinnydaskeo@gmail.com | S76: 40734 | T76: =IF(S76="","",DATEDIF(S76,TODAY(),"Y")) -> 15 | U76: La Trinidad, Benguet | V76: Daskeo, Klient Patrick F. | W76: Daskeo, May G. | X76: Yes | Y76: 44933 | Z76: Yes | AA76: 2022 | AE76: Elementary - Current | AF76: Pinsao Elementary School | AI76: Bible Quizzing | AK76: Arts & Deco | AL76: Chess/Dama | AM76: Painting
D77: No | E77: Active | F77: David | H77: Member | I77: =IF(AND(K77="",J77=""),"",CONCATENATE(J77,", ",K77)) -> Daskeo, Khyzer Clark | J77: Daskeo | K77: Khyzer Clark | L77: G | M77: Male | T77: =IF(S77="","",DATEDIF(S77,TODAY(),"Y"))
D78: No | E78: Sunday Goer | F78: Paul | H78: Member | I78: =IF(AND(K78="",J78=""),"",CONCATENATE(J78,", ",K78)) -> De Ausen, Claude | J78: De Ausen | K78: Claude | M78: Male | T78: =IF(S78="","",DATEDIF(S78,TODAY(),"Y"))
D79: No | E79: Sunday Goer | F79: Jacob | H79: Member | I79: =IF(AND(K79="",J79=""),"",CONCATENATE(J79,", ",K79)) -> De Guzman, Sandy | J79: De Guzman | K79: Sandy | M79: Female | T79: =IF(S79="","",DATEDIF(S79,TODAY(),"Y"))
D80: No | E80: Sunday Goer | F80: Jacob | H80: Member | I80: =IF(AND(K80="",J80=""),"",CONCATENATE(J80,", ",K80)) -> De Guzman, Grant | J80: De Guzman | K80: Grant | M80: Male | T80: =IF(S80="","",DATEDIF(S80,TODAY(),"Y"))
D81: No | E81: Sunday Goer | F81: Samuel | H81: Member | I81: =IF(AND(K81="",J81=""),"",CONCATENATE(J81,", ",K81)) -> De Guzman, Faith | J81: De Guzman | K81: Faith | M81: Female | T81: =IF(S81="","",DATEDIF(S81,TODAY(),"Y"))
D82: No | E82: Bible Study | F82: Elijah | H82: Member | I82: =IF(AND(K82="",J82=""),"",CONCATENATE(J82,", ",K82)) -> Dela Cruz, Dani | J82: Dela Cruz | K82: Dani | M82: Female | T82: =IF(S82="","",DATEDIF(S82,TODAY(),"Y"))
D83: No | E83: Inactive | F83: Elijah | H83: Member | I83: =IF(AND(K83="",J83=""),"",CONCATENATE(J83,", ",K83)) -> Delos Trinos, Jessamin | J83: Delos Trinos | K83: Jessamin | M83: Female | T83: =IF(S83="","",DATEDIF(S83,TODAY(),"Y"))
D84: No | E84: Sunday Goer | F84: Elijah | H84: Member | I84: =IF(AND(K84="",J84=""),"",CONCATENATE(J84,", ",K84)) -> Diamsay, Khaizer | J84: Diamsay | K84: Khaizer | M84: Male | T84: =IF(S84="","",DATEDIF(S84,TODAY(),"Y"))
D85: No | E85: Sunday Goer | F85: Isaac | G85: Hyphen | H85: Member | I85: =IF(AND(K85="",J85=""),"",CONCATENATE(J85,", ",K85)) -> Dimasangca, Fajad | J85: Dimasangca | K85: Fajad | M85: Male | T85: =IF(S85="","",DATEDIF(S85,TODAY(),"Y"))
D86: Yes | E86: Other Church | F86: Abraham | G86: Hyphen | H86: Member | I86: =IF(AND(K86="",J86=""),"",CONCATENATE(J86,", ",K86)) -> Doligas, Kimberly | J86: Doligas | K86: Kimberly | L86: G | M86: Female | N86: Purok 5 | O86: Sto. Rosario Valley | P86: Sagapa Central Tadian Mt Province | Q86: 0906-203-4964 | R86: sevenfour18@gmail.com | S86: 30985 | T86: =IF(S86="","",DATEDIF(S86,TODAY(),"Y")) -> 41 | U86: Tadian, Mt. Province | V86: Doligas, Basilio S. | W86: Doligas, Yolanda G. | X86: Yes | Y86: 1998 | Z86: Yes | AB86: Roman Catholic | AE86: College Graduate | AH86: Faculty - U.C. | AK86: Teaching | AN86: 4 | AO86: 5 | AP86: Doligas, Prince G. | AQ86: Balili, La Trinidad | AR86: Sibling | AS86: 0947-736-2629
D87: Yes | I87: =IF(AND(K87="",J87=""),"",CONCATENATE(J87,", ",K87)) -> Doligas, Kemuel | J87: Doligas | K87: Kemuel | L87: G | M87: Male | N87: Poblacion Tadian Mt. Province | Q87: 0967-021-9292 | R87: kemueldoligas@gmail.com | S87: 38128 | T87: =IF(S87="","",DATEDIF(S87,TODAY(),"Y")) -> 22 | U87: Lepanto | V87: Doligas, Basilio S. | W87: Doligas, Yolanda G. | X87: Yes | Z87: Yes | AC87: UPC Lepanto | AD87: Ptr. Joel Morales | AE87: Currently enrolled - College | AF87: U.C. | AG87: ROTC
D88: No | E88: Active | F88: Paul | H88: Member | I88: =IF(AND(K88="",J88=""),"",CONCATENATE(J88,", ",K88)) -> Domigsi, Lyza Mae | J88: Domigsi | K88: Lyza Mae | M88: Female | T88: =IF(S88="","",DATEDIF(S88,TODAY(),"Y"))
D89: No | E89: Bible Study | F89: Jacob | H89: Member | I89: =IF(AND(K89="",J89=""),"",CONCATENATE(J89,", ",K89)) -> Donaire, Lovely | J89: Donaire | K89: Lovely | M89: Female | T89: =IF(S89="","",DATEDIF(S89,TODAY(),"Y"))
D90: Yes | I90: =IF(AND(K90="",J90=""),"",CONCATENATE(J90,", ",K90)) -> Dumaniel, Nilda | J90: Dumaniel | K90: Nilda | M90: Female | N90: Capiz, Roxas City | P90: Capiz, Roxas City | Q90: 0961-664-9886 | R90: nilda.19dumaniel@gmail.com | T90: =IF(S90="","",DATEDIF(S90,TODAY(),"Y")) | V90: Dumaniel, Joseph | W90: Dumaniel, Nida | X90: Yes | Y90: 43973 | Z90: Yes | AA90: 46103 | AC90: The Good News Church | AD90: Ptr. Joseph Vargas | AK90: Teaching | AM90: Cooking
D91: Yes | E91: Sunday Goer | F91: Abraham | G91: Hyphen | H91: Member | I91: =IF(AND(K91="",J91=""),"",CONCATENATE(J91,", ",K91)) -> Feliciano, Gideon | J91: Feliciano | K91: Gideon | L91: P | M91: Male | N91: 23 Purok 8 | O91: Asin Road | Q91: 0910-410-5978 | R91: feliciano.gidoen1012@gmail.com | T91: =IF(S91="","",DATEDIF(S91,TODAY(),"Y")) | X91: Yes | Z91: Yes | AE91: BSED Math, MAED Math | AF91: U.C. | AH91: Medical Records Clerk - SLU SHMC | AI91: Ushering | AK91: Teaching | AL91: Volleyball, Basketball, Badminton, Chess/Dama | AM91: Cooking
D92: Yes | E92: Sunday Goer | F92: Elisha | H92: Member | I92: =IF(AND(K92="",J92=""),"",CONCATENATE(J92,", ",K92)) -> Feliciano, Geraldine | J92: Feliciano | K92: Geraldine | L92: P | M92: Female | N92: 23 J. Smith Drive | O92: Asin Road | P92: Lomon Kapangan, Benguet | Q92: 0939-258-3813 | R92: greendail31@gmail.com | S92: 35277 | T92: =IF(S92="","",DATEDIF(S92,TODAY(),"Y")) -> 30 | U92: Tublay, Benguet | V92: Feliciano, Inciong | W92: Pagnas, Felisa | X92: Yes | Y92: May 2013 | Z92: Yes | AA92: May 2013 | AB92: Roman Catholic | AE92: College | AH92: Admin - Leadergraphics | AI92: Ushering | AK92: Teaching | AN92: 1 | AO92: 1 | AP92: Saingan, Genevieve | AQ92: Tadiangan Tuba, benguet | AR92: Sibling | AS92: 0938-808-0581
D93: No | E93: Inactive | F93: Isaac | H93: Member | I93: =IF(AND(K93="",J93=""),"",CONCATENATE(J93,", ",K93)) -> Felipe, Nathaniel | J93: Felipe | K93: Nathaniel | M93: Male | T93: =IF(S93="","",DATEDIF(S93,TODAY(),"Y"))
D94: No | E94: Inactive | F94: Isaac | H94: Member | I94: =IF(AND(K94="",J94=""),"",CONCATENATE(J94,", ",K94)) -> Felipe, Naphtali | J94: Felipe | K94: Naphtali | M94: Male | T94: =IF(S94="","",DATEDIF(S94,TODAY(),"Y"))
D95: Yes | I95: =IF(AND(K95="",J95=""),"",CONCATENATE(J95,", ",K95)) -> Felipe, Yael | J95: Felipe | K95: Yael | L95: B | M95: Male | N95: B2 Lower | O95: Fairview | Q95: 0948-071-0916 | S95: 41009 | T95: =IF(S95="","",DATEDIF(S95,TODAY(),"Y")) -> 14 | U95: Abatan, Buguias | V95: Felipe, Bernard | W95: Felipe, Vilma | X95: Yes | Y95: 45765 | Z95: Yes | AA95: 45800 | AC95: Calvary Tabernacle Baguio | AD95: Ptr. Eugene Banez | AF95: Baguio Shiloam Christian Academy | AK95: Guitar | AL95: Football | AM95: Cooking
D96: No | E96: Inactive | F96: Elisha | H96: Member | I96: =IF(AND(K96="",J96=""),"",CONCATENATE(J96,", ",K96)) -> Ferreras, Raymond | J96: Ferreras | K96: Raymond | M96: Male | T96: =IF(S96="","",DATEDIF(S96,TODAY(),"Y"))
D97: Yes | E97: Sunday Goer | F97: David | H97: Member | I97: =IF(AND(K97="",J97=""),"",CONCATENATE(J97,", ",K97)) -> Garcia, Linelle | J97: Garcia | K97: Linelle | L97: B | M97: Female | N97: OC-074 | O97: Central Tawang, La Trinidad | P97: Tawang, La Trinidad | Q97: 0991-365-7312 | R97: linellegarciakm12@gmail.com | S97: 39185 | T97: =IF(S97="","",DATEDIF(S97,TODAY(),"Y")) -> 19 | U97: La Trinidad, Benguet | V97: Garcia, Manuel G. | W97: Garcia, Carlita B. | X97: Yes | Z97: Yes | AE97: Senior High School - Graduating | AF97: B.S.U. | AJ97: Music, Childrens Ministries | AK97: Teaching, Photography, Communication | AL97: Volleyball, Badminton, Softball | AN97: 3 | AO97: 4 | AP97: Castro, Ellen | AQ97: Same as Home Address | AR97: Aunt | AS97: 0909-383-8570
D98: No | E98: Sunday Goer | F98: Paul | H98: Member | I98: =IF(AND(K98="",J98=""),"",CONCATENATE(J98,", ",K98)) -> Garcia, Lemuel | J98: Garcia | K98: Lemuel | M98: Male | T98: =IF(S98="","",DATEDIF(S98,TODAY(),"Y"))
D99: No | E99: Inactive | F99: Jacob | H99: Member | I99: =IF(AND(K99="",J99=""),"",CONCATENATE(J99,", ",K99)) -> Gayados, Ivan | J99: Gayados | K99: Ivan | M99: Male | T99: =IF(S99="","",DATEDIF(S99,TODAY(),"Y"))
D100: No | E100: Inactive | F100: Samuel | H100: Member | I100: =IF(AND(K100="",J100=""),"",CONCATENATE(J100,", ",K100)) -> Gayados, Cleo Jean | J100: Gayados | K100: Cleo Jean | M100: Female | T100: =IF(S100="","",DATEDIF(S100,TODAY(),"Y"))
D101: No | E101: Inactive | F101: Joshua | H101: Member | I101: =IF(AND(K101="",J101=""),"",CONCATENATE(J101,", ",K101)) -> Gayados, Belle | J101: Gayados | K101: Belle | M101: Female | T101: =IF(S101="","",DATEDIF(S101,TODAY(),"Y"))
...

Sheet Childrens
A1: CHILDREN'S MINISTRY
A3: Count per filter | B3: =SUBTOTAL(3,Childrens!$I$5:$I$201) -> 30
D4: With Profiling Forn | E4: Status | F4: Age Group | G4: Full Name (Last, First) | H4: Last Name | I4: First Name | J4: Middle Initial | K4: Gender | L4: Street | M4: City Address | N4: Provincial Address | O4: Contact Number | P4: Email | Q4: Birthdate | R4: Age | S4: Birthplace | T4: Father | U4: Mother | V4: Baptized in Water | W4: Date | X4: Baptized in Holy Ghost | Y4: Date2 | Z4: Former Religious Affiliation | AA4: Home Church | AB4: Pastor's Name | AC4: Grade level | AD4: School Name | AE4: Health Information | AF4: Allergies | AG4: Medical Conditions | AH4: Ministries you like to be involved in | AI4: Interests and Hobbies | AJ4: Favorite Activities | AK4: Favorite Sports | AL4: Special Skills or Talents | AM4: Emergency Contact | AN4: Address | AO4: Relationship | AP4: Contact Number2
D5: Yes | F5: =IF($R5="","",IF($R5>=13,"Junior",IF(AND($R5>=11,$R5<=12),"Primary",IF(AND($R5>=9,$R5<=10),"Beginners 2",IF(AND($R5>=7,$R5<=8),"Beginners 1",IF(AND($R5>=5,$R5<=6),"Toddlers 2",IF(AND($R5>=3,$R5<=4),"Toddlers 1",""))))))) -> Beginners 2 | G5: =IF(AND(I5="",H5=""),"",CONCATENATE(H5,", ",I5)) -> Aguinaldo, Raiven Ezekel | H5: Aguinaldo | I5: Raiven Ezekel | J5: L | K5: Male | L5: 354 Purok 1 | M5: Pinsao Pilot Project | O5: 0991-365-5743 | Q5: 42762 | R5: =IF(Q5="","",DATEDIF(Q5,TODAY(),"Y")) -> 9 | S5: Palawan | T5: Aguinaldo, John Philip | U5: Larida, Ma. Concepcion | V5: No | X5: No | AC5: Grade 2 | AD5: Mabini Elementary School | AI5: Drawing, Singing | AJ5: Basketball | AK5: Swimming | AL5: Singing, Dancing, Eating | AM5: Larida, Maria | AN5: 354 Purok 1, Pinsao Pilot Project | AO5: Mother | AP5: 0950-525-5114
D6: Yes | F6: =IF($R6="","",IF($R6>=13,"Junior",IF(AND($R6>=11,$R6<=12),"Primary",IF(AND($R6>=9,$R6<=10),"Beginners 2",IF(AND($R6>=7,$R6<=8),"Beginners 1",IF(AND($R6>=5,$R6<=6),"Toddlers 2",IF(AND($R6>=3,$R6<=4),"Toddlers 1",""))))))) -> Beginners 1 | G6: =IF(AND(I6="",H6=""),"",CONCATENATE(H6,", ",I6)) -> Aguinaldo, Raveena Scarlet | H6: Aguinaldo | I6: Raveena Scarlet | J6: L | K6: Female | L6: 354 Purok 1 | M6: Pinsao Pilot Project | Q6: 43292 | R6: =IF(Q6="","",DATEDIF(Q6,TODAY(),"Y")) -> 8 | S6: Baguio City | T6: Aguinaldo, John Philip | U6: Larida, Ma. Concepcion | V6: No | X6: No | AC6: Grade 1 | AD6: Mabini Elementary School | AH6: Sunday School | AI6: Singing | AJ6: Singing | AK6: Swimming | AL6: Singing | AM6: Larida, Maria | AN6: 354 Purok 1, Pinsao Pilot Project | AO6: Mother | AP6: 0950-525-5114
D7: Yes | F7: =IF($R7="","",IF($R7>=13,"Junior",IF(AND($R7>=11,$R7<=12),"Primary",IF(AND($R7>=9,$R7<=10),"Beginners 2",IF(AND($R7>=7,$R7<=8),"Beginners 1",IF(AND($R7>=5,$R7<=6),"Toddlers 2",IF(AND($R7>=3,$R7<=4),"Toddlers 1",""))))))) -> Junior | G7: =IF(AND(I7="",H7=""),"",CONCATENATE(H7,", ",I7)) -> Amistad, Elisha | H7: Amistad | I7: Elisha | J7: C | K7: Male | L7: 7 Purok 1 | M7: Irisan | Q7: 41535 | R7: =IF(Q7="","",DATEDIF(Q7,TODAY(),"Y")) -> 13 | S7: Baguio City | T7: Amistad, Joseph Sinesin H. | U7: Amistad, Hadassah Olive C. | V7: No | X7: No | AC7: Grade 6 | AD7: Quirino Elementary School | AI7: Reading | AK7: Badminton, Table Tennis | AM7: Amistad, Joseph Sinesin H. | AN7: 7 Purok 1, Irisan, Baguio City | AO7: Father | AP7: 0918-502-8785
D8: Yes | F8: =IF($R8="","",IF($R8>=13,"Junior",IF(AND($R8>=11,$R8<=12),"Primary",IF(AND($R8>=9,$R8<=10),"Beginners 2",IF(AND($R8>=7,$R8<=8),"Beginners 1",IF(AND($R8>=5,$R8<=6),"Toddlers 2",IF(AND($R8>=3,$R8<=4),"Toddlers 1",""))))))) -> Toddlers 1 | G8: =IF(AND(I8="",H8=""),"",CONCATENATE(H8,", ",I8)) -> Amistad, Judah | H8: Amistad | I8: Judah | J8: C | K8: Male | L8: 7 Purok 1 | M8: Irisan | Q8: 45189 | R8: =IF(Q8="","",DATEDIF(Q8,TODAY(),"Y")) -> 3 | S8: Baguio City | T8: Amistad, Joseph Sinesin H. | U8: Amistad, Hadassah Olive C. | V8: No | X8: No | AM8: Amistad, Joseph Sinesin H. | AN8: 7 Purok 1, Irisan, Baguio City | AO8: Father | AP8: 0918-502-8785
D9: Yes | F9: =IF($R9="","",IF($R9>=13,"Junior",IF(AND($R9>=11,$R9<=12),"Primary",IF(AND($R9>=9,$R9<=10),"Beginners 2",IF(AND($R9>=7,$R9<=8),"Beginners 1",IF(AND($R9>=5,$R9<=6),"Toddlers 2",IF(AND($R9>=3,$R9<=4),"Toddlers 1",""))))))) -> Beginners 2 | G9: =IF(AND(I9="",H9=""),"",CONCATENATE(H9,", ",I9)) -> Amistad, Lucas | H9: Amistad | I9: Lucas | J9: C | K9: Male | L9: 7 Purok 1 | M9: Irisan | Q9: 42536 | R9: =IF(Q9="","",DATEDIF(Q9,TODAY(),"Y")) -> 10 | S9: Baguio City | T9: Amistad, Joseph Sinesin H. | U9: Amistad, Hadassah Olive C. | V9: No | X9: No | AC9: Grade 3 | AD9: Quirino Elementary School | AM9: Amistad, Joseph Sinesin H. | AN9: 7 Purok 1, Irisan, Baguio City | AO9: Father | AP9: 0918-502-8785
D10: No | F10: =IF($R10="","",IF($R10>=13,"Junior",IF(AND($R10>=11,$R10<=12),"Primary",IF(AND($R10>=9,$R10<=10),"Beginners 2",IF(AND($R10>=7,$R10<=8),"Beginners 1",IF(AND($R10>=5,$R10<=6),"Toddlers 2",IF(AND($R10>=3,$R10<=4),"Toddlers 1",""))))))) | G10: =IF(AND(I10="",H10=""),"",CONCATENATE(H10,", ",I10)) -> Amplogio, Zhoilo | H10: Amplogio | I10: Zhoilo | R10: =IF(Q10="","",DATEDIF(Q10,TODAY(),"Y"))
D11: No | F11: =IF($R11="","",IF($R11>=13,"Junior",IF(AND($R11>=11,$R11<=12),"Primary",IF(AND($R11>=9,$R11<=10),"Beginners 2",IF(AND($R11>=7,$R11<=8),"Beginners 1",IF(AND($R11>=5,$R11<=6),"Toddlers 2",IF(AND($R11>=3,$R11<=4),"Toddlers 1",""))))))) | G11: =IF(AND(I11="",H11=""),"",CONCATENATE(H11,", ",I11)) -> Amplogio, Harvey | H11: Amplogio | I11: Harvey | R11: =IF(Q11="","",DATEDIF(Q11,TODAY(),"Y"))
D12: Yes | F12: =IF($R12="","",IF($R12>=13,"Junior",IF(AND($R12>=11,$R12<=12),"Primary",IF(AND($R12>=9,$R12<=10),"Beginners 2",IF(AND($R12>=7,$R12<=8),"Beginners 1",IF(AND($R12>=5,$R12<=6),"Toddlers 2",IF(AND($R12>=3,$R12<=4),"Toddlers 1",""))))))) -> Beginners 2 | G12: =IF(AND(I12="",H12=""),"",CONCATENATE(H12,", ",I12)) -> Aragon, Reviel Arcai | H12: Aragon | I12: Reviel Arcai | J12: W | K12: Male | L12: 8 De Jesus St | M12: Aurora Hill | N12: 0236 Silangan St. Bayog Los Banos, Laguna | Q12: 42831 | R12: =IF(Q12="","",DATEDIF(Q12,TODAY(),"Y")) -> 9 | S12: Laguna | T12: Aragon, Marc Andrew Rai | U12: Aragon, Elaine Marie | V12: No | X12: No | AC12: Grade 2 | AD12: Doña Aurora Elementary School | AH12: Music Ministry, Bible Quizzing | AI12: Watching | AJ12: Singing | AK12: Soccer | AM12: Aragon, Elaine Marie | AN12: 8 De Jesus St Aurora Hill | AO12: Mother | AP12: 0994-157-8808
D13: Yes | F13: =IF($R13="","",IF($R13>=13,"Junior",IF(AND($R13>=11,$R13<=12),"Primary",IF(AND($R13>=9,$R13<=10),"Beginners 2",IF(AND($R13>=7,$R13<=8),"Beginners 1",IF(AND($R13>=5,$R13<=6),"Toddlers 2",IF(AND($R13>=3,$R13<=4),"Toddlers 1",""))))))) -> Toddlers 2 | G13: =IF(AND(I13="",H13=""),"",CONCATENATE(H13,", ",I13)) -> Bacsa, Vienna Brylle | H13: Bacsa | I13: Vienna Brylle | J13: B | K13: Female | L13: 048 B Boted | M13: Tawang, La Trinidad | O13: 0967-301-6762 | P13: bryllevhien@gmail.com | Q13: 44473 | R13: =IF(Q13="","",DATEDIF(Q13,TODAY(),"Y")) -> 5 | S13: La Trinidad, Benguet | T13: Bacsa, Vhal | U13: Bacsa, Hyneth Gwenn | V13: No | X13: No | AM13: Bacsa, Hyneth Gwen | AN13: 048 B Boted Tawang, La Trinidad | AO13: Mother | AP13: 0967-301-6762
D14: Yes | F14: =IF($R14="","",IF($R14>=13,"Junior",IF(AND($R14>=11,$R14<=12),"Primary",IF(AND($R14>=9,$R14<=10),"Beginners 2",IF(AND($R14>=7,$R14<=8),"Beginners 1",IF(AND($R14>=5,$R14<=6),"Toddlers 2",IF(AND($R14>=3,$R14<=4),"Toddlers 1",""))))))) | G14: =IF(AND(I14="",H14=""),"",CONCATENATE(H14,", ",I14)) -> Bacsa, Xyrelle Vhien | H14: Bacsa | I14: Xyrelle Vhien | J14: B | K14: Female | L14: 048 B Boted | M14: Tawang, La Trinidad | O14: 0967-301-6762 | P14: bryllevhien@gmail.com | Q14: 45410 | R14: =IF(Q14="","",DATEDIF(Q14,TODAY(),"Y")) -> 2 | S14: La Trinidad, Benguet | T14: Bacsa, Vhal | U14: Bacsa, Hyneth Gwenn | V14: No | X14: No | AM14: Bacsa, Hyneth Gwen | AN14: 048 B Boted Tawang, La Trinidad | AO14: Mother | AP14: 0967-301-6762
D15: Yes | F15: =IF($R15="","",IF($R15>=13,"Junior",IF(AND($R15>=11,$R15<=12),"Primary",IF(AND($R15>=9,$R15<=10),"Beginners 2",IF(AND($R15>=7,$R15<=8),"Beginners 1",IF(AND($R15>=5,$R15<=6),"Toddlers 2",IF(AND($R15>=3,$R15<=4),"Toddlers 1",""))))))) -> Junior | G15: =IF(AND(I15="",H15=""),"",CONCATENATE(H15,", ",I15)) -> Bambao, Kizzayha Mayline | H15: Bambao | I15: Kizzayha Mayline | K15: Female | L15: 15 Balacbac Central | M15: Sto. Tomas Proper | O15: 0912-186-2964 | Q15: 41538 | R15: =IF(Q15="","",DATEDIF(Q15,TODAY(),"Y")) -> 13 | S15: Baguio City | T15: Bambao, Angel Sr. | U15: Bambao, Joanna | V15: Yes | W15: 45683 | X15: Yes | Y15: 45683 | Z15: Roman Catholic | AC15: Grade 6 | AD15: SLU | AH15: Music Ministry, Bible Quizzing | AI15: Arts and croachet | AM15: Bambao, Joanna | AN15: 15 Balacbac Central, Sto. Tomas Proper | AO15: Mother | AP15: 0912-186-2964
D16: Yes | F16: =IF($R16="","",IF($R16>=13,"Junior",IF(AND($R16>=11,$R16<=12),"Primary",IF(AND($R16>=9,$R16<=10),"Beginners 2",IF(AND($R16>=7,$R16<=8),"Beginners 1",IF(AND($R16>=5,$R16<=6),"Toddlers 2",IF(AND($R16>=3,$R16<=4),"Toddlers 1",""))))))) -> Primary | G16: =IF(AND(I16="",H16=""),"",CONCATENATE(H16,", ",I16)) -> Bentrez, Jezreel Genrev | H16: Bentrez | I16: Jezreel Genrev | K16: Male | L16: 123 Blk 3 | M16: Middle Quirino Hill | O16: 0927-211-0251 | Q16: 41809 | R16: =IF(Q16="","",DATEDIF(Q16,TODAY(),"Y")) -> 12 | S16: Baguio City | T16: Bentrez, Isaac | U16: Bentrez, Jacqueline R. | V16: Yes | W16: 45697 | X16: Yes | AC16: Grade 5 | AD16: Lucban Elementary School Science Class | AH16: Bible Quizzing | AI16: Gym Workouts | AJ16: Playing Chess | AK16: Chess, Soccer | AL16: Drums | AM16: Bentrez, Isaac | AN16: 123 Blk 3 Middle Quirino Hill, Baguio City | AO16: Father | AP16: 0977-822-5999
D17: Yes | F17: =IF($R17="","",IF($R17>=13,"Junior",IF(AND($R17>=11,$R17<=12),"Primary",IF(AND($R17>=9,$R17<=10),"Beginners 2",IF(AND($R17>=7,$R17<=8),"Beginners 1",IF(AND($R17>=5,$R17<=6),"Toddlers 2",IF(AND($R17>=3,$R17<=4),"Toddlers 1",""))))))) -> Junior | G17: =IF(AND(I17="",H17=""),"",CONCATENATE(H17,", ",I17)) -> Castillo, Princess Lhianne | H17: Castillo | I17: Princess Lhianne | J17: B | K17: Female | L17: 53 Badihoy St | M17: Guisad Surong | N17: Blk 82 Lot 116 Area D, Sapang Palay, San Jose Del Monte Bulacan City | O17: 0955-318-8813 | Q17: 41485 | R17: =IF(Q17="","",DATEDIF(Q17,TODAY(),"Y")) -> 13 | S17: Bulacan | T17: Castillo, Antohino | U17: Belleza, Rosie | V17: No | X17: No | AC17: Grade 5 | AD17: Easter College School | AH17: Sunday School | AI17: Arts and Deco | AK17: Volleyball | AL17: Painting | AM17: Belleza, Rosie | AN17: 53 Badihoy St Guisad, Surong | AO17: Mother | AP17: 0955-318-8813
D18: Yes | F18: =IF($R18="","",IF($R18>=13,"Junior",IF(AND($R18>=11,$R18<=12),"Primary",IF(AND($R18>=9,$R18<=10),"Beginners 2",IF(AND($R18>=7,$R18<=8),"Beginners 1",IF(AND($R18>=5,$R18<=6),"Toddlers 2",IF(AND($R18>=3,$R18<=4),"Toddlers 1",""))))))) -> Toddlers 2 | G18: =IF(AND(I18="",H18=""),"",CONCATENATE(H18,", ",I18)) -> Castro, Prince Jedi | H18: Castro | I18: Prince Jedi | J18: A | K18: Male | L18: 7 Purok 1 | M18: Irisan | Q18: 44090 | R18: =IF(Q18="","",DATEDIF(Q18,TODAY(),"Y")) -> 6 | S18: Quezon City | T18: Castro, Jewel | U18: Albuera, Dian | V18: No | X18: No | AC18: Pre-kindergarten | AD18: Cypress Christian School | AG18: G6PD | AM18: Amistad, Joseph Sinesin H. | AN18: 7 Purok 1, Irisan, Baguio City | AO18: Uncle | AP18: 0918-502-8785
D19: Yes | F19: =IF($R19="","",IF($R19>=13,"Junior",IF(AND($R19>=11,$R19<=12),"Primary",IF(AND($R19>=9,$R19<=10),"Beginners 2",IF(AND($R19>=7,$R19<=8),"Beginners 1",IF(AND($R19>=5,$R19<=6),"Toddlers 2",IF(AND($R19>=3,$R19<=4),"Toddlers 1",""))))))) -> Beginners 1 | G19: =IF(AND(I19="",H19=""),"",CONCATENATE(H19,", ",I19)) -> Cayandag, James | H19: Cayandag | I19: James | K19: Male | L19: P2 - 224 | M19: Poliwes | Q19: 43385 | R19: =IF(Q19="","",DATEDIF(Q19,TODAY(),"Y")) -> 8 | S19: Baguio City | T19: Cayandag, Jimmy | U19: Cayandag, Marilou | V19: No | X19: No | Z19: Roman Catholic | Anglican | AC19: Grade 1 | AD19: Baguio Central School | AM19: Cayandag, Marilou | AN19: P2 - 224 Poliwes, Kn. Rd., Baguio City | AO19: Mother | AP19: 0910-807-5193
D20: Yes | F20: =IF($R20="","",IF($R20>=13,"Junior",IF(AND($R20>=11,$R20<=12),"Primary",IF(AND($R20>=9,$R20<=10),"Beginners 2",IF(AND($R20>=7,$R20<=8),"Beginners 1",IF(AND($R20>=5,$R20<=6),"Toddlers 2",IF(AND($R20>=3,$R20<=4),"Toddlers 1",""))))))) -> Beginners 2 | G20: =IF(AND(I20="",H20=""),"",CONCATENATE(H20,", ",I20)) -> Cayandag, Jazzy | H20: Cayandag | I20: Jazzy | K20: Female | L20: P2 - 224 | M20: Poliwes | Q20: 42605 | R20: =IF(Q20="","",DATEDIF(Q20,TODAY(),"Y")) -> 10 | S20: Baguio City | T20: Cayandag, Jimmy | U20: Cayandag, Marilou | V20: No | X20: No | Z20: Roman Catholic | Anglican | AC20: Grade 2 | AD20: Baguio Central School | AM20: Cayandag, Marilou | AN20: P2 - 224 Poliwes, Kn. Rd., Baguio City | AO20: Mother | AP20: 0910-807-5193
D21: Yes | F21: =IF($R21="","",IF($R21>=13,"Junior",IF(AND($R21>=11,$R21<=12),"Primary",IF(AND($R21>=9,$R21<=10),"Beginners 2",IF(AND($R21>=7,$R21<=8),"Beginners 1",IF(AND($R21>=5,$R21<=6),"Toddlers 2",IF(AND($R21>=3,$R21<=4),"Toddlers 1",""))))))) -> Primary | G21: =IF(AND(I21="",H21=""),"",CONCATENATE(H21,", ",I21)) -> Coyasan, Jharen | H21: Coyasan | I21: Jharen | K21: Male | L21: AB006 | M21: Ambiong, La Trinidad | O21: 0928-194-5799 | Q21: 42100 | R21: =IF(Q21="","",DATEDIF(Q21,TODAY(),"Y")) -> 11 | S21: Baguio City | T21: Coyasan, Priston | U21: Coyasan, Mary Joe | V21: No | X21: No | Z21: Roman Catholic | AC21: Grade 4 | AD21: Ambiong Elementary School | AI21: Basketball, Biking, Watching, Cooking, Drawing | AJ21: Basketball | AK21: Basketball | AM21: Coyasan, Mary Joe | AN21: AB006 Ambiong, La Trinidad | AO21: Mother | AP21: 0928-194-5799
D22: No | F22: =IF($R22="","",IF($R22>=13,"Junior",IF(AND($R22>=11,$R22<=12),"Primary",IF(AND($R22>=9,$R22<=10),"Beginners 2",IF(AND($R22>=7,$R22<=8),"Beginners 1",IF(AND($R22>=5,$R22<=6),"Toddlers 2",IF(AND($R22>=3,$R22<=4),"Toddlers 1",""))))))) -> Primary | G22: =IF(AND(I22="",H22=""),"",CONCATENATE(H22,", ",I22)) -> De Castro, Marl Jakob | H22: De Castro | I22: Marl Jakob | J22: F | K22: Male | L22: 25B Purok 4 | M22: Bakakeng Norte | O22: 0906-3785711 | Q22: 42292 | R22: =IF(Q22="","",DATEDIF(Q22,TODAY(),"Y")) -> 11
D23: No | F23: =IF($R23="","",IF($R23>=13,"Junior",IF(AND($R23>=11,$R23<=12),"Primary",IF(AND($R23>=9,$R23<=10),"Beginners 2",IF(AND($R23>=7,$R23<=8),"Beginners 1",IF(AND($R23>=5,$R23<=6),"Toddlers 2",IF(AND($R23>=3,$R23<=4),"Toddlers 1",""))))))) -> Beginners 1 | G23: =IF(AND(I23="",H23=""),"",CONCATENATE(H23,", ",I23)) -> De Castro, Rebekah Faith | H23: De Castro | I23: Rebekah Faith | J23: F | K23: Female | L23: 25B Purok 4 | M23: Bakakeng Norte | O23: 0906-3785711 | Q23: 43286 | R23: =IF(Q23="","",DATEDIF(Q23,TODAY(),"Y")) -> 8
A24: Age bracket (to check) | D24: Yes | F24: =IF($R24="","",IF($R24>=13,"Junior",IF(AND($R24>=11,$R24<=12),"Primary",IF(AND($R24>=9,$R24<=10),"Beginners 2",IF(AND($R24>=7,$R24<=8),"Beginners 1",IF(AND($R24>=5,$R24<=6),"Toddlers 2",IF(AND($R24>=3,$R24<=4),"Toddlers 1",""))))))) -> Beginners 2 | G24: =IF(AND(I24="",H24=""),"",CONCATENATE(H24,", ",I24)) -> Galasgas, Yzhexiel Zyric | H24: Galasgas | I24: Yzhexiel Zyric | J24: B | K24: Male | L24: FC 323 2nd Rd | M24: Central Balili, La Trinidad | Q24: 42727 | R24: =IF(Q24="","",DATEDIF(Q24,TODAY(),"Y")) -> 9 | S24: Baguio City | T24: Galasgas, Mark Noel | U24: Boteng, Angeline | V24: No | X24: Yes | AC24: Grade 2 | AD24: BSU-ELS | AH24: Music Ministry | AI24: Singing | AJ24: Singing | AL24: Singing | AM24: Boteng, Angeline | AN24: FC 323 2nd Rd, Central Balili, La Trinidad | AO24: Mother | AP24: 0928-412-5014
A25: Toddlers 1: 4-5 y/o | D25: Yes | F25: =IF($R25="","",IF($R25>=13,"Junior",IF(AND($R25>=11,$R25<=12),"Primary",IF(AND($R25>=9,$R25<=10),"Beginners 2",IF(AND($R25>=7,$R25<=8),"Beginners 1",IF(AND($R25>=5,$R25<=6),"Toddlers 2",IF(AND($R25>=3,$R25<=4),"Toddlers 1",""))))))) -> Beginners 1 | G25: =IF(AND(I25="",H25=""),"",CONCATENATE(H25,", ",I25)) -> Gumpal, Aiko Gwyneth | H25: Gumpal | I25: Aiko Gwyneth | J25: C | K25: Female | L25: 70 | M25: Magsaysay Private Road | P25: gumpalaikogwyneth@gmail.com | Q25: 43688 | R25: =IF(Q25="","",DATEDIF(Q25,TODAY(),"Y")) -> 7 | S25: Baguio City | T25: Gumpal, Nicko Rey T. | U25: Gumpal, Aimee C. | V25: No | X25: No | AC25: Kindergarten | AD25: Berkeley School | AF25: Under Observation | AI25: Arts and Crafts, Painting | AM25: Gumpal, Aimee C. | AN25: 70 Magsaysay Private Road, Baguio City | AO25: Mother | AP25: 0917-176-0408
A26: Toddlers 2: 6-7y/o | D26: Yes | F26: =IF($R26="","",IF($R26>=13,"Junior",IF(AND($R26>=11,$R26<=12),"Primary",IF(AND($R26>=9,$R26<=10),"Beginners 2",IF(AND($R26>=7,$R26<=8),"Beginners 1",IF(AND($R26>=5,$R26<=6),"Toddlers 2",IF(AND($R26>=3,$R26<=4),"Toddlers 1",""))))))) -> Junior | G26: =IF(AND(I26="",H26=""),"",CONCATENATE(H26,", ",I26)) -> Kiaki, Allen James | H26: Kiaki | I26: Allen James | K26: Male | L26: 14 Purok 24 | M26: San Carlos Heights | Q26: 41336 | R26: =IF(Q26="","",DATEDIF(Q26,TODAY(),"Y")) -> 13 | S26: Baguio City | T26: Kiaki, Joerdan | U26: Kiaki, Ma. Luningning D. | V26: No | X26: No | Z26: Roman Catholic | AC26: Grade 6 | AD26: Josefa Elementary School | AG26: Asthma | AK26: Basketball | AL26: Singing | AM26: Kiaki, Ma. Luningning D. | AN26: 14 Purok 24 San Carlos Heights, Baguio City | AO26: Mother
A27: Beginners 1: 8-9 y/o | D27: Yes | F27: =IF($R27="","",IF($R27>=13,"Junior",IF(AND($R27>=11,$R27<=12),"Primary",IF(AND($R27>=9,$R27<=10),"Beginners 2",IF(AND($R27>=7,$R27<=8),"Beginners 1",IF(AND($R27>=5,$R27<=6),"Toddlers 2",IF(AND($R27>=3,$R27<=4),"Toddlers 1",""))))))) -> Beginners 1 | G27: =IF(AND(I27="",H27=""),"",CONCATENATE(H27,", ",I27)) -> Kiaki, Paul Jordan | H27: Kiaki | I27: Paul Jordan | K27: Male | L27: 14 Purok 24 | M27: San Carlos Heights | Q27: 43442 | R27: =IF(Q27="","",DATEDIF(Q27,TODAY(),"Y")) -> 7 | S27: Baguio City | T27: Kiaki, Joerdan | U27: Kiaki, Ma. Luningning D. | V27: No | X27: No | AC27: Kindergarten 2 | AD27: King Kids Christian Academy | AG27: Asthma | AK27: Dance | AL27: Drawing | AM27: Kiaki, Ma. Luningning D. | AN27: 14 Purok 24 San Carlos Heights, Baguio City | AO27: Mother
A28: Beginners 2: 9-10 y/o | D28: Yes | F28: =IF($R28="","",IF($R28>=13,"Junior",IF(AND($R28>=11,$R28<=12),"Primary",IF(AND($R28>=9,$R28<=10),"Beginners 2",IF(AND($R28>=7,$R28<=8),"Beginners 1",IF(AND($R28>=5,$R28<=6),"Toddlers 2",IF(AND($R28>=3,$R28<=4),"Toddlers 1",""))))))) -> Primary | G28: =IF(AND(I28="",H28=""),"",CONCATENATE(H28,", ",I28)) -> Pacsi, Kaela Margarette | H28: Pacsi | I28: Kaela Margarette | J28: R | K28: Female | L28: 54A Dapiting | M28: Alapang, La Trinidad | O28: 0910-567-6442 | Q28: 42078 | R28: =IF(Q28="","",DATEDIF(Q28,TODAY(),"Y")) -> 11 | S28: Baguio City | T28: Pacsi, Randy Q. | U28: Pacsi, Maricel R. | V28: No | X28: No | AC28: Grade 4 | AD28: Don Pulas, Elementary School - Alapang | AI28: Singing | AJ28: Playing with Friends | AL28: Singing | AM28: Pacsi, Maricel | AN28: 54A Dapiting, Alapang, La Trinidad | AO28: Mother | AP28: 0910-567-6442
A29: Primary: 11-12 y/o | D29: Yes | F29: =IF($R29="","",IF($R29>=13,"Junior",IF(AND($R29>=11,$R29<=12),"Primary",IF(AND($R29>=9,$R29<=10),"Beginners 2",IF(AND($R29>=7,$R29<=8),"Beginners 1",IF(AND($R29>=5,$R29<=6),"Toddlers 2",IF(AND($R29>=3,$R29<=4),"Toddlers 1",""))))))) -> Primary | G29: =IF(AND(I29="",H29=""),"",CONCATENATE(H29,", ",I29)) -> Prado, Ezekiel Shem | H29: Prado | I29: Ezekiel Shem | J29: C | K29: Male | L29: 076 Lamug St Purok 25 | M29: Irisan | N29: Mankayan Benguet / Anda Pangasinan | O29: 0995-056-5503 | Q29: 41828 | R29: =IF(Q29="","",DATEDIF(Q29,TODAY(),"Y")) -> 12 | S29: Mankayan, Benguet | T29: Prado, Reymond G. | U29: Prado, Jeazell | V29: No | X29: No | Z29: Baptist | AC29: Grade 5 | AD29: Quezon Hill Elementary School | AG29: Near Sighted | AH29: Music Ministry, Bible Quizzing | AI29: Singing, Video Games | AJ29: Word Puzzles | AK29: Skating, Basketball | AM29: Prado, Jeazell | AN29: 076 Lamug St Purok 25, Irisan, Baguio City | AO29: Mother | AP29: 0995-056-5503
D30: Yes | F30: =IF($R30="","",IF($R30>=13,"Junior",IF(AND($R30>=11,$R30<=12),"Primary",IF(AND($R30>=9,$R30<=10),"Beginners 2",IF(AND($R30>=7,$R30<=8),"Beginners 1",IF(AND($R30>=5,$R30<=6),"Toddlers 2",IF(AND($R30>=3,$R30<=4),"Toddlers 1",""))))))) -> Primary | G30: =IF(AND(I30="",H30=""),"",CONCATENATE(H30,", ",I30)) -> Pulicay, Ceanne Marc | H30: Pulicay | I30: Ceanne Marc | J30: A | K30: Male | L30: AP 31 Sitio Paltingan | M30: Ambiong, La Trinidad | N30: Tayug, Pangasinan | O30: 0919-890-9185 | Q30: 42024 | R30: =IF(Q30="","",DATEDIF(Q30,TODAY(),"Y")) -> 11 | S30: Baguio City | T30: Pulicay, Mark Angelo | U30: Pulicay, Janice A. | V30: No | X30: No | AC30: Grade 4 | AD30: Doña Aurora Elementary School | AH30: Sunday School, Bible Quizzing | AI30: Reading, Playing Badminton | AK30: Badminton | AM30: Pulicay, Janice A. | AN30: AP 31 Sitio Paltingan, Ambiong, La Trinidad | AO30: Mother | AP30: 0919-890-9185
D31: Yes | F31: =IF($R31="","",IF($R31>=13,"Junior",IF(AND($R31>=11,$R31<=12),"Primary",IF(AND($R31>=9,$R31<=10),"Beginners 2",IF(AND($R31>=7,$R31<=8),"Beginners 1",IF(AND($R31>=5,$R31<=6),"Toddlers 2",IF(AND($R31>=3,$R31<=4),"Toddlers 1",""))))))) -> Beginners 1 | G31: =IF(AND(I31="",H31=""),"",CONCATENATE(H31,", ",I31)) -> Rivera, Princess Khina | H31: Rivera | I31: Princess Khina | K31: Female | M31: Apugan, Sto. Tomas | O31: 0954-270-4941 | Q31: 43068 | R31: =IF(Q31="","",DATEDIF(Q31,TODAY(),"Y")) -> 8 | S31: Baguio City | T31: Rivera, Jay | U31: Imbang, Aileen | V31: No | X31: No | AC31: Grade 3 | AD31: Apugan Sto. Tomas Elementary School | AH31: Prayer Network | AK31: Badminton | AL31: Singing | AM31: Rivera, Jay | AN31: Apugan, Sto. Tomas | AO31: Father | AP31: 0926-096-026
D32: Yes | F32: =IF($R32="","",IF($R32>=13,"Junior",IF(AND($R32>=11,$R32<=12),"Primary",IF(AND($R32>=9,$R32<=10),"Beginners 2",IF(AND($R32>=7,$R32<=8),"Beginners 1",IF(AND($R32>=5,$R32<=6),"Toddlers 2",IF(AND($R32>=3,$R32<=4),"Toddlers 1",""))))))) -> Primary | G32: =IF(AND(I32="",H32=""),"",CONCATENATE(H32,", ",I32)) -> Romeo, Sean Thyrinz | H32: Romeo | I32: Sean Thyrinz | J32: P | K32: Male | L32: Purok 3 | M32: Upper Mines View | Q32: 41669 | R32: =IF(Q32="","",DATEDIF(Q32,TODAY(),"Y")) -> 12 | S32: Quirino Province | T32: Romero, Jether Dan | U32: Romero, Lanie Palma | V32: No | X32: No | AC32: Grade 5 | AD32: Gibraltar Elementary School | AM32: Romero, Margie | AN32: Mines View | AO32: Grandmother | AP32: 0966-612-8459
D33: Yes | F33: =IF($R33="","",IF($R33>=13,"Junior",IF(AND($R33>=11,$R33<=12),"Primary",IF(AND($R33>=9,$R33<=10),"Beginners 2",IF(AND($R33>=7,$R33<=8),"Beginners 1",IF(AND($R33>=5,$R33<=6),"Toddlers 2",IF(AND($R33>=3,$R33<=4),"Toddlers 1",""))))))) -> Toddlers 1 | G33: =IF(AND(I33="",H33=""),"",CONCATENATE(H33,", ",I33)) -> Sayan, Leandrei Zhayne Zenkai | H33: Sayan | I33: Leandrei Zhayne Zenkai | J33: B | K33: Male | L33: L-B11 Rocky Side 1 | M33: Lubas, La Trinidad | N33: 358 Goldfield Poblacion Itogon Benguet | O33: 0998-578-5773 | Q33: 44776 | R33: =IF(Q33="","",DATEDIF(Q33,TODAY(),"Y")) -> 4 | S33: Baguio City | T33: Sayan, Scheychelles Aries | U33: Sayan, Jovelyn | V33: Yes | W33: 45165 | X33: No | AM33: Sayan, Jovelyn | AN33: L-B11 Rocky Side 1, Lubas, La Trinidad | AO33: Mother | AP33: 0998-578-5773
D34: Yes | F34: =IF($R34="","",IF($R34>=13,"Junior",IF(AND($R34>=11,$R34<=12),"Primary",IF(AND($R34>=9,$R34<=10),"Beginners 2",IF(AND($R34>=7,$R34<=8),"Beginners 1",IF(AND($R34>=5,$R34<=6),"Toddlers 2",IF(AND($R34>=3,$R34<=4),"Toddlers 1",""))))))) -> Primary | G34: =IF(AND(I34="",H34=""),"",CONCATENATE(H34,", ",I34)) -> Zapata, Khezziah Enica | H34: Zapata | I34: Khezziah Enica | K34: Female | L34: 33 | M34: Central Fairview | O34: 0999-694-0537 | P34: yengcaragay46@gmail.com | Q34: 41915 | R34: =IF(Q34="","",DATEDIF(Q34,TODAY(),"Y")) -> 12 | S34: Baguio City | T34: Zapata, Rando B. | U34: Zapata, Florencia | V34: No | X34: No | Z34: Roman Catholic | Anglican | AC34: Grade 4 | AD34: SLU | AH34: All!!! | AI34: Drawing, Painting | AJ34: Painting | AM34: Zapata, Florence | AN34: 33 Central Fairview | AO34: Mother | AP34: 0999-694-0537
F35: =IF($R35="","",IF($R35>=13,"Junior",IF(AND($R35>=11,$R35<=12),"Primary",IF(AND($R35>=9,$R35<=10),"Beginners 2",IF(AND($R35>=7,$R35<=8),"Beginners 1",IF(AND($R35>=5,$R35<=6),"Toddlers 2",IF(AND($R35>=3,$R35<=4),"Toddlers 1",""))))))) | G35: =IF(AND(I35="",H35=""),"",CONCATENATE(H35,", ",I35)) | R35: =IF(Q35="","",DATEDIF(Q35,TODAY(),"Y"))
F36: =IF($R36="","",IF($R36>=13,"Junior",IF(AND($R36>=11,$R36<=12),"Primary",IF(AND($R36>=9,$R36<=10),"Beginners 2",IF(AND($R36>=7,$R36<=8),"Beginners 1",IF(AND($R36>=5,$R36<=6),"Toddlers 2",IF(AND($R36>=3,$R36<=4),"Toddlers 1",""))))))) | G36: =IF(AND(I36="",H36=""),"",CONCATENATE(H36,", ",I36)) | R36: =IF(Q36="","",DATEDIF(Q36,TODAY(),"Y"))
F37: =IF($R37="","",IF($R37>=13,"Junior",IF(AND($R37>=11,$R37<=12),"Primary",IF(AND($R37>=9,$R37<=10),"Beginners 2",IF(AND($R37>=7,$R37<=8),"Beginners 1",IF(AND($R37>=5,$R37<=6),"Toddlers 2",IF(AND($R37>=3,$R37<=4),"Toddlers 1",""))))))) | G37: =IF(AND(I37="",H37=""),"",CONCATENATE(H37,", ",I37)) | R37: =IF(Q37="","",DATEDIF(Q37,TODAY(),"Y"))
F38: =IF($R38="","",IF($R38>=13,"Junior",IF(AND($R38>=11,$R38<=12),"Primary",IF(AND($R38>=9,$R38<=10),"Beginners 2",IF(AND($R38>=7,$R38<=8),"Beginners 1",IF(AND($R38>=5,$R38<=6),"Toddlers 2",IF(AND($R38>=3,$R38<=4),"Toddlers 1",""))))))) | G38: =IF(AND(I38="",H38=""),"",CONCATENATE(H38,", ",I38)) | R38: =IF(Q38="","",DATEDIF(Q38,TODAY(),"Y"))
F39: =IF($R39="","",IF($R39>=13,"Junior",IF(AND($R39>=11,$R39<=12),"Primary",IF(AND($R39>=9,$R39<=10),"Beginners 2",IF(AND($R39>=7,$R39<=8),"Beginners 1",IF(AND($R39>=5,$R39<=6),"Toddlers 2",IF(AND($R39>=3,$R39<=4),"Toddlers 1",""))))))) | G39: =IF(AND(I39="",H39=""),"",CONCATENATE(H39,", ",I39)) | R39: =IF(Q39="","",DATEDIF(Q39,TODAY(),"Y"))
F40: =IF($R40="","",IF($R40>=13,"Junior",IF(AND($R40>=11,$R40<=12),"Primary",IF(AND($R40>=9,$R40<=10),"Beginners 2",IF(AND($R40>=7,$R40<=8),"Beginners 1",IF(AND($R40>=5,$R40<=6),"Toddlers 2",IF(AND($R40>=3,$R40<=4),"Toddlers 1",""))))))) | G40: =IF(AND(I40="",H40=""),"",CONCATENATE(H40,", ",I40)) | R40: =IF(Q40="","",DATEDIF(Q40,TODAY(),"Y"))
F41: =IF($R41="","",IF($R41>=13,"Junior",IF(AND($R41>=11,$R41<=12),"Primary",IF(AND($R41>=9,$R41<=10),"Beginners 2",IF(AND($R41>=7,$R41<=8),"Beginners 1",IF(AND($R41>=5,$R41<=6),"Toddlers 2",IF(AND($R41>=3,$R41<=4),"Toddlers 1",""))))))) | G41: =IF(AND(I41="",H41=""),"",CONCATENATE(H41,", ",I41)) | R41: =IF(Q41="","",DATEDIF(Q41,TODAY(),"Y"))
F42: =IF($R42="","",IF($R42>=13,"Junior",IF(AND($R42>=11,$R42<=12),"Primary",IF(AND($R42>=9,$R42<=10),"Beginners 2",IF(AND($R42>=7,$R42<=8),"Beginners 1",IF(AND($R42>=5,$R42<=6),"Toddlers 2",IF(AND($R42>=3,$R42<=4),"Toddlers 1",""))))))) | G42: =IF(AND(I42="",H42=""),"",CONCATENATE(H42,", ",I42)) | R42: =IF(Q42="","",DATEDIF(Q42,TODAY(),"Y"))
F43: =IF($R43="","",IF($R43>=13,"Junior",IF(AND($R43>=11,$R43<=12),"Primary",IF(AND($R43>=9,$R43<=10),"Beginners 2",IF(AND($R43>=7,$R43<=8),"Beginners 1",IF(AND($R43>=5,$R43<=6),"Toddlers 2",IF(AND($R43>=3,$R43<=4),"Toddlers 1",""))))))) | G43: =IF(AND(I43="",H43=""),"",CONCATENATE(H43,", ",I43)) | R43: =IF(Q43="","",DATEDIF(Q43,TODAY(),"Y"))
F44: =IF($R44="","",IF($R44>=13,"Junior",IF(AND($R44>=11,$R44<=12),"Primary",IF(AND($R44>=9,$R44<=10),"Beginners 2",IF(AND($R44>=7,$R44<=8),"Beginners 1",IF(AND($R44>=5,$R44<=6),"Toddlers 2",IF(AND($R44>=3,$R44<=4),"Toddlers 1",""))))))) | G44: =IF(AND(I44="",H44=""),"",CONCATENATE(H44,", ",I44)) | R44: =IF(Q44="","",DATEDIF(Q44,TODAY(),"Y"))
F45: =IF($R45="","",IF($R45>=13,"Junior",IF(AND($R45>=11,$R45<=12),"Primary",IF(AND($R45>=9,$R45<=10),"Beginners 2",IF(AND($R45>=7,$R45<=8),"Beginners 1",IF(AND($R45>=5,$R45<=6),"Toddlers 2",IF(AND($R45>=3,$R45<=4),"Toddlers 1",""))))))) | G45: =IF(AND(I45="",H45=""),"",CONCATENATE(H45,", ",I45)) | R45: =IF(Q45="","",DATEDIF(Q45,TODAY(),"Y"))
F46: =IF($R46="","",IF($R46>=13,"Junior",IF(AND($R46>=11,$R46<=12),"Primary",IF(AND($R46>=9,$R46<=10),"Beginners 2",IF(AND($R46>=7,$R46<=8),"Beginners 1",IF(AND($R46>=5,$R46<=6),"Toddlers 2",IF(AND($R46>=3,$R46<=4),"Toddlers 1",""))))))) | G46: =IF(AND(I46="",H46=""),"",CONCATENATE(H46,", ",I46)) | R46: =IF(Q46="","",DATEDIF(Q46,TODAY(),"Y"))
... F201: =IF($R201="","",IF($R201>=13,"Junior",IF(AND($R201>=11,$R201<=12),"Primary",IF(AND($R201>=9,$R201<=10),"Beginners 2",IF(AND($R201>=7,$R201<=8),"Beginners 1",IF(AND($R201>=5,$R201<=6),"Toddlers 2",IF(AND($R201>=3,$R201<=4),"Toddlers 1",""))))))) | G201: =IF(AND(I201="",H201=""),"",CONCATENATE(H201,", ",I201)) | R201: =IF(Q201="","",DATEDIF(Q201,TODAY(),"Y"))

Sheet All Attendance
A1: 0
A2: 0 | C2: CALVARY TABERNACLE CHURCH
A3: 0 | C3: SUNDAY ATTENDANCE
A4: 0
A5: 0 | B5: Type capital "P" for PRESENT | E5: 2026
A6: 0 | E6: JULY | I6: AUGUST | M6: SEPTEMBER | Q6: OCTOBER | U6: NOVEMBER | Z6: DECEMEBER
A7: 0
A8: 0 | B8: FAMILY | C8: DEPARTMENT | D8: NAME | E8: 5 | F8: 12 | G8: 19 | H8: 26 | I8: 2 | J8: 9 | K8: 16 | L8: 23 | M8: 30 | N8: 6 | O8: 13 | P8: 20 | Q8: 27 | R8: 4 | S8: 11 | T8: 18 | U8: 25 | V8: 1 | W8: 8 | X8: 15 | Y8: 22 | Z8: 29 | AA8: 6 | AB8: 13 | AC8: 20 | AD8: 27 | AE8: TOTAL
A9: 0.1 | D9: NUMBER OF ATTENDANCE | E9: =COUNTIF(E10:E703,"TRUE") -> 360 | F9: =COUNTIF(F10:F703,"TRUE") -> 311 | G9: =COUNTIF(G11:G689,"TRUE") -> 400 | H9: =COUNTIF(H11:H659,"TRUE") -> 321
A10: 0.11 | B10: Column1 | C10: Column2 | D10: Column3 | E10: Column4 | F10: Column5 | G10: Column6 | H10: Column7 | I10: Column8 | J10: Column9 | K10: Column10 | L10: Column11 | M10: Column12 | N10: Column13 | O10: Column14 | P10: Column15 | Q10: Column16 | R10: Column17 | S10: Column18 | T10: Column19 | U10: Column20 | V10: Column21 | W10: Column22 | X10: Column23 | Y10: Column24 | Z10: Column25 | AA10: Column26 | AB10: Column27 | AC10: Column28 | AD10: Column29 | AE10: Column30
A11: 1 | C11: LM | D11: Abad, Joan | E11: FALSE | F11: FALSE | G11: TRUE | H11: FALSE | AE11: =COUNTIF(E11:AD11,"TRUE") -> 1
A12: 2 | D12: Abenez, Stephanie | E12: TRUE | F12: TRUE | G12: TRUE | H12: TRUE | AE12: =COUNTIF(E12:AD12,"TRUE") -> 4
A13: 3 | B13: Abuan 2 | C13: LM | D13: Abuan, Christine | E13: TRUE | F13: TRUE | G13: TRUE | H13: TRUE | AE13: =COUNTIF(E13:AD13,"TRUE") -> 4
A14: 4 | B14: Abuan 2 | C14: AMM | D14: Abuan, Jomar | E14: TRUE | F14: TRUE | G14: TRUE | H14: TRUE | AE14: =COUNTIF(E14:AD14,"TRUE") -> 4
A15: 5 | B15: Abuan 1 | C15: LM | D15: Abuan, Maria Fe | E15: TRUE | F15: TRUE | G15: TRUE | H15: TRUE | AE15: =COUNTIF(E15:AD15,"TRUE") -> 4
A16: 6 | B16: Abuan 1 | C16: AMM | D16: Abuan, Ricardo | E16: TRUE | F16: TRUE | G16: TRUE | H16: TRUE | AE16: =COUNTIF(E16:AD16,"TRUE") -> 4
A17: 7 | C17: LM | D17: Adame, Esther | E17: TRUE | F17: FALSE | G17: TRUE | H17: TRUE | AE17: =COUNTIF(E17:AD17,"TRUE") -> 3
A18: 9 | B18: Agpalo | C18: YM | D18: Agpalo, Charles | E18: FALSE | F18: FALSE | G18: FALSE | H18: FALSE | AE18: =COUNTIF(E18:AD18,"TRUE") -> 0
A19: 10 | B19: Aguinaldo | C19: CM | D19: Aguinaldo, Raiven Ezekel | E19: FALSE | F19: FALSE | G19: FALSE | H19: FALSE | AE19: =COUNTIF(E19:AD19,"TRUE") -> 0
A20: 11 | B20: Aguinaldo | C20: CM | D20: Aguinaldo, Raveena Scarlet | E20: FALSE | F20: FALSE | G20: FALSE | H20: FALSE | AE20: =COUNTIF(E20:AD20,"TRUE") -> 0
A21: 12 | B21: Akiapat 1 | C21: LM | D21: Akiapat, Felipa | E21: TRUE | F21: TRUE | G21: TRUE | H21: FALSE | AE21: =COUNTIF(E21:AD21,"TRUE") -> 3
A22: 13 | C22: YM | D22: Akiapat, Femy | E22: TRUE | F22: FALSE | G22: TRUE | H22: FALSE | AE22: =COUNTIF(E22:AD22,"TRUE") -> 2
A23: 14 | B23: Alarcio 2 | D23: Alarcio, Adrian | E23: TRUE | F23: TRUE | G23: TRUE | H23: TRUE | AE23: =COUNTIF(E23:AD23,"TRUE") -> 4
A24: 16 | B24: Alarcio 1 | C24: LM | D24: Alarcio, Grace | E24: TRUE | F24: TRUE | G24: TRUE | H24: TRUE | AE24: =COUNTIF(E24:AD24,"TRUE") -> 4
A25: 17 | B25: Alarcio 2 | C25: LM | D25: Alarcio, Kaye Cee | E25: TRUE | F25: TRUE | G25: TRUE | H25: TRUE | AE25: =COUNTIF(E25:AD25,"TRUE") -> 4
A26: 18 | B26: Alarcio 1 | C26: AMM | D26: Alarcio, Marcial | E26: TRUE | F26: TRUE | G26: TRUE | H26: TRUE | AE26: =COUNTIF(E26:AD26,"TRUE") -> 4
A27: 19 | B27: Albing 1 | C27: YM | D27: Albing, Alpha May | E27: TRUE | F27: TRUE | G27: TRUE | H27: TRUE | AE27: =COUNTIF(E27:AD27,"TRUE") -> 4
A28: 20 | B28: Albing 1 | C28: YM | D28: Albing, Amela Grace | E28: TRUE | F28: TRUE | G28: TRUE | H28: TRUE | AE28: =COUNTIF(E28:AD28,"TRUE") -> 4
A29: 21 | B29: Albing 1 | C29: YM | D29: Albing, John Lee | E29: FALSE | F29: FALSE | G29: TRUE | H29: FALSE | AE29: =COUNTIF(E29:AD29,"TRUE") -> 1
A30: 22 | C30: YM | D30: Alcantara, Axel | E30: FALSE | F30: FALSE | G30: FALSE | H30: FALSE | AE30: =COUNTIF(E30:AD30,"TRUE") -> 0
A31: 23 | C31: YM | D31: Alcoriza, Clarisse | E31: FALSE | F31: FALSE | G31: FALSE | H31: FALSE | AE31: =COUNTIF(E31:AD31,"TRUE") -> 0
A32: 626 | B32: Alcoriza 1 | C32: LM | D32: Alcoriza, Jocelyn | E32: TRUE | F32: TRUE | G32: TRUE | H32: FALSE | AE32: =COUNTIF(E32:AD32,"TRUE") -> 3
A33: 24 | B33: Alcoriza 2 | C33: YM | D33: Alcoriza, Renalyn | E33: FALSE | F33: FALSE | G33: FALSE | H33: TRUE | AE33: =COUNTIF(E33:AD33,"TRUE") -> 1
A34: 25 | B34: Alcoriza 1 | C34: AMM | D34: Alcoriza, Reynaldo | E34: TRUE | F34: TRUE | G34: TRUE | H34: TRUE | AE34: =COUNTIF(E34:AD34,"TRUE") -> 4
A35: 26 | B35: Aleo 1 | C35: LM | D35: Aleo, Nena | E35: FALSE | F35: TRUE | G35: TRUE | H35: TRUE | AE35: =COUNTIF(E35:AD35,"TRUE") -> 3
A36: 27 | B36: BEAM | D36: Alfonso, Abia | E36: FALSE | F36: FALSE | G36: TRUE | H36: FALSE | AE36: =COUNTIF(E36:AD36,"TRUE") -> 1
A37: 28 | C37: AMM | D37: Alfornon, Bobby | E37: FALSE | F37: FALSE | G37: FALSE | H37: TRUE | AE37: =COUNTIF(E37:AD37,"TRUE") -> 1
A38: 29 | B38: Alister | C38: YM | D38: Alister, Jun | E38: FALSE | F38: FALSE | G38: FALSE | H38: FALSE | AE38: =COUNTIF(E38:AD38,"TRUE") -> 0
A39: 31 | B39: Amistad 3 | C39: CM | D39: Amistad, Elisha | E39: TRUE | F39: TRUE | G39: TRUE | H39: TRUE | AE39: =COUNTIF(E39:AD39,"TRUE") -> 4
A40: 32 | B40: Amistad 2 | C40: LM | D40: Amistad, Hadassah Olive | E40: FALSE | F40: FALSE | G40: FALSE | H40: FALSE | AE40: =COUNTIF(E40:AD40,"TRUE") -> 0
A41: 33 | B41: Amistad 2 | C41: AMM | D41: Amistad, Joseph Sinesin | E41: TRUE | F41: TRUE | G41: TRUE | H41: TRUE | AE41: =COUNTIF(E41:AD41,"TRUE") -> 4
A42: 34 | B42: Amistad 3 | C42: CM | D42: Amistad, Judah | E42: FALSE | F42: FALSE | G42: FALSE | H42: FALSE | AE42: =COUNTIF(E42:AD42,"TRUE") -> 0
A43: 38 | B43: Amistad 3 | C43: CM | D43: Amistad, Lucas | E43: TRUE | F43: TRUE | G43: TRUE | H43: TRUE | AE43: =COUNTIF(E43:AD43,"TRUE") -> 4
A44: 39 | B44: Amplogio 1 | C44: AMM | D44: Amplogio, Charlie | E44: TRUE | F44: FALSE | G44: FALSE | H44: FALSE | AE44: =COUNTIF(E44:AD44,"TRUE") -> 1
A45: 40 | B45: Amplogio 1 | C45: LM | D45: Amplogio, Gina | E45: TRUE | F45: TRUE | G45: TRUE | H45: TRUE | AE45: =COUNTIF(E45:AD45,"TRUE") -> 4
A46: 41 | B46: Amplogio 2 | C46: YM | D46: Amplogio, Harvey | E46: TRUE | F46: TRUE | G46: TRUE | H46: FALSE | AE46: =COUNTIF(E46:AD46,"TRUE") -> 3
A47: 42 | B47: Amplogio 2 | C47: YM | D47: Amplogio, Zhoilo | E47: TRUE | F47: FALSE | G47: TRUE | H47: FALSE | AE47: =COUNTIF(E47:AD47,"TRUE") -> 2
A48: 43 | B48: Andrada | C48: LM | D48: Andrada, Lolita | E48: FALSE | F48: FALSE | G48: FALSE | H48: FALSE | AE48: =COUNTIF(E48:AD48,"TRUE") -> 0
A49: 44 | B49: Ano 1 | C49: LM | D49: Ano, Emiliana | E49: TRUE | F49: TRUE | G49: TRUE | H49: TRUE | AE49: =COUNTIF(E49:AD49,"TRUE") -> 4
A50: 45 | D50: Anonuevo, Jun | E50: TRUE | F50: FALSE | G50: FALSE | H50: FALSE
A51: 46 | C51: YM | D51: Antonio, Arjelyn | E51: FALSE | F51: FALSE | G51: TRUE | H51: FALSE
A52: 48 | B52: Antonio 2 | C52: YM | D52: Antonio, Froxh Zion | E52: FALSE | F52: FALSE | G52: FALSE | H52: FALSE | AE52: =COUNTIF(E52:AD52,"TRUE") -> 0
A53: 49 | C53: CM | D53: Antonio, Isen | E53: FALSE | F53: TRUE | G53: FALSE | H53: FALSE
A54: 50 | C54: LM | D54: Antonio, Jolie Mae | E54: FALSE | F54: FALSE | G54: FALSE | H54: FALSE | AE54: =COUNTIF(E54:AD54,"TRUE") -> 0
A55: 51 | B55: Apilada 2 | C55: YM | D55: Apilada, Arbie | E55: FALSE | F55: FALSE | G55: FALSE | H55: TRUE | AE55: =COUNTIF(E55:AD55,"TRUE") -> 1
A56: 52 | B56: Apilada 2 | C56: YM | D56: Apilada, Arman Angelo | E56: FALSE | F56: TRUE | G56: TRUE | H56: TRUE | AE56: =COUNTIF(E56:AD56,"TRUE") -> 3
A57: 53 | B57: Apilada 1 | C57: AMM | D57: Apilada, Armando | E57: FALSE | F57: TRUE | G57: TRUE | H57: TRUE | AE57: =COUNTIF(E57:AD57,"TRUE") -> 3
A58: 54 | B58: Apilada 3 | C58: YM | D58: Apilada, Jairah May | E58: FALSE | F58: FALSE | G58: TRUE | H58: TRUE | AE58: =COUNTIF(E58:AD58,"TRUE") -> 2
A59: 55 | B59: Apilada 1 | C59: LM | D59: Apilada, Susan | E59: FALSE | F59: FALSE | G59: TRUE | H59: TRUE | AE59: =COUNTIF(E59:AD59,"TRUE") -> 2
A60: 56 | B60: Apolinario | C60: YM | D60: Apolinario, Troy Kenneth | E60: FALSE | F60: FALSE | G60: FALSE | H60: FALSE | AE60: =COUNTIF(E60:AD60,"TRUE") -> 0
A61: 57 | D61: Aquino, Lyra | E61: FALSE | F61: TRUE | G61: FALSE | H61: FALSE | AE61: =COUNTIF(E61:AD61,"TRUE") -> 1
A62: 58 | B62: Aragon 1 | C62: LM | D62: Aragon, Elaine Marie | E62: TRUE | F62: TRUE | G62: TRUE | H62: FALSE | AE62: =COUNTIF(E62:AD62,"TRUE") -> 3
A63: 59 | B63: Aragon 1 | C63: AMM | D63: Aragon, Marc Andrew Reli | E63: TRUE | F63: TRUE | G63: TRUE | H63: TRUE | AE63: =COUNTIF(E63:AD63,"TRUE") -> 4
A64: 60 | B64: Aragon 2 | C64: CM | D64: Aragon, Reviel Arcai | E64: TRUE | F64: TRUE | G64: TRUE | H64: FALSE | AE64: =COUNTIF(E64:AD64,"TRUE") -> 3
A65: 61 | B65: Arcangel | C65: LM | D65: Arcangel, Delia | E65: TRUE | F65: FALSE | G65: FALSE | H65: FALSE | AE65: =COUNTIF(E65:AD65,"TRUE") -> 1
A66: 63 | B66: Ating 1 | C66: AMM | D66: Ating, Dwight Paul | E66: FALSE | F66: FALSE | G66: TRUE | H66: TRUE | AE66: =COUNTIF(E66:AD66,"TRUE") -> 2
A67: 64 | C67: LM | D67: Ating, Grace | E67: FALSE | F67: FALSE | G67: FALSE | H67: TRUE
A68: 66 | D68: Augustin, Aprilyn | E68: FALSE | F68: FALSE | G68: TRUE | H68: FALSE
A69: 67 | C69: YM | D69: Augusto, Guillian | E69: TRUE | F69: TRUE | G69: FALSE | H69: TRUE | AE69: =COUNTIF(E69:AD69,"TRUE") -> 3
A70: 68 | C70: LM | D70: Ayson, Cora | E70: FALSE | F70: FALSE | G70: FALSE | H70: FALSE | AE70: =COUNTIF(E70:AD70,"TRUE") -> 0
A71: 69 | B71: Ayungo 1 | C71: LM | D71: Ayungo, Ailene | E71: TRUE | F71: FALSE | G71: TRUE | H71: TRUE | AE71: =COUNTIF(E71:AD71,"TRUE") -> 3
A72: 70 | B72: Ayungo 2 | C72: YM | D72: Ayungo, Martin Aileslee III | E72: FALSE | F72: FALSE | G72: FALSE | H72: TRUE | AE72: =COUNTIF(E72:AD72,"TRUE") -> 1
A73: 72 | B73: Ayungo 1 | C73: AMM | D73: Ayungo, Martin Jr | E73: TRUE | F73: FALSE | G73: TRUE | H73: FALSE | AE73: =COUNTIF(E73:AD73,"TRUE") -> 2
A74: 73 | B74: Azores 1 | C74: AMM | D74: Azores, Ronald | E74: TRUE | F74: TRUE | G74: TRUE | H74: FALSE | AE74: =COUNTIF(E74:AD74,"TRUE") -> 3
A75: 74 | D75: Bac-a-ao, Kil | E75: FALSE | F75: TRUE | G75: FALSE | H75: FALSE | AE75: =COUNTIF(E75:AD75,"TRUE") -> 1
A76: 77 | B76: Bacsa 1 | C76: LM | D76: Bacsa, Hyneth Gwenn | E76: FALSE | F76: FALSE | G76: TRUE | H76: FALSE | AE76: =COUNTIF(E76:AD76,"TRUE") -> 1
A77: 81 | B77: Bacsa 1 | C77: AMM | D77: Bacsa, Vhal | E77: FALSE | F77: TRUE | G77: TRUE | H77: FALSE | AE77: =COUNTIF(E77:AD77,"TRUE") -> 2
A78: 82 | C78: CM | D78: Badilla , Vienna Brylle | E78: FALSE | F78: FALSE | G78: FALSE | H78: TRUE
A79: 83 | B79: Bacsa | C79: CM | D79: Badilla, Xyrelle Vhien | E79: TRUE | F79: FALSE | G79: TRUE | H79: FALSE | AE79: =COUNTIF(E79:AD79,"TRUE") -> 2
A80: 84 | B80: Balbino | C80: LM | D80: Balbino, Beverly | E80: FALSE | F80: FALSE | G80: FALSE | H80: TRUE | AE80: =COUNTIF(E80:AD80,"TRUE") -> 1
A81: 85 | B81: Baldoz | C81: YM | D81: Baldoz, King Stevenlee | E81: FALSE | F81: FALSE | G81: FALSE | H81: FALSE | AE81: =COUNTIF(E81:AD81,"TRUE") -> 0
A82: 86 | B82: Balinggan 4 | C82: LM | D82: Balinggan, Deborah | E82: FALSE | F82: TRUE | G82: FALSE | H82: TRUE | AE82: =COUNTIF(E82:AD82,"TRUE") -> 2
A83: 87 | B83: Balinggan 3 | C83: YM | D83: Balinggan, Gabrielle Troi | E83: FALSE | F83: FALSE | G83: FALSE | H83: FALSE | AE83: =COUNTIF(E83:AD83,"TRUE") -> 0
A84: 88 | B84: Balinggan 3 | C84: LM | D84: Balinggan, Gene | E84: TRUE | F84: TRUE | G84: FALSE | H84: TRUE | AE84: =COUNTIF(E84:AD84,"TRUE") -> 3
A85: 89 | B85: Balinggan 3 | C85: YM | D85: Balinggan, Jadden Tredway | E85: TRUE | F85: TRUE | G85: TRUE | H85: TRUE | AE85: =COUNTIF(E85:AD85,"TRUE") -> 4
A86: 90 | B86: Balinggan 2 | C86: LM | D86: Balinggan, Jubilee | E86: TRUE | F86: TRUE | G86: TRUE | H86: TRUE | AE86: =COUNTIF(E86:AD86,"TRUE") -> 4
A87: 91 | B87: Balinggan 2 | C87: AMM | D87: Balinggan, Jurickson | E87: TRUE | F87: TRUE | G87: TRUE | H87: TRUE | AE87: =COUNTIF(E87:AD87,"TRUE") -> 4
A88: 92 | B88: Balinggan 1 | C88: LM | D88: Balinggan, Mercedes | E88: TRUE | F88: TRUE | G88: TRUE | H88: TRUE | AE88: =COUNTIF(E88:AD88,"TRUE") -> 4
A89: 93 | B89: Balinggan 1 | C89: AMM | D89: Balinggan, Paul | E89: TRUE | F89: TRUE | G89: TRUE | H89: TRUE | AE89: =COUNTIF(E89:AD89,"TRUE") -> 4
A90: 94 | B90: Balinggan 2 | C90: CM | D90: Balinggan, Zuri | E90: TRUE | F90: TRUE | G90: TRUE | H90: TRUE | AE90: =COUNTIF(E90:AD90,"TRUE") -> 4
... A97: 102 | B97: Banaag | C97: YM | D97: Banaag, Aldgeryne Faith | E97: TRUE | F97: TRUE | G97: TRUE | H97: TRUE | AE97: =COUNTIF(E97:AD97,"TRUE") -> 4
A98: 103 | B98: BEAM | D98: Banaag, Daniel | E98: FALSE | F98: FALSE | G98: TRUE | H98: FALSE | AE98: =COUNTIF(E98:AD98,"TRUE") -> 1
A99: 104 | B99: Banaag | C99: AMM | D99: Banaag, Gerald | E99: TRUE | F99: TRUE | G99: TRUE | H99: FALSE | AE99: =COUNTIF(E99:AD99,"TRUE") -> 3
A100: 105 | B100: Banaag | C100: YM | D100: Banaag, Geraldine Marijoe | E100: FALSE | F100: TRUE | G100: TRUE | H100: TRUE | AE100: =COUNTIF(E100:AD100,"TRUE") -> 3
A101: 106 | B101: Banaag | C101: LM | D101: Banaag, Marjorie | E101: TRUE | F101: TRUE | G101: TRUE | H101: TRUE | AE101: =COUNTIF(E101:AD101,"TRUE") -> 4
A102: 108 | C102: CM | D102: Banaag, Zechariah | E102: TRUE | F102: FALSE | G102: FALSE | H102: FALSE
A103: 624 | C103: LM | D103: Bañares, Alicia Hafalla | E103: TRUE | F103: FALSE | G103: FALSE | H103: FALSE | AE103: =COUNTIF(E103:AD103,"TRUE") -> 1
A104: 109 | C104: AMM | D104: Bañez, Eugene | E104: TRUE | F104: TRUE | G104: FALSE | H104: TRUE | AE104: =COUNTIF(E104:AD104,"TRUE") -> 3
A105: 111 | C105: YM | D105: Bañez, Journey Ryan | E105: TRUE | F105: TRUE | G105: TRUE | H105: TRUE | AE105: =COUNTIF(E105:AD105,"TRUE") -> 4
A106: 112 | C106: LM | D106: Bañez, Lucina | E106: TRUE | F106: TRUE | G106: TRUE | H106: TRUE | AE106: =COUNTIF(E106:AD106,"TRUE") -> 4
...

Sheet VA-H300
B2: CALVARY TABERNACLE CHURCH | AF2: CLICK + TO UNHIDE
B3: VISITORS ATTENDANCE | HARVEST 300
A5: Type capital "P" for PRESENT | AG5: 2026
AG6: JULY | AK6: AUGUST | AO6: SEPTEMBER | AS6: OCTOBER | AW6: NOVEMBER | BB6: DECEMEBER
A7: Count per filter (FN) | B7: =SUBTOTAL(3,'VA-H300'!$H$8:$H$352) -> 28 | D7: # | E7: DATE ATTENDED | F7: DEPT | G7: LAST NAME | H7: FIRST NAME | I7: MIDDLE INITIAL | J7: Full Name (Last, First) | K7: GENDER | L7: STREET | M7: CITY ADDRESS | N7: PROVINCIAL ADDRESS | O7: CONTACT NUMBER | P7: EMAIL | Q7: BIRTHDATE | R7: AGE | S7: BIRTHPLACE | T7: FATHER | U7: MOTHER | V7: GUEST OF (LAST, FIRST) | W7: INTERESTED IN BIBLE STUDY? | X7: AVAILABLE DAY/S | Y7: AVAILABLE TIME | Z7: START DATE | AA7: ASSIGNED BIBLE STUDY TO | AB7: CONTACT PERSON | AC7: ADDRESS | AD7: RELATIONSHIP | AE7: CONTACT NUMBER2 | AF7: Column1 | AG7: 5 | AH7: 12 | AI7: 19 | AJ7: 26 | AK7: 2 | AL7: 9 | AM7: 16 | AN7: 23 | AO7: 30 | AP7: 6 | AQ7: 13 | AR7: 20 | AS7: 27 | AT7: 4 | AU7: 11 | AV7: 18 | AW7: 25 | AX7: 1 | AY7: 8 | AZ7: 15 | BA7: 22 | BB7: 29 | BC7: 62 | BD7: 133 | BE7: 204 | BF7: 275 | BG7: TOTAL
J8: =IF(AND(H8="",G8=""),"",CONCATENATE(G8,", ",H8)) | R8: =IF(Q8="","",DATEDIF(Q8,TODAY(),"Y"))
J9: =IF(AND(H9="",G9=""),"",CONCATENATE(G9,", ",H9)) | R9: =IF(Q9="","",DATEDIF(Q9,TODAY(),"Y"))
D10: 1 | E10: 46208 | F10: Youth | G10: Lopez | H10: Natalie | J10: =IF(AND(H10="",G10=""),"",CONCATENATE(G10,", ",H10)) -> Lopez, Natalie | K10: Female | L10: Naguilian Road | M10: Quezon Hill | O10: 0994-351-5833 | V10: Beninsig, Shane | AG10: TRUE | AH10: FALSE | AI10: FALSE | AJ10: FALSE | BG10: =COUNTIF(AG10:BF10,"P") -> 0
D11: 2 | E11: 46208 | G11: Martillana | H11: Harold | J11: =IF(AND(H11="",G11=""),"",CONCATENATE(G11,", ",H11)) -> Martillana, Harold | K11: Male | L11: Purok 5 | M11: Gibraltar | O11: 0912-086-0306 | R11: =IF(Q11="","",DATEDIF(Q11,TODAY(),"Y")) | V11: Leonardo, Maria | AG11: TRUE | AH11: FALSE | AI11: FALSE | AJ11: FALSE | BG11: =COUNTIF(AG11:BF11,"P") -> 0
D12: 3 | E12: 46208 | F12: LM | G12: Lopez | H12: Maureen | J12: =IF(AND(H12="",G12=""),"",CONCATENATE(G12,", ",H12)) -> Lopez, Maureen | K12: Female | L12: Naguilian Road | M12: Quezon Hill | O12: 0994-351-5833 | R12: =IF(Q12="","",DATEDIF(Q12,TODAY(),"Y")) | V12: Beninsig, Shane | AG12: TRUE | AH12: FALSE | AI12: FALSE | AJ12: FALSE | BG12: =COUNTIF(AG12:BF12,"P") -> 0
D13: 4 | E13: 46208 | F13: AMM | G13: Lopez | H13: Rolly | J13: =IF(AND(H13="",G13=""),"",CONCATENATE(G13,", ",H13)) -> Lopez, Rolly | L13: Naguilian Road | M13: Quezon Hill | O13: 0991-896-9611 | R13: =IF(Q13="","",DATEDIF(Q13,TODAY(),"Y")) | V13: Beninsig, Shane | AG13: TRUE | AH13: FALSE | AI13: FALSE | AJ13: FALSE | BG13: =COUNTIF(AG13:BF13,"P") -> 0
D14: 5 | E14: 46208 | F14: AMM | G14: Eraldo | H14: Federico Jr. | I14: T | J14: =IF(AND(H14="",G14=""),"",CONCATENATE(G14,", ",H14)) -> Eraldo, Federico Jr. | L14: Purok 5 Amparo Heights | M14: Camp 7 | O14: 0955-751-4955 | R14: =IF(Q14="","",DATEDIF(Q14,TODAY(),"Y")) | V14: UPC Tandang Sora | AG14: TRUE | AH14: FALSE | AI14: FALSE | AJ14: FALSE | BG14: =COUNTIF(AG14:BF14,"P") -> 0
D15: 6 | E15: 46215 | F15: Youth | G15: Cabubas | H15: Alma | I15: G | J15: =IF(AND(H15="",G15=""),"",CONCATENATE(G15,", ",H15)) -> Cabubas, Alma | K15: Female | O15: 0915-085-0587 | R15: 34 | AG15: FALSE | AH15: TRUE | AI15: FALSE | AJ15: FALSE | BG15: =COUNTIF(AG15:BF15,"P") -> 0
D16: 7 | E16: 46215 | F16: Youth | G16: Anonuevo | H16: Jun | J16: =IF(AND(H16="",G16=""),"",CONCATENATE(G16,", ",H16)) -> Anonuevo, Jun | K16: Male | R16: =IF(Q16="","",DATEDIF(Q16,TODAY(),"Y")) | V16: Ptr. Aldrin Martinez | AG16: FALSE | AH16: TRUE | AI16: FALSE | AJ16: FALSE | BG16: =COUNTIF(AG16:BF16,"P") -> 0
D17: 8 | E17: 46215 | F17: Youth | G17: Magamao | H17: Jingle | J17: =IF(AND(H17="",G17=""),"",CONCATENATE(G17,", ",H17)) -> Magamao, Jingle | K17: Female | R17: 26 | V17: Guma-ad, Shyrin Nicole | AG17: FALSE | AH17: TRUE | AI17: FALSE | AJ17: FALSE | BG17: =COUNTIF(AG17:BF17,"P") -> 0
D18: 9 | E18: 46215 | F18: Youth | G18: Galimba | H18: Jordan | J18: =IF(AND(H18="",G18=""),"",CONCATENATE(G18,", ",H18)) -> Galimba, Jordan | K18: Male | R18: =IF(Q18="","",DATEDIF(Q18,TODAY(),"Y")) | V18: UPC San Jose City | AG18: FALSE | AH18: TRUE | AI18: FALSE | AJ18: FALSE | BG18: =COUNTIF(AG18:BF18,"P") -> 0
D19: 10 | E19: 46222 | F19: LM | G19: Eraldo | H19: Jenelyn | J19: =IF(AND(H19="",G19=""),"",CONCATENATE(G19,", ",H19)) -> Eraldo, Jenelyn | K19: Female | O19: 0908-253-8454 | R19: 59 | V19: Eraldo, Federico Jr. | AG19: FALSE | AH19: FALSE | AI19: TRUE | AJ19: FALSE | BG19: =COUNTIF(AG19:BF19,"P") -> 0
D20: 11 | E20: 46222 | F20: Youth | G20: Eraldo | H20: Irish | J20: =IF(AND(H20="",G20=""),"",CONCATENATE(G20,", ",H20)) -> Eraldo, Irish | K20: Female | O20: 0908-253-8454 | R20: 40 | V20: Eraldo, Federico Jr. | AG20: FALSE | AH20: FALSE | AI20: TRUE | AJ20: FALSE | BG20: =COUNTIF(AG20:BF20,"P") -> 0
D21: 12 | E21: 46222 | F21: Youth | G21: Bentod | H21: Kharen | I21: W | J21: =IF(AND(H21="",G21=""),"",CONCATENATE(G21,", ",H21)) -> Bentod, Kharen | K21: Female | O21: 0948-390-4606 | R21: 18 | V21: Marticio, Edna W. | AG21: FALSE | AH21: FALSE | AI21: TRUE | AJ21: FALSE | BG21: =COUNTIF(AG21:BF21,"P") -> 0
D22: 13 | E22: 46222 | F22: LM | G22: Maglalang | H22: Marilyn | J22: =IF(AND(H22="",G22=""),"",CONCATENATE(G22,", ",H22)) -> Maglalang, Marilyn | K22: Female | R22: 49 | V22: FB Page / Walk In | AG22: FALSE | AH22: FALSE | AI22: TRUE | AJ22: FALSE | BG22: =COUNTIF(AG22:BF22,"P") -> 0
D23: 14 | E23: 46222 | F23: Youth | G23: Maglalang | H23: Shalom Jed | J23: =IF(AND(H23="",G23=""),"",CONCATENATE(G23,", ",H23)) -> Maglalang, Shalom Jed | K23: Male | R23: =IF(Q23="","",DATEDIF(Q23,TODAY(),"Y")) | V23: FB Page / Walk In | AG23: FALSE | AH23: FALSE | AI23: TRUE | AJ23: FALSE | BG23: =COUNTIF(AG23:BF23,"P") -> 0
D24: 15 | E24: 46222 | F24: Youth | G24: Antonio | H24: Arjelyn | J24: =IF(AND(H24="",G24=""),"",CONCATENATE(G24,", ",H24)) -> Antonio, Arjelyn | K24: Female | O24: 0907-605-3934 | R24: 24 | V24: UPC Gerona Tarlac | AG24: FALSE | AH24: FALSE | AI24: TRUE | AJ24: FALSE | BG24: =COUNTIF(AG24:BF24,"P") -> 0
D25: 16 | E25: 46222 | G25: Augustin | H25: Aprilin | J25: =IF(AND(H25="",G25=""),"",CONCATENATE(G25,", ",H25)) -> Augustin, Aprilin | K25: Female | R25: =IF(Q25="","",DATEDIF(Q25,TODAY(),"Y")) | AG25: FALSE | AH25: FALSE | AI25: TRUE | AJ25: FALSE | BG25: =COUNTIF(AG25:BF25,"P") -> 0
D26: 17 | E26: 46222 | G26: Ocampo | H26: Aileene | J26: =IF(AND(H26="",G26=""),"",CONCATENATE(G26,", ",H26)) -> Ocampo, Aileene | K26: Female | R26: =IF(Q26="","",DATEDIF(Q26,TODAY(),"Y")) | V26: Ptr. Roger Capili | AG26: FALSE | AH26: FALSE | AI26: TRUE | AJ26: FALSE | BG26: =COUNTIF(AG26:BF26,"P") -> 0
D27: 18 | E27: 46222 | G27: Ocampo | H27: Duchess Hannah | J27: =IF(AND(H27="",G27=""),"",CONCATENATE(G27,", ",H27)) -> Ocampo, Duchess Hannah | K27: Female | R27: =IF(Q27="","",DATEDIF(Q27,TODAY(),"Y")) | V27: Ptr. Roger Capili | AG27: FALSE | AH27: FALSE | AI27: TRUE | AJ27: FALSE | BG27: =COUNTIF(AG27:BF27,"P") -> 0
D28: 19 | E28: 46222 | G28: Buan | H28: Abigail | J28: =IF(AND(H28="",G28=""),"",CONCATENATE(G28,", ",H28)) -> Buan, Abigail | K28: Female | R28: =IF(Q28="","",DATEDIF(Q28,TODAY(),"Y")) | V28: Ptr. Roger Capili | AG28: FALSE | AH28: FALSE | AI28: TRUE | AJ28: FALSE | BG28: =COUNTIF(AG28:BF28,"P") -> 0
D29: 20 | E29: 46222 | G29: Buan | H29: Samantha Joseph | J29: =IF(AND(H29="",G29=""),"",CONCATENATE(G29,", ",H29)) -> Buan, Samantha Joseph | K29: Female | R29: =IF(Q29="","",DATEDIF(Q29,TODAY(),"Y")) | V29: Ptr. Roger Capili | AG29: FALSE | AH29: FALSE | AI29: TRUE | AJ29: FALSE | BG29: =COUNTIF(AG29:BF29,"P") -> 0
D30: 21 | E30: 46222 | G30: Ladrido | H30: Ruth | J30: =IF(AND(H30="",G30=""),"",CONCATENATE(G30,", ",H30)) -> Ladrido, Ruth | K30: Female | R30: =IF(Q30="","",DATEDIF(Q30,TODAY(),"Y")) | V30: Ptr. Roger Capili | AG30: FALSE | AH30: FALSE | AI30: TRUE | AJ30: FALSE | BG30: =COUNTIF(AG30:BF30,"P") -> 0
D31: 22 | E31: 46222 | G31: Ladrido | H31: Austin Raphael | J31: =IF(AND(H31="",G31=""),"",CONCATENATE(G31,", ",H31)) -> Ladrido, Austin Raphael | K31: Male | R31: =IF(Q31="","",DATEDIF(Q31,TODAY(),"Y")) | V31: Ptr. Roger Capili | AG31: FALSE | AH31: FALSE | AI31: TRUE | AJ31: FALSE | BG31: =COUNTIF(AG31:BF31,"P") -> 0
D32: 23 | E32: 46222 | G32: Ladrido | H32: Athynah Ruchie | J32: =IF(AND(H32="",G32=""),"",CONCATENATE(G32,", ",H32)) -> Ladrido, Athynah Ruchie | K32: Female | R32: =IF(Q32="","",DATEDIF(Q32,TODAY(),"Y")) | V32: Ptr. Roger Capili | AG32: FALSE | AH32: FALSE | AI32: TRUE | AJ32: FALSE | BG32: =COUNTIF(AG32:BF32,"P") -> 0
D33: 24 | E33: 46222 | F33: AMM | G33: Palomara | H33: Ptr. Raynon | J33: =IF(AND(H33="",G33=""),"",CONCATENATE(G33,", ",H33)) -> Palomara, Ptr. Raynon | K33: Male | R33: =IF(Q33="","",DATEDIF(Q33,TODAY(),"Y")) | AG33: FALSE | AH33: FALSE | AI33: TRUE | AJ33: FALSE | BG33: =COUNTIF(AG33:BF33,"P") -> 0
D34: 25 | E34: 46222 | F34: LM | G34: Palomara | H34: Jovilyn | J34: =IF(AND(H34="",G34=""),"",CONCATENATE(G34,", ",H34)) -> Palomara, Jovilyn | K34: Female | R34: =IF(Q34="","",DATEDIF(Q34,TODAY(),"Y")) | AG34: FALSE | AH34: FALSE | AI34: TRUE | AJ34: FALSE | BG34: =COUNTIF(AG34:BF34,"P") -> 0
D35: 26 | E35: 46222 | G35: Palomara | H35: Cristel May | J35: =IF(AND(H35="",G35=""),"",CONCATENATE(G35,", ",H35)) -> Palomara, Cristel May | K35: Female | R35: =IF(Q35="","",DATEDIF(Q35,TODAY(),"Y")) | AG35: FALSE | AH35: FALSE | AI35: TRUE | AJ35: FALSE | BG35: =COUNTIF(AG35:BF35,"P") -> 0
D36: 27 | E36: 46222 | G36: Palomara | H36: Gabrielle | J36: =IF(AND(H36="",G36=""),"",CONCATENATE(G36,", ",H36)) -> Palomara, Gabrielle | K36: Female | R36: =IF(Q36="","",DATEDIF(Q36,TODAY(),"Y")) | V36: Ptr. Raynon Palomara | AG36: FALSE | AH36: FALSE | AI36: TRUE | AJ36: FALSE | BG36: =COUNTIF(AG36:BF36,"P") -> 0
D37: 28 | E37: 46222 | G37: Palomara | H37: Ray Arden | J37: =IF(AND(H37="",G37=""),"",CONCATENATE(G37,", ",H37)) -> Palomara, Ray Arden | K37: Male | R37: =IF(Q37="","",DATEDIF(Q37,TODAY(),"Y")) | V37: Ptr. Raynon Palomara | AG37: FALSE | AH37: FALSE | AI37: TRUE | AJ37: FALSE | BG37: =COUNTIF(AG37:BF37,"P") -> 0
D38: 29 | J38: =IF(AND(H38="",G38=""),"",CONCATENATE(G38,", ",H38)) | R38: =IF(Q38="","",DATEDIF(Q38,TODAY(),"Y")) | AG38: FALSE | AH38: FALSE | AI38: FALSE | AJ38: FALSE | BG38: =COUNTIF(AG38:BF38,"P") -> 0
D39: 30 | J39: =IF(AND(H39="",G39=""),"",CONCATENATE(G39,", ",H39)) | R39: =IF(Q39="","",DATEDIF(Q39,TODAY(),"Y")) | AG39: FALSE | AH39: FALSE | AI39: FALSE | AJ39: FALSE | BG39: =COUNTIF(AG39:BF39,"P") -> 0
D40: 31 | J40: =IF(AND(H40="",G40=""),"",CONCATENATE(G40,", ",H40)) | R40: =IF(Q40="","",DATEDIF(Q40,TODAY(),"Y")) | AG40: FALSE | AH40: FALSE | AI40: FALSE | AJ40: FALSE | BG40: =COUNTIF(AG40:BF40,"P") -> 0
D41: 32 | J41: =IF(AND(H41="",G41=""),"",CONCATENATE(G41,", ",H41)) | R41: =IF(Q41="","",DATEDIF(Q41,TODAY(),"Y")) | AG41: FALSE | AH41: FALSE | AI41: FALSE | AJ41: FALSE | BG41: =COUNTIF(AG41:BF41,"P") -> 0
D42: 33 | J42: =IF(AND(H42="",G42=""),"",CONCATENATE(G42,", ",H42)) | R42: =IF(Q42="","",DATEDIF(Q42,TODAY(),"Y")) | AG42: FALSE | AH42: FALSE | AI42: FALSE | AJ42: FALSE | BG42: =COUNTIF(AG42:BF42,"P") -> 0
D43: 34 | J43: =IF(AND(H43="",G43=""),"",CONCATENATE(G43,", ",H43)) | R43: =IF(Q43="","",DATEDIF(Q43,TODAY(),"Y")) | AG43: FALSE | AH43: FALSE | AI43: FALSE | AJ43: FALSE | BG43: =COUNTIF(AG43:BF43,"P") -> 0
D44: 35 | J44: =IF(AND(H44="",G44=""),"",CONCATENATE(G44,", ",H44)) | R44: =IF(Q44="","",DATEDIF(Q44,TODAY(),"Y")) | AG44: FALSE | AH44: FALSE | AI44: FALSE | AJ44: FALSE | BG44: =COUNTIF(AG44:BF44,"P") -> 0
D45: 36 | J45: =IF(AND(H45="",G45=""),"",CONCATENATE(G45,", ",H45)) | R45: =IF(Q45="","",DATEDIF(Q45,TODAY(),"Y")) | AG45: FALSE | AH45: FALSE | AI45: FALSE | AJ45: FALSE | BG45: =COUNTIF(AG45:BF45,"P") -> 0
D46: 37 | J46: =IF(AND(H46="",G46=""),"",CONCATENATE(G46,", ",H46)) | R46: =IF(Q46="","",DATEDIF(Q46,TODAY(),"Y")) | AG46: FALSE | AH46: FALSE | AI46: FALSE | AJ46: FALSE | BG46: =COUNTIF(AG46:BF46,"P") -> 0
D47: 38 | J47: =IF(AND(H47="",G47=""),"",CONCATENATE(G47,", ",H47)) | R47: =IF(Q47="","",DATEDIF(Q47,TODAY(),"Y")) | AG47: FALSE | AH47: FALSE | AI47: FALSE | AJ47: FALSE | BG47: =COUNTIF(AG47:BF47,"P") -> 0
D48: 39 | J48: =IF(AND(H48="",G48=""),"",CONCATENATE(G48,", ",H48)) | R48: =IF(Q48="","",DATEDIF(Q48,TODAY(),"Y")) | AG48: FALSE | AH48: FALSE | AI48: FALSE | AJ48: FALSE | BG48: =COUNTIF(AG48:BF48,"P") -> 0
D49: 40 | J49: =IF(AND(H49="",G49=""),"",CONCATENATE(G49,", ",H49)) | R49: =IF(Q49="","",DATEDIF(Q49,TODAY(),"Y")) | AG49: FALSE | AH49: FALSE | AI49: FALSE | AJ49: FALSE | BG49: =COUNTIF(AG49:BF49,"P") -> 0
... D209: 200 | J209: =IF(AND(H209="",G209=""),"",CONCATENATE(G209,", ",H209)) | R209: =IF(Q209="","",DATEDIF(Q209,TODAY(),"Y")) | AG209: FALSE | AH209: FALSE | AI209: FALSE | AJ209: FALSE | BG209: =COUNTIF(AG209:BF209,"P") -> 0
D210: 201 | J210: =IF(AND(H210="",G210=""),"",CONCATENATE(G210,", ",H210)) | R210: =IF(Q210="","",DATEDIF(Q210,TODAY(),"Y")) | BG210: =COUNTIF(AG210:BF210,"P") -> 0
D211: 202 | J211: =IF(AND(H211="",G211=""),"",CONCATENATE(G211,", ",H211)) | R211: =IF(Q211="","",DATEDIF(Q211,TODAY(),"Y")) | BG211: =COUNTIF(AG211:BF211,"P") -> 0
D212: 203 | J212: =IF(AND(H212="",G212=""),"",CONCATENATE(G212,", ",H212)) | R212: =IF(Q212="","",DATEDIF(Q212,TODAY(),"Y")) | BG212: =COUNTIF(AG212:BF212,"P") -> 0
D213: 204 | J213: =IF(AND(H213="",G213=""),"",CONCATENATE(G213,", ",H213)) | R213: =IF(Q213="","",DATEDIF(Q213,TODAY(),"Y")) | BG213: =COUNTIF(AG213:BF213,"P") -> 0
D214: 205 | J214: =IF(AND(H214="",G214=""),"",CONCATENATE(G214,", ",H214)) | R214: =IF(Q214="","",DATEDIF(Q214,TODAY(),"Y")) | BG214: =COUNTIF(AG214:BF214,"P") -> 0
D215: 206 | J215: =IF(AND(H215="",G215=""),"",CONCATENATE(G215,", ",H215)) | R215: =IF(Q215="","",DATEDIF(Q215,TODAY(),"Y")) | BG215: =COUNTIF(AG215:BF215,"P") -> 0
D216: 207 | J216: =IF(AND(H216="",G216=""),"",CONCATENATE(G216,", ",H216)) | R216: =IF(Q216="","",DATEDIF(Q216,TODAY(),"Y")) | BG216: =COUNTIF(AG216:BF216,"P") -> 0
D217: 208 | J217: =IF(AND(H217="",G217=""),"",CONCATENATE(G217,", ",H217)) | R217: =IF(Q217="","",DATEDIF(Q217,TODAY(),"Y")) | BG217: =COUNTIF(AG217:BF217,"P") -> 0
D218: 209 | J218: =IF(AND(H218="",G218=""),"",CONCATENATE(G218,", ",H218)) | R218: =IF(Q218="","",DATEDIF(Q218,TODAY(),"Y")) | BG218: =COUNTIF(AG218:BF218,"P") -> 0
D219: 210 | J219: =IF(AND(H219="",G219=""),"",CONCATENATE(G219,", ",H219)) | R219: =IF(Q219="","",DATEDIF(Q219,TODAY(),"Y")) | BG219: =COUNTIF(AG219:BF219,"P") -> 0
D220: 211 | J220: =IF(AND(H220="",G220=""),"",CONCATENATE(G220,", ",H220)) | R220: =IF(Q220="","",DATEDIF(Q220,TODAY(),"Y")) | BG220: =COUNTIF(AG220:BF220,"P") -> 0
D221: 212 | J221: =IF(AND(H221="",G221=""),"",CONCATENATE(G221,", ",H221)) | R221: =IF(Q221="","",DATEDIF(Q221,TODAY(),"Y")) | BG221: =COUNTIF(AG221:BF221,"P") -> 0
... D352: 343 | J352: =IF(AND(H352="",G352=""),"",CONCATENATE(G352,", ",H352)) | R352: =IF(Q352="","",DATEDIF(Q352,TODAY(),"Y")) | BG352: =COUNTIF(AG352:BF352,"P") -> 0

Sheet dropdown list
B2: COMPLETED FORM | C2: Status | D2: Youth CG | E2: LM CG | F2: AMM CG | H2: GENDER | I2: CITY ADDRESS | J2: BAPTIZED
B3: No | C3: Active | D3: Abraham | E3: Almond | F3: Benjamin | H3: Male | I3: Alapang, La Trinidad | J3: No
B4: Yes | C4: Bible Study | D4: David | E4: Cedar | F4: Levi | H4: Female | I4: Ambiong Central, La Trinidad | J4: Yes
C5: Inactive | D5: Elijah | E5: Juniper | F5: Judah | I5: Ambiong, La Trinidad
C6: Other Church | D6: Elisha | E6: Palm | F6: Issachar | I6: Andres Bonifacio
C7: Sunday Goer | D7: Isaac | E7: Sycamore | F7: Dan | I7: Apugan, Sto. Tomas
D8: Jacob | E8: Hazelnut | F8: Joseph | I8: Asin Road
D9: Joseph | E9: Oak | F9: Reuben | I9: Aurora Hill
D10: Joshua | E10: Olive | I10: Bakakeng Central
D11: Moses | E11: Pomegranate | I11: Bakakeng Norte
D12: Paul | E12: Mulberry | I12: Bakakeng Sur
D13: Samuel | E13: Tamarisk | I13: Balsigan Rd
D14: Timothy | E14: Chestnut | I14: Beckel, La Trinidad
E15: Acacia | I15: Betag, La Trinidad
I16: Bineng, La Trinidad
I17: Camp 7
D18: Youth CG Position | E18: LM CG Position | F18: AMM CG Position | I18: Central Ambiong, La Trinidad
D19: Member | E19: Member | F19: Member | I19: Central Balili, La Trinidad
D20: Leader | E20: Leader | F20: Leader | I20: Central Fairview
D21: Assistant Leader | E21: Assistant Leader | F21: Assistant Leader | I21: Central Tawang, La Trinidad
E22: Secretary | I22: Cresencia Village
I23: Daclan, Tublay
I24: Dominican Hill
I25: Dreamland
I26: Fairview
I27: Gibraltar
I28: Goldfield, Itogon
I29: Green Valley
I30: Green Valley Village
I31: Guisad
I32: Guisad Central
I33: Guisad Surong
I34: Hangar Market
... I85: Zamora St

Sheet Youth masterlist - 12 CG
A1: Completed Form | B1: Status | C1: Cell Group | D1: CG Position | E1: Full Name | F1: First Name | G1: Last Name | H1: Middle Initial | I1: Street | J1: City Address | K1: Provincial Address | L1: Contact Number | M1: Email | N1: Birthdate | O1: Birthplace | P1: Father | Q1: Mother | R1: Age
A2: Yes | B2: Active | C2: 10th CG | D2: Members | E2: =_xlfn.CONCAT(F2," ",G2) -> Jeehan Jane Castillejo | F2: Jeehan Jane | G2: Castillejo | H2: T | I2: Avelino St | J2: Andres Bonifacio | K2: Dist. 2 San Manuel Isabela | L2: 0975-688-2492 | M2: jeehanjanecastillejo@gmail.com | N2: 35796 | R2: =(TODAY()-N2)/365 -> 28.835616
A3: Yes | B3: Active | C3: 10th CG | D3: 2 Assistant | E3: =_xlfn.CONCAT(F3," ",G3) -> Arabea Bless Taloban | F3: Arabea Bless | G3: Taloban | H3: M | I3: 8 Avelino St | J3: Andres Bonifacio | L3: 0999-574-5811 | M3: arbytaloban05@gmail.com | N3: 38867 | R3: =(TODAY()-N3)/365 -> 20.421918
A4: No | B4: Active | C4: 10th CG | D4: Members | E4: =_xlfn.CONCAT(F4," ",G4) -> Lindsay Dagupen | F4: Lindsay Dagupen
A5: No | B5: Active | C5: 10th CG | D5: 1 Leader | E5: =_xlfn.CONCAT(F5," ",G5) -> Journey Ryan Bañez | F5: Journey Ryan | G5: Bañez
A6: No | B6: Active | C6: 12th CG | D6: Members | E6: =_xlfn.CONCAT(F6," ",G6) -> Chalisa Jasmine Tacbas | F6: Chalisa Jasmine | G6: Tacbas
A7: No | B7: Bible Study | C7: 10th CG | D7: Members | E7: =_xlfn.CONCAT(F7," ",G7) -> Lovely Donaire | F7: Lovely | G7: Donaire
A8: No | B8: Inactive | C8: 10th CG | D8: Members | E8: =_xlfn.CONCAT(F8," ",G8) -> Ivan Gayados | F8: Ivan Gayados
A9: No | B9: Inactive | C9: 10th CG | D9: Members | E9: =_xlfn.CONCAT(F9," ",G9) -> Frederick Mago | F9: Frederick Mago
A10: No | B10: Other Church | C10: 10th CG | D10: Members | E10: =_xlfn.CONCAT(F10," ",G10) -> Mark Roston Mamolang | F10: Mark Roston | G10: Mamolang
A11: Yes | B11: Sunday Goer | C11: 10th CG | D11: Members | E11: =_xlfn.CONCAT(F11," ",G11) -> Kurt Rhanz Gabryl Pacsi | F11: Kurt Rhanz Gabryl | G11: Pacsi | H11: R | I11: 54 A | J11: Dapiting Alapang | N11: 40140 | R11: =(TODAY()-N11)/365 -> 16.934247
A12: No | B12: Sunday Goer | C12: 10th CG | D12: Members | E12: =_xlfn.CONCAT(F12," ",G12) -> Grant De Guzman | F12: Grant De Guzman
A13: No | B13: Sunday Goer | C13: 10th CG | D13: Members | E13: =_xlfn.CONCAT(F13," ",G13) -> Sandy De Guzman | F13: Sandy De Guzman
